Workbook
Name Scenario: 'Scenarios'!$C$4
Name Revenue_2026E: 'Income Statement'!$G$7
Name NI_Parent_2026E: 'Income Statement'!$G$68
Name EPS_2026E: 'Income Statement'!$G$75
Name UFCF_2026E: 'DCF Inputs'!$G$15
Name Revenue_2027E: 'Income Statement'!$H$7
Name NI_Parent_2027E: 'Income Statement'!$H$68
Name EPS_2027E: 'Income Statement'!$H$75
Name UFCF_2027E: 'DCF Inputs'!$H$15
Name Revenue_2028E: 'Income Statement'!$I$7
Name NI_Parent_2028E: 'Income Statement'!$I$68
Name EPS_2028E: 'Income Statement'!$I$75
Name UFCF_2028E: 'DCF Inputs'!$I$15
Name Revenue_2029E: 'Income Statement'!$J$7
Name NI_Parent_2029E: 'Income Statement'!$J$68
Name EPS_2029E: 'Income Statement'!$J$75
Name UFCF_2029E: 'DCF Inputs'!$J$15
Name Revenue_2030E: 'Income Statement'!$K$7
Name NI_Parent_2030E: 'Income Statement'!$K$68
Name EPS_2030E: 'Income Statement'!$K$75
Name UFCF_2030E: 'DCF Inputs'!$K$15
Name NetDebt_2025A: 'DCF Inputs'!$F$21
Name Minority_BV_2025A: 'DCF Inputs'!$F$22
Name Shares: 'DCF Inputs'!$F$26
Name Price: 'DCF Inputs'!$F$30

Sheet Cover
A1: 中国核电（601985.SH）财务模型
A2: Financial Model — China National Nuclear Power Co., Ltd.
A3: 编制日期 | B3: 2026-10-02（initiating-coverage · Task 2）
A4: 当前情景 | B4: =Scenarios!D4 -> Base 基准
A5: 单位 | B5: 亿元人民币（另有注明除外）；电量 亿千瓦时；装机 万千瓦；电价 元/千瓦时（含增值税）
A6: 历史期 | B6: 2022A–2025A：2023 年年报（2022、2023）与 2025 年年报（2024、2025）合并报表；2026H1A 见利润表 M 列
A7: 预测期 | B7: 2026E–2030E：公式驱动；所有情景假设在 Scenarios 工作表（C4 切换），其余假设以蓝色输入列示在各表行内
A8: 颜色规范 | B8: 蓝色=硬编码输入/历史数据；黑色=公式；绿色=跨表链接；灰底=历史期
A9: 平衡机制 | B9: 长期借款为平衡项：净借款使期末现金=目标现金（收入×18%）；利息按期初有息负债计提，无循环引用
A10: 工作表 | B10: Task 2：Revenue Model｜Income Statement｜Cash Flow｜Balance Sheet｜Scenarios｜DCF Inputs；Task 3：DCF｜Sensitivity｜Comps｜Precedents｜Valuation Summary；Checks｜Hist_Data
A11: 目标价（元，12 个月） | B11: ='Valuation Summary'!C12 -> 8
A12: 评级 | B12: ='Valuation Summary'!C17 -> 减持 SELL
A13: 数据来源 | B13: CNNP_601985/source/：CNNP_2023_年报.pdf、CNNP_2025_年报.pdf、CNNP_2026H1_半年报.pdf；行业及股价数据见 Task 1 研究文档
A14: 重要局限 | B14: ①2022–23A 与 2024–25A 成本分析表口径不同；②核电/新能源分产品收入为上网电量×综合电价推算；③2024 年末风光装机拆分为估算；④分地区 2022A/2024A 按同比倒推；⑤新机组造价按预算/容量，庄河、金七门 3–4 号为估计
A15: 校验 | B15: =IF(Checks!C18,"全部校验通过 ✔","存在未通过校验 ✘ — 见 Checks") -> 全部校验通过 ✔

Sheet Revenue Model
A1: 收入模型 Revenue Model — 中国核电 601985.SH
A2: 单位：亿元人民币（另有注明除外）｜蓝色=硬编码输入 黑色=公式 绿色=跨表链接｜A=实际 E=预测
A3: 项目 / Line item | B3: 单位 | C3: 2022 | D3: 2023 | E3: 2024 | F3: 2025 | G3: 2026 | H3: 2027 | I3: 2028 | J3: 2029 | K3: 2030 | L3: 来源 / 说明
A6: A. 核电机组投产计划 Nuclear pipeline（年报 2025 第 17、33 页；2026 半年报第 11 页）
A7: 机组 Unit | B7: 区域 | C7: 容量 万kW | D7: 计划商运年 | E7: 情景商运年 | F7: 单位造价 元/kW | G7: ← 各年平均装机贡献（万千瓦） 2026E–2030E → | L7: 预算/说明
A8: 田湾 7 号 | B8: 华东 | C8: 126.5 | D8: 2026 | E8: =D8+'Scenarios'!$G$24 -> 2026 | F8: 20011 | G8: =IF(G$3>$E8,$C8,IF(G$3=$E8,$C8*'Scenarios'!G$30,0)) -> 50.6 | H8: =IF(H$3>$E8,$C8,IF(H$3=$E8,$C8*'Scenarios'!H$30,0)) -> 126.5 | I8: =IF(I$3>$E8,$C8,IF(I$3=$E8,$C8*'Scenarios'!I$30,0)) -> 126.5 | J8: =IF(J$3>$E8,$C8,IF(J$3=$E8,$C8*'Scenarios'!J$30,0)) -> 126.5 | K8: =IF(K$3>$E8,$C8,IF(K$3=$E8,$C8*'Scenarios'!K$30,0)) -> 126.5 | L8: 田湾 7、8 号预算 506.29 亿；2026-08 首次装料
A9: 海南小堆 玲龙一号 | B9: 华南 | C9: 12.5 | D9: 2026 | E9: =D9+'Scenarios'!$G$24 -> 2026 | F9: 30120 | G9: =IF(G$3>$E9,$C9,IF(G$3=$E9,$C9*'Scenarios'!G$30,0)) -> 5 | H9: =IF(H$3>$E9,$C9,IF(H$3=$E9,$C9*'Scenarios'!H$30,0)) -> 12.5 | I9: =IF(I$3>$E9,$C9,IF(I$3=$E9,$C9*'Scenarios'!I$30,0)) -> 12.5 | J9: =IF(J$3>$E9,$C9,IF(J$3=$E9,$C9*'Scenarios'!J$30,0)) -> 12.5 | K9: =IF(K$3>$E9,$C9,IF(K$3=$E9,$C9*'Scenarios'!K$30,0)) -> 12.5 | L9: 预算 37.65 亿；全球首个陆上商用 SMR
A10: 徐大堡 3 号 | B10: 东北 | C10: 127.4 | D10: 2027 | E10: =D10+'Scenarios'!$G$24 -> 2027 | F10: 20544 | G10: =IF(G$3>$E10,$C10,IF(G$3=$E10,$C10*'Scenarios'!G$30,0)) -> 0 | H10: =IF(H$3>$E10,$C10,IF(H$3=$E10,$C10*'Scenarios'!H$30,0)) -> 50.96 | I10: =IF(I$3>$E10,$C10,IF(I$3=$E10,$C10*'Scenarios'!I$30,0)) -> 127.4 | J10: =IF(J$3>$E10,$C10,IF(J$3=$E10,$C10*'Scenarios'!J$30,0)) -> 127.4 | K10: =IF(K$3>$E10,$C10,IF(K$3=$E10,$C10*'Scenarios'!K$30,0)) -> 127.4 | L10: 徐大堡 3、4 号预算 523.47 亿
A11: 三门 3 号 | B11: 华东 | C11: 125.1 | D11: 2027 | E11: =D11+'Scenarios'!$G$24 -> 2027 | F11: 18455 | G11: =IF(G$3>$E11,$C11,IF(G$3=$E11,$C11*'Scenarios'!G$30,0)) -> 0 | H11: =IF(H$3>$E11,$C11,IF(H$3=$E11,$C11*'Scenarios'!H$30,0)) -> 50.04 | I11: =IF(I$3>$E11,$C11,IF(I$3=$E11,$C11*'Scenarios'!I$30,0)) -> 125.1 | J11: =IF(J$3>$E11,$C11,IF(J$3=$E11,$C11*'Scenarios'!J$30,0)) -> 125.1 | K11: =IF(K$3>$E11,$C11,IF(K$3=$E11,$C11*'Scenarios'!K$30,0)) -> 125.1 | L11: 三门 3、4 号预算 461.75 亿
A12: 田湾 8 号 | B12: 华东 | C12: 126.5 | D12: 2027 | E12: =D12+'Scenarios'!$G$24 -> 2027 | F12: 20011 | G12: =IF(G$3>$E12,$C12,IF(G$3=$E12,$C12*'Scenarios'!G$30,0)) -> 0 | H12: =IF(H$3>$E12,$C12,IF(H$3=$E12,$C12*'Scenarios'!H$30,0)) -> 50.6 | I12: =IF(I$3>$E12,$C12,IF(I$3=$E12,$C12*'Scenarios'!I$30,0)) -> 126.5 | J12: =IF(J$3>$E12,$C12,IF(J$3=$E12,$C12*'Scenarios'!J$30,0)) -> 126.5 | K12: =IF(K$3>$E12,$C12,IF(K$3=$E12,$C12*'Scenarios'!K$30,0)) -> 126.5 | L12: 2026H1 启动冷试
A13: 三门 4 号 | B13: 华东 | C13: 125.1 | D13: 2027 | E13: =D13+'Scenarios'!$G$24 -> 2027 | F13: 18455 | G13: =IF(G$3>$E13,$C13,IF(G$3=$E13,$C13*'Scenarios'!G$30,0)) -> 0 | H13: =IF(H$3>$E13,$C13,IF(H$3=$E13,$C13*'Scenarios'!H$30,0)) -> 50.04 | I13: =IF(I$3>$E13,$C13,IF(I$3=$E13,$C13*'Scenarios'!I$30,0)) -> 125.1 | J13: =IF(J$3>$E13,$C13,IF(J$3=$E13,$C13*'Scenarios'!J$30,0)) -> 125.1 | K13: =IF(K$3>$E13,$C13,IF(K$3=$E13,$C13*'Scenarios'!K$30,0)) -> 125.1
A14: 徐大堡 1 号 | B14: 东北 | C14: 129.1 | D14: 2028 | E14: =D14+'Scenarios'!$G$24 -> 2028 | F14: 16339 | G14: =IF(G$3>$E14,$C14,IF(G$3=$E14,$C14*'Scenarios'!G$30,0)) -> 0 | H14: =IF(H$3>$E14,$C14,IF(H$3=$E14,$C14*'Scenarios'!H$30,0)) -> 0 | I14: =IF(I$3>$E14,$C14,IF(I$3=$E14,$C14*'Scenarios'!I$30,0)) -> 51.64 | J14: =IF(J$3>$E14,$C14,IF(J$3=$E14,$C14*'Scenarios'!J$30,0)) -> 129.1 | K14: =IF(K$3>$E14,$C14,IF(K$3=$E14,$C14*'Scenarios'!K$30,0)) -> 129.1 | L14: 徐大堡 1、2 号预算 421.88 亿
A15: 徐大堡 4 号 | B15: 东北 | C15: 127.4 | D15: 2028 | E15: =D15+'Scenarios'!$G$24 -> 2028 | F15: 20544 | G15: =IF(G$3>$E15,$C15,IF(G$3=$E15,$C15*'Scenarios'!G$30,0)) -> 0 | H15: =IF(H$3>$E15,$C15,IF(H$3=$E15,$C15*'Scenarios'!H$30,0)) -> 0 | I15: =IF(I$3>$E15,$C15,IF(I$3=$E15,$C15*'Scenarios'!I$30,0)) -> 50.96 | J15: =IF(J$3>$E15,$C15,IF(J$3=$E15,$C15*'Scenarios'!J$30,0)) -> 127.4 | K15: =IF(K$3>$E15,$C15,IF(K$3=$E15,$C15*'Scenarios'!K$30,0)) -> 127.4
A16: 漳州 3 号 | B16: 华东 | C16: 121.2 | D16: 2029 | E16: =D16+'Scenarios'!$G$24 -> 2029 | F16: 16362 | G16: =IF(G$3>$E16,$C16,IF(G$3=$E16,$C16*'Scenarios'!G$30,0)) -> 0 | H16: =IF(H$3>$E16,$C16,IF(H$3=$E16,$C16*'Scenarios'!H$30,0)) -> 0 | I16: =IF(I$3>$E16,$C16,IF(I$3=$E16,$C16*'Scenarios'!I$30,0)) -> 0 | J16: =IF(J$3>$E16,$C16,IF(J$3=$E16,$C16*'Scenarios'!J$30,0)) -> 48.48 | K16: =IF(K$3>$E16,$C16,IF(K$3=$E16,$C16*'Scenarios'!K$30,0)) -> 121.2 | L16: 漳州 3、4 号预算 396.62 亿
A17: 徐大堡 2 号 | B17: 东北 | C17: 129.1 | D17: 2029 | E17: =D17+'Scenarios'!$G$24 -> 2029 | F17: 16339 | G17: =IF(G$3>$E17,$C17,IF(G$3=$E17,$C17*'Scenarios'!G$30,0)) -> 0 | H17: =IF(H$3>$E17,$C17,IF(H$3=$E17,$C17*'Scenarios'!H$30,0)) -> 0 | I17: =IF(I$3>$E17,$C17,IF(I$3=$E17,$C17*'Scenarios'!I$30,0)) -> 0 | J17: =IF(J$3>$E17,$C17,IF(J$3=$E17,$C17*'Scenarios'!J$30,0)) -> 51.64 | K17: =IF(K$3>$E17,$C17,IF(K$3=$E17,$C17*'Scenarios'!K$30,0)) -> 129.1
A18: 漳州 4 号 | B18: 华东 | C18: 121.2 | D18: 2029 | E18: =D18+'Scenarios'!$G$24 -> 2029 | F18: 16362 | G18: =IF(G$3>$E18,$C18,IF(G$3=$E18,$C18*'Scenarios'!G$30,0)) -> 0 | H18: =IF(H$3>$E18,$C18,IF(H$3=$E18,$C18*'Scenarios'!H$30,0)) -> 0 | I18: =IF(I$3>$E18,$C18,IF(I$3=$E18,$C18*'Scenarios'!I$30,0)) -> 0 | J18: =IF(J$3>$E18,$C18,IF(J$3=$E18,$C18*'Scenarios'!J$30,0)) -> 48.48 | K18: =IF(K$3>$E18,$C18,IF(K$3=$E18,$C18*'Scenarios'!K$30,0)) -> 121.2
A19: 金七门 1 号 | B19: 华东 | C19: 121.5 | D19: 2030 | E19: =D19+'Scenarios'!$G$24 -> 2030 | F19: 18343 | G19: =IF(G$3>$E19,$C19,IF(G$3=$E19,$C19*'Scenarios'!G$30,0)) -> 0 | H19: =IF(H$3>$E19,$C19,IF(H$3=$E19,$C19*'Scenarios'!H$30,0)) -> 0 | I19: =IF(I$3>$E19,$C19,IF(I$3=$E19,$C19*'Scenarios'!I$30,0)) -> 0 | J19: =IF(J$3>$E19,$C19,IF(J$3=$E19,$C19*'Scenarios'!J$30,0)) -> 0 | K19: =IF(K$3>$E19,$C19,IF(K$3=$E19,$C19*'Scenarios'!K$30,0)) -> 48.6 | L19: 金七门 1、2 号预算 445.74 亿
A20: 徐圩 1 号 | B20: 华东 | C20: 122.2 | D20: 2031 | E20: =D20+'Scenarios'!$G$24 -> 2031 | F20: 23183 | G20: =IF(G$3>$E20,$C20,IF(G$3=$E20,$C20*'Scenarios'!G$30,0)) -> 0 | H20: =IF(H$3>$E20,$C20,IF(H$3=$E20,$C20*'Scenarios'!H$30,0)) -> 0 | I20: =IF(I$3>$E20,$C20,IF(I$3=$E20,$C20*'Scenarios'!I$30,0)) -> 0 | J20: =IF(J$3>$E20,$C20,IF(J$3=$E20,$C20*'Scenarios'!J$30,0)) -> 0 | K20: =IF(K$3>$E20,$C20,IF(K$3=$E20,$C20*'Scenarios'!K$30,0)) -> 0 | L20: 徐圩一期预算 719.61 亿（含高温堆，310.4 万kW）
A21: 金七门 2 号 | B21: 华东 | C21: 121.5 | D21: 2031 | E21: =D21+'Scenarios'!$G$24 -> 2031 | F21: 18343 | G21: =IF(G$3>$E21,$C21,IF(G$3=$E21,$C21*'Scenarios'!G$30,0)) -> 0 | H21: =IF(H$3>$E21,$C21,IF(H$3=$E21,$C21*'Scenarios'!H$30,0)) -> 0 | I21: =IF(I$3>$E21,$C21,IF(I$3=$E21,$C21*'Scenarios'!I$30,0)) -> 0 | J21: =IF(J$3>$E21,$C21,IF(J$3=$E21,$C21*'Scenarios'!J$30,0)) -> 0 | K21: =IF(K$3>$E21,$C21,IF(K$3=$E21,$C21*'Scenarios'!K$30,0)) -> 0 | L21: 2026-04 FCD；计划商运年为作者估计
A22: 三门 6 号 | B22: 华东 | C22: 121.5 | D22: 2031 | E22: =D22+'Scenarios'!$G$24 -> 2031 | F22: 16675 | G22: =IF(G$3>$E22,$C22,IF(G$3=$E22,$C22*'Scenarios'!G$30,0)) -> 0 | H22: =IF(H$3>$E22,$C22,IF(H$3=$E22,$C22*'Scenarios'!H$30,0)) -> 0 | I22: =IF(I$3>$E22,$C22,IF(I$3=$E22,$C22*'Scenarios'!I$30,0)) -> 0 | J22: =IF(J$3>$E22,$C22,IF(J$3=$E22,$C22*'Scenarios'!J$30,0)) -> 0 | K22: =IF(K$3>$E22,$C22,IF(K$3=$E22,$C22*'Scenarios'!K$30,0)) -> 0 | L22: 公司披露：计划 2031-10 建成
A23: 三门 5 号 | B23: 华东 | C23: 121.5 | D23: 2032 | E23: =D23+'Scenarios'!$G$24 -> 2032 | F23: 16675 | G23: =IF(G$3>$E23,$C23,IF(G$3=$E23,$C23*'Scenarios'!G$30,0)) -> 0 | H23: =IF(H$3>$E23,$C23,IF(H$3=$E23,$C23*'Scenarios'!H$30,0)) -> 0 | I23: =IF(I$3>$E23,$C23,IF(I$3=$E23,$C23*'Scenarios'!I$30,0)) -> 0 | J23: =IF(J$3>$E23,$C23,IF(J$3=$E23,$C23*'Scenarios'!J$30,0)) -> 0 | K23: =IF(K$3>$E23,$C23,IF(K$3=$E23,$C23*'Scenarios'!K$30,0)) -> 0 | L23: 公司披露：计划 2032-08 建成
A24: 徐圩 2 号 + 高温堆 | B24: 华东 | C24: 188.2 | D24: 2032 | E24: =D24+'Scenarios'!$G$24 -> 2032 | F24: 23183 | G24: =IF(G$3>$E24,$C24,IF(G$3=$E24,$C24*'Scenarios'!G$30,0)) -> 0 | H24: =IF(H$3>$E24,$C24,IF(H$3=$E24,$C24*'Scenarios'!H$30,0)) -> 0 | I24: =IF(I$3>$E24,$C24,IF(I$3=$E24,$C24*'Scenarios'!I$30,0)) -> 0 | J24: =IF(J$3>$E24,$C24,IF(J$3=$E24,$C24*'Scenarios'!J$30,0)) -> 0 | K24: =IF(K$3>$E24,$C24,IF(K$3=$E24,$C24*'Scenarios'!K$30,0)) -> 0 | L24: 计划商运年为作者估计
A25: 庄河 1 号 | B25: 东北 | C25: 125 | D25: 2032 | E25: =D25+'Scenarios'!$G$24 -> 2032 | F25: 18000 | G25: =IF(G$3>$E25,$C25,IF(G$3=$E25,$C25*'Scenarios'!G$30,0)) -> 0 | H25: =IF(H$3>$E25,$C25,IF(H$3=$E25,$C25*'Scenarios'!H$30,0)) -> 0 | I25: =IF(I$3>$E25,$C25,IF(I$3=$E25,$C25*'Scenarios'!I$30,0)) -> 0 | J25: =IF(J$3>$E25,$C25,IF(J$3=$E25,$C25*'Scenarios'!J$30,0)) -> 0 | K25: =IF(K$3>$E25,$C25,IF(K$3=$E25,$C25*'Scenarios'!K$30,0)) -> 0 | L25: 2026-07-31 核准；造价、商运年为作者估计
A26: 庄河 2 号 | B26: 东北 | C26: 125 | D26: 2033 | E26: =D26+'Scenarios'!$G$24 -> 2033 | F26: 18000 | G26: =IF(G$3>$E26,$C26,IF(G$3=$E26,$C26*'Scenarios'!G$30,0)) -> 0 | H26: =IF(H$3>$E26,$C26,IF(H$3=$E26,$C26*'Scenarios'!H$30,0)) -> 0 | I26: =IF(I$3>$E26,$C26,IF(I$3=$E26,$C26*'Scenarios'!I$30,0)) -> 0 | J26: =IF(J$3>$E26,$C26,IF(J$3=$E26,$C26*'Scenarios'!J$30,0)) -> 0 | K26: =IF(K$3>$E26,$C26,IF(K$3=$E26,$C26*'Scenarios'!K$30,0)) -> 0
A27: 金七门 3 号 | B27: 华东 | C27: 123 | D27: 2032 | E27: =D27+'Scenarios'!$G$24 -> 2032 | F27: 18000 | G27: =IF(G$3>$E27,$C27,IF(G$3=$E27,$C27*'Scenarios'!G$30,0)) -> 0 | H27: =IF(H$3>$E27,$C27,IF(H$3=$E27,$C27*'Scenarios'!H$30,0)) -> 0 | I27: =IF(I$3>$E27,$C27,IF(I$3=$E27,$C27*'Scenarios'!I$30,0)) -> 0 | J27: =IF(J$3>$E27,$C27,IF(J$3=$E27,$C27*'Scenarios'!J$30,0)) -> 0 | K27: =IF(K$3>$E27,$C27,IF(K$3=$E27,$C27*'Scenarios'!K$30,0)) -> 0 | L27: 2026-07-31 核准；造价、商运年为作者估计
A28: 金七门 4 号 | B28: 华东 | C28: 123 | D28: 2033 | E28: =D28+'Scenarios'!$G$24 -> 2033 | F28: 18000 | G28: =IF(G$3>$E28,$C28,IF(G$3=$E28,$C28*'Scenarios'!G$30,0)) -> 0 | H28: =IF(H$3>$E28,$C28,IF(H$3=$E28,$C28*'Scenarios'!H$30,0)) -> 0 | I28: =IF(I$3>$E28,$C28,IF(I$3=$E28,$C28*'Scenarios'!I$30,0)) -> 0 | J28: =IF(J$3>$E28,$C28,IF(J$3=$E28,$C28*'Scenarios'!J$30,0)) -> 0 | K28: =IF(K$3>$E28,$C28,IF(K$3=$E28,$C28*'Scenarios'!K$30,0)) -> 0
A29: 在建及核准待建合计（22 台） | B29: 万千瓦 | C29: =SUM(C8:C28) -> 2563.5 | G29: =SUM(G8:G28) -> 55.6 | H29: =SUM(H8:H28) -> 340.64 | I29: =SUM(I8:I28) -> 745.7 | J29: =SUM(J8:J28) -> 1048.2 | K29: =SUM(K8:K28) -> 1319.7 | L29: 校验：应等于 2,563.50 万千瓦（2026 半年报披露日口径）
A30: 新机组年末在运容量 | B30: 万千瓦 | G30: =SUMPRODUCT(($E$8:$E$28<=G$3)*$C$8:$C$28) -> 139 | H30: =SUMPRODUCT(($E$8:$E$28<=H$3)*$C$8:$C$28) -> 643.1 | I30: =SUMPRODUCT(($E$8:$E$28<=I$3)*$C$8:$C$28) -> 899.6 | J30: =SUMPRODUCT(($E$8:$E$28<=J$3)*$C$8:$C$28) -> 1271.1 | K30: =SUMPRODUCT(($E$8:$E$28<=K$3)*$C$8:$C$28) -> 1392.6
A31: 新机组投产转固金额（容量×单位造价） | B31: 亿元 | G31: =SUMPRODUCT(($E$8:$E$28=G$3)*$C$8:$C$28*$F$8:$F$28)/10000 -> 290.78915 | H31: =SUMPRODUCT(($E$8:$E$28=H$3)*$C$8:$C$28*$F$8:$F$28)/10000 -> 976.61381 | I31: =SUMPRODUCT(($E$8:$E$28=I$3)*$C$8:$C$28*$F$8:$F$28)/10000 -> 472.66705 | J31: =SUMPRODUCT(($E$8:$E$28=J$3)*$C$8:$C$28*$F$8:$F$28)/10000 -> 607.55137 | K31: =SUMPRODUCT(($E$8:$E$28=K$3)*$C$8:$C$28*$F$8:$F$28)/10000 -> 222.86745 | L31: 链接 Balance Sheet 在建工程→固定资产
A33: B. 核电经营数据 Nuclear operations
A34: 秦山基地（含方家山，9台） 装机 | B34: 万千瓦 | D34: 666.4 | E34: 666.4 | F34: 670.2 | G34: 670.2 | H34: 670.2 | I34: 670.2 | J34: 670.2 | K34: 670.2 | L34: 存量机组装机（年报 2025 第 33 页；秦二厂 2 号 2025 年增容至 70.8 万kW）
A35: 田湾 1–6 号 装机 | B35: 万千瓦 | D35: 660.8 | E35: 660.8 | F35: 660.8 | G35: 660.8 | H35: 660.8 | I35: 660.8 | J35: 660.8 | K35: 660.8
A36: 福清 1–6 号 装机 | B36: 万千瓦 | D36: 667.8 | E36: 667.8 | F36: 667.8 | G36: 667.8 | H36: 667.8 | I36: 667.8 | J36: 667.8 | K36: 667.8
A37: 三门 1–2 号（AP1000） 装机 | B37: 万千瓦 | D37: 250 | E37: 250 | F37: 250 | G37: 250 | H37: 250 | I37: 250 | J37: 250 | K37: 250
A38: 海南昌江 1–2 号 装机 | B38: 万千瓦 | D38: 130 | E38: 130 | F38: 130 | G38: 130 | H38: 130 | I38: 130 | J38: 130 | K38: 130
A39: 漳州 1–2 号（华龙一号） 装机 | B39: 万千瓦 | D39: 0 | E39: 0 | F39: 121.2 | G39: 242.4 | H39: 242.4 | I39: 242.4 | J39: 242.4 | K39: 242.4
A40: 存量机组装机合计 | B40: 万千瓦 | D40: =SUM(D34:D39) -> 2375 | E40: =SUM(E34:E39) -> 2375 | F40: =SUM(F34:F39) -> 2500 | G40: =SUM(G34:G39) -> 2621.2 | H40: =SUM(H34:H39) -> 2621.2 | I40: =SUM(I34:I39) -> 2621.2 | J40: =SUM(J34:J39) -> 2621.2 | K40: =SUM(K34:K39) -> 2621.2
A41: 核电控股在运装机（年末） | B41: 万千瓦 | C41: 2375 | D41: 2375 | E41: 2375 | F41: 2500 | G41: =G40+G30 -> 2760.2 | H41: =H40+H30 -> 3264.3 | I41: =I40+I30 -> 3520.8 | J41: =J40+J30 -> 3892.3 | K41: =K40+K30 -> 4013.8 | L41: 2025A 2,500 万kW（26 台）；2026-01-01 漳州 2 号商运后 2,621.2 万kW
A42: 存量机组利用小时（情景） | B42: 小时 | D42: 7852 | E42: 7710 | F42: 8038 | G42: ='Scenarios'!G18 -> 7650 | H42: ='Scenarios'!H18 -> 7950 | I42: ='Scenarios'!I18 -> 7950 | J42: ='Scenarios'!J18 -> 7950 | K42: ='Scenarios'!K18 -> 7950 | L42: 历史=公司平均利用小时（年报发电效率表）
A43: 秦山基地（含方家山，9台） 发电量 | B43: 亿kWh | D43: 555.89675 | E43: 547.46205 | F43: 538.89202 | G43: =G34*G42/10000 -> 512.703 | H43: =H34*H42/10000 -> 532.809 | I43: =I34*I42/10000 -> 532.809 | J43: =J34*J42/10000 -> 532.809 | K43: =K34*K42/10000 -> 532.809 | L43: 历史=Σ机组容量×利用小时（推算）；预测装机 670.2 万kW
A44: 田湾 1–6 号 发电量 | B44: 亿kWh | D44: 502.76332 | E44: 517.63812 | F44: 527.40832 | G44: =G35*G42/10000 -> 505.512 | H44: =H35*H42/10000 -> 525.336 | I44: =I35*I42/10000 -> 525.336 | J44: =J35*J42/10000 -> 525.336 | K44: =K35*K42/10000 -> 525.336 | L44: 历史=Σ机组容量×利用小时（推算）；预测装机 660.8 万kW
A45: 福清 1–6 号 发电量 | B45: 亿kWh | D45: 494.82018 | E45: 461.46555 | F45: 546.94458 | G45: =G36*G42/10000 -> 510.867 | H45: =H36*H42/10000 -> 530.901 | I45: =I36*I42/10000 -> 530.901 | J45: =J36*J42/10000 -> 530.901 | K45: =K36*K42/10000 -> 530.901 | L45: 历史=Σ机组容量×利用小时（推算）；预测装机 667.8 万kW
A46: 三门 1–2 号（AP1000） 发电量 | B46: 亿kWh | D46: 206.2875 | E46: 207.9 | F46: 193.9375 | G46: =G37*G42/10000 -> 191.25 | H46: =H37*H42/10000 -> 198.75 | I46: =I37*I42/10000 -> 198.75 | J46: =J37*J42/10000 -> 198.75 | K46: =K37*K42/10000 -> 198.75 | L46: 历史=Σ机组容量×利用小时（推算）；预测装机 250.0 万kW
A47: 海南昌江 1–2 号 发电量 | B47: 亿kWh | D47: 105.0075 | E47: 96.7655 | F47: 100.139 | G47: =G38*G42/10000 -> 99.45 | H47: =H38*H42/10000 -> 103.35 | I47: =I38*I42/10000 -> 103.35 | J47: =J38*J42/10000 -> 103.35 | K47: =K38*K42/10000 -> 103.35 | L47: 历史=Σ机组容量×利用小时（推算）；预测装机 130.0 万kW
A48: 漳州 1–2 号（华龙一号） 发电量 | B48: 亿kWh | D48: 0 | E48: 0 | F48: 102.12312 | G48: =G39*G42/10000 -> 185.436 | H48: =H39*H42/10000 -> 192.708 | I48: =I39*I42/10000 -> 192.708 | J48: =J39*J42/10000 -> 192.708 | K48: =K39*K42/10000 -> 192.708 | L48: 历史=Σ机组容量×利用小时（推算）；预测装机 242.4 万kW；漳州 2 号 2026-01-01 商运
A49: 田湾 7–8 号 发电量 | B49: 亿kWh | G49: =(G8+G12)*G42/10000 -> 38.709 | H49: =(H8+H12)*H42/10000 -> 140.7945 | I49: =(I8+I12)*I42/10000 -> 201.135 | J49: =(J8+J12)*J42/10000 -> 201.135 | K49: =(K8+K12)*K42/10000 -> 201.135
A50: 海南小堆 发电量 | B50: 亿kWh | G50: =(G9)*G42/10000 -> 3.825 | H50: =(H9)*H42/10000 -> 9.9375 | I50: =(I9)*I42/10000 -> 9.9375 | J50: =(J9)*J42/10000 -> 9.9375 | K50: =(K9)*K42/10000 -> 9.9375
A51: 三门 3–4 号 发电量 | B51: 亿kWh | G51: =(G11+G13)*G42/10000 -> 0 | H51: =(H11+H13)*H42/10000 -> 79.5636 | I51: =(I11+I13)*I42/10000 -> 198.909 | J51: =(J11+J13)*J42/10000 -> 198.909 | K51: =(K11+K13)*K42/10000 -> 198.909
A52: 徐大堡 1–4 号 发电量 | B52: 亿kWh | G52: =(G10+G14+G15+G17)*G42/10000 -> 0 | H52: =(H10+H14+H15+H17)*H42/10000 -> 40.5132 | I52: =(I10+I14+I15+I17)*I42/10000 -> 182.85 | J52: =(J10+J14+J15+J17)*J42/10000 -> 346.2543 | K52: =(K10+K14+K15+K17)*K42/10000 -> 407.835
A53: 漳州 3–4 号 发电量 | B53: 亿kWh | G53: =(G16+G18)*G42/10000 -> 0 | H53: =(H16+H18)*H42/10000 -> 0 | I53: =(I16+I18)*I42/10000 -> 0 | J53: =(J16+J18)*J42/10000 -> 77.0832 | K53: =(K16+K18)*K42/10000 -> 192.708
A54: 金七门 1–2 号 发电量 | B54: 亿kWh | G54: =(G19+G21)*G42/10000 -> 0 | H54: =(H19+H21)*H42/10000 -> 0 | I54: =(I19+I21)*I42/10000 -> 0 | J54: =(J19+J21)*J42/10000 -> 0 | K54: =(K19+K21)*K42/10000 -> 38.637
A55: 徐圩/三门 5–6/庄河/金七门 3–4 发电量 | B55: 亿kWh | G55: =(G20+G22+G23+G24+G25+G26+G27+G28)*G42/10000 -> 0 | H55: =(H20+H22+H23+H24+H25+H26+H27+H28)*H42/10000 -> 0 | I55: =(I20+I22+I23+I24+I25+I26+I27+I28)*I42/10000 -> 0 | J55: =(J20+J22+J23+J24+J25+J26+J27+J28)*J42/10000 -> 0 | K55: =(K20+K22+K23+K24+K25+K26+K27+K28)*K42/10000 -> 0
A56: 核电发电量（按机组推算合计） | B56: 亿kWh | D56: =SUM(D43:D55) -> 1864.7752 | E56: =SUM(E43:E55) -> 1831.2312 | F56: =SUM(F43:F55) -> 2009.4445 | G56: =SUM(G43:G55) -> 2047.752 | H56: =SUM(H43:H55) -> 2354.6628 | I56: =SUM(I43:I55) -> 2676.6855 | J56: =SUM(J43:J55) -> 2917.173 | K56: =SUM(K43:K55) -> 3133.0155
A57: 核电发电量（报告口径） | B57: 亿kWh | C57: 1852.39 | D57: 1864.77 | E57: 1831.22 | F57: 2008.07 | G57: =G56 -> 2047.752 | H57: =H56 -> 2354.6628 | I57: =I56 -> 2676.6855 | J57: =J56 -> 2917.173 | K57: =K56 -> 3133.0155 | L57: 年报产销量表；含蒸汽供能折算电量（2025 年 10.24 亿 kWh）
A58: 核电上网电量/发电量 | B58: % | C58: =C59/C57 -> 0.93509466 | D58: =D59/D57 -> 0.93554701 | E58: =E59/E57 -> 0.93522351 | F58: =F59/F57 -> 0.93546042 | G58: 0.9355 | H58: 0.9355 | I58: 0.9355 | J58: 0.9355 | K58: 0.9355 | L58: 2025A 93.55% / 2024A 93.52%
A59: 核电上网电量 | B59: 亿kWh | C59: 1732.16 | D59: 1744.58 | E59: 1712.6 | F59: 1878.47 | G59: =G57*G58 -> 1915.672 | H59: =H57*H58 -> 2202.787 | I59: =I57*I58 -> 2504.0393 | J59: =J57*J58 -> 2729.0153 | K59: =K57*K58 -> 2930.936
A60: 核电综合电价（含税） | B60: 元/kWh | E60: 0.4151 | F60: 0.3937 | G60: ='Scenarios'!G12 -> 0.378 | H60: ='Scenarios'!H12 -> 0.376 | I60: ='Scenarios'!I12 -> 0.375 | J60: ='Scenarios'!J12 -> 0.375 | K60: ='Scenarios'!K12 -> 0.375 | L60: 年报 2025 售电业务经营情况；预测链接 Scenarios
A61: 增值税率 | B61: % | C61: 0.13 | D61: 0.13 | E61: 0.13 | F61: 0.13 | G61: 0.13 | H61: 0.13 | I61: 0.13 | J61: 0.13 | K61: 0.13
A63: C. 新能源经营数据 Renewables operations
A64: 风电在运装机（年末） | B64: 万千瓦 | D64: 595.15 | E64: 941 | F64: 1062.68 | G64: =F64+'Scenarios'!G54*G67 -> 1185.18 | H64: =G64+'Scenarios'!H54*H67 -> 1272.68 | I64: =H64+'Scenarios'!I54*I67 -> 1342.68 | J64: =I64+'Scenarios'!J54*J67 -> 1412.68 | K64: =J64+'Scenarios'!K54*K67 -> 1482.68 | L64: 2024A 为作者按总装机比例估算（年报未单独披露 2024 年末风光拆分）
A65: 光伏在运装机（年末） | B65: 万千瓦 | D65: 1256.44 | E65: 2018.62 | F65: 2301.42 | G65: =F65+'Scenarios'!G54*(1-G67) -> 2528.92 | H65: =G65+'Scenarios'!H54*(1-H67) -> 2691.42 | I65: =H65+'Scenarios'!I54*(1-I67) -> 2821.42 | J65: =I65+'Scenarios'!J54*(1-J67) -> 2951.42 | K65: =J65+'Scenarios'!K54*(1-K67) -> 3081.42
A66: 新能源在运装机合计（年末） | B66: 万千瓦 | C66: 1253.07 | D66: 1851.59 | E66: 2959.62 | F66: 3364.1 | G66: =G64+G65 -> 3714.1 | H66: =H64+H65 -> 3964.1 | I66: =I64+I65 -> 4164.1 | J66: =J64+J65 -> 4364.1 | K66: =K64+K65 -> 4564.1 | L66: 不含独立储能（2025 年末 165.10 万kW）
A67: 新增装机中风电占比 | B67: % | G67: 0.35 | H67: 0.35 | I67: 0.35 | J67: 0.35 | K67: 0.35 | L67: 2025 年末在建：风电 260.74 / 光伏 532.43 万kW
A68: 风电利用小时 | B68: 小时 | F68: 1928 | G68: ='Scenarios'!G42 -> 1800 | H68: ='Scenarios'!H42 -> 1800 | I68: ='Scenarios'!I42 -> 1800 | J68: ='Scenarios'!J42 -> 1800 | K68: ='Scenarios'!K42 -> 1800 | L68: 2025A 按平均装机推算
A69: 光伏利用小时 | B69: 小时 | F69: 1126 | G69: ='Scenarios'!G48 -> 1050 | H69: ='Scenarios'!H48 -> 1050 | I69: ='Scenarios'!I48 -> 1050 | J69: ='Scenarios'!J48 -> 1050 | K69: ='Scenarios'!K48 -> 1050
A70: 风电发电量 | B70: 亿kWh | C70: 65.37 | D70: 109.03 | E70: 151.58 | F70: 193.14 | G70: =(F64+G64)/2*G68/10000 -> 202.3074 | H70: =(G64+H64)/2*H68/10000 -> 221.2074 | I70: =(H64+I64)/2*I68/10000 -> 235.3824 | J70: =(I64+J64)/2*J68/10000 -> 247.9824 | K70: =(J64+K64)/2*K68/10000 -> 260.5824 | L70: 2022A/2024A 由同比增速倒推
A71: 光伏发电量 | B71: 亿kWh | C71: 75.11 | D71: 124.78 | E71: 180.69 | F71: 243.08 | G71: =(F65+G65)/2*G69/10000 -> 253.59285 | H71: =(G65+H65)/2*H69/10000 -> 274.06785 | I71: =(H65+I65)/2*I69/10000 -> 289.4241 | J71: =(I65+J65)/2*J69/10000 -> 303.0741 | K71: =(J65+K65)/2*K69/10000 -> 316.7241
A72: 新能源发电量合计 | B72: 亿kWh | C72: =C70+C71 -> 140.48 | D72: =D70+D71 -> 233.81 | E72: =E70+E71 -> 332.27 | F72: =F70+F71 -> 436.22 | G72: =G70+G71 -> 455.90025 | H72: =H70+H71 -> 495.27525 | I72: =I70+I71 -> 524.8065 | J72: =J70+J71 -> 551.0565 | K72: =K70+K71 -> 577.3065
A73: 新能源上网率 | B73: % | G73: 0.9834 | H73: 0.9834 | I73: 0.9834 | J73: 0.9834 | K73: 0.9834 | L73: 2025A 429.00/436.23=98.34%
A74: 新能源上网电量 | B74: 亿kWh | C74: 138.23 | D74: 229.91 | E74: 326.63 | F74: 429 | G74: =G72*G73 -> 448.33231 | H74: =H72*H73 -> 487.05368 | I74: =I72*I73 -> 516.09471 | J74: =J72*J73 -> 541.90896 | K74: =K72*K73 -> 567.72321
A75: 新能源综合电价（含税） | B75: 元/kWh | E75: 0.4203 | F75: 0.3732 | G75: ='Scenarios'!G36 -> 0.355 | H75: ='Scenarios'!H36 -> 0.345 | I75: ='Scenarios'!I36 -> 0.34 | J75: ='Scenarios'!J36 -> 0.335 | K75: ='Scenarios'!K36 -> 0.335
A77: D. 分产品/分电站收入 Revenue by product & plant（不含增值税）
A78: 秦山基地（含方家山，9台） | B78: 亿元 | G78: =G43*G58*G60/(1+G61) -> 160.44382 | H78: =H43*H58*H60/(1+H61) -> 165.85354 | I78: =I43*I58*I60/(1+I61) -> 165.41244 | J78: =J43*J58*J60/(1+J61) -> 165.41244 | K78: =K43*K58*K60/(1+K61) -> 165.41244
A79: 田湾 1–6 号 | B79: 亿元 | G79: =G44*G58*G60/(1+G61) -> 158.19349 | H79: =H44*H58*H60/(1+H61) -> 163.52733 | I79: =I44*I58*I60/(1+I61) -> 163.09242 | J79: =J44*J58*J60/(1+J61) -> 163.09242 | K79: =K44*K58*K60/(1+K61) -> 163.09242
A80: 福清 1–6 号 | B80: 亿元 | G80: =G45*G58*G60/(1+G61) -> 159.86927 | H80: =H45*H58*H60/(1+H61) -> 165.25961 | I80: =I45*I58*I60/(1+I61) -> 164.82009 | J80: =J45*J58*J60/(1+J61) -> 164.82009 | K80: =K45*K58*K60/(1+K61) -> 164.82009
A81: 三门 1–2 号（AP1000） | B81: 亿元 | G81: =G46*G58*G60/(1+G61) -> 59.849233 | H81: =H46*H58*H60/(1+H61) -> 61.867181 | I81: =I46*I58*I60/(1+I61) -> 61.702641 | J81: =J46*J58*J60/(1+J61) -> 61.702641 | K81: =K46*K58*K60/(1+K61) -> 61.702641
A82: 海南昌江 1–2 号 | B82: 亿元 | G82: =G47*G58*G60/(1+G61) -> 31.121601 | H82: =H47*H58*H60/(1+H61) -> 32.170934 | I82: =I47*I58*I60/(1+I61) -> 32.085373 | J82: =J47*J58*J60/(1+J61) -> 32.085373 | K82: =K47*K58*K60/(1+K61) -> 32.085373
A83: 漳州 1–2 号（华龙一号） | B83: 亿元 | G83: =G48*G58*G60/(1+G61) -> 58.029817 | H83: =H48*H58*H60/(1+H61) -> 59.986419 | I83: =I48*I58*I60/(1+I61) -> 59.826881 | J83: =J48*J58*J60/(1+J61) -> 59.826881 | K83: =K48*K58*K60/(1+K61) -> 59.826881
A84: 田湾 7–8 号（新机组） | B84: 亿元 | G84: =G49*G58*G60/(1+G61) -> 12.113485 | H84: =H49*H58*H60/(1+H61) -> 43.826711 | I84: =I49*I58*I60/(1+I61) -> 62.443073 | J84: =J49*J58*J60/(1+J61) -> 62.443073 | K84: =K49*K58*K60/(1+K61) -> 62.443073
A85: 海南小堆（新机组） | B85: 亿元 | G85: =G50*G58*G60/(1+G61) -> 1.1969847 | H85: =H50*H58*H60/(1+H61) -> 3.0933591 | I85: =I50*I58*I60/(1+I61) -> 3.0851321 | J85: =J50*J58*J60/(1+J61) -> 3.0851321 | K85: =K50*K58*K60/(1+K61) -> 3.0851321
A86: 三门 3–4 号（新机组） | B86: 亿元 | G86: =G51*G58*G60/(1+G61) -> 0 | H86: =H51*H58*H60/(1+H61) -> 24.76667 | I86: =I51*I58*I60/(1+I61) -> 61.752003 | J86: =J51*J58*J60/(1+J61) -> 61.752003 | K86: =K51*K58*K60/(1+K61) -> 61.752003
A87: 徐大堡 1–4 号（新机组） | B87: 亿元 | G87: =G52*G58*G60/(1+G61) -> 0 | H87: =H52*H58*H60/(1+H61) -> 12.611006 | I87: =I52*I58*I60/(1+I61) -> 56.76643 | J87: =J52*J58*J60/(1+J61) -> 107.49587 | K87: =K52*K58*K60/(1+K61) -> 126.61382
A88: 漳州 3–4 号（新机组） | B88: 亿元 | G88: =G53*G58*G60/(1+G61) -> 0 | H88: =H53*H58*H60/(1+H61) -> 0 | I88: =I53*I58*I60/(1+I61) -> 0 | J88: =J53*J58*J60/(1+J61) -> 23.930752 | K88: =K53*K58*K60/(1+K61) -> 59.826881
A89: 金七门 1–2 号（新机组） | B89: 亿元 | G89: =G54*G58*G60/(1+G61) -> 0 | H89: =H54*H58*H60/(1+H61) -> 0 | I89: =I54*I58*I60/(1+I61) -> 0 | J89: =J54*J58*J60/(1+J61) -> 0 | K89: =K54*K58*K60/(1+K61) -> 11.994993
A90: 徐圩/三门 5–6/庄河/金七门 3–4（新机组） | B90: 亿元 | G90: =G55*G58*G60/(1+G61) -> 0 | H90: =H55*H58*H60/(1+H61) -> 0 | I90: =I55*I58*I60/(1+I61) -> 0 | J90: =J55*J58*J60/(1+J61) -> 0 | K90: =K55*K58*K60/(1+K61) -> 0
A91: 核电收入 Nuclear revenue | B91: 亿元 | E91: =E59*E60/(1+E61) -> 629.11527 | F91: =F59*F60/(1+F61) -> 654.47225 | G91: =SUM(G78:G90) -> 640.81771 | H91: =SUM(H78:H90) -> 732.96277 | I91: =SUM(I78:I90) -> 830.98649 | J91: =SUM(J78:J90) -> 905.64668 | K91: =SUM(K78:K90) -> 972.65575 | L91: 2024–25A=上网电量×综合电价/1.13（推算；2025 年报核电收入 654.53 亿）
A92: 同比 YoY | B92: % | F92: =F91/E91-1 -> 0.040305765 | G92: =G91/F91-1 -> -0.020863429 | H92: =H91/G91-1 -> 0.14379293 | I92: =I91/H91-1 -> 0.13373629 | J92: =J91/I91-1 -> 0.089845258 | K92: =K91/J91-1 -> 0.073990298
A93: 风电收入 | B93: 亿元 | E93: =E70*E74/E72*E75/(1+E61) -> 55.422714 | F93: =F70*F74/F72*F75/(1+F61) -> 62.731712 | G93: =G70*G73*G75/(1+G61) -> 62.501708 | H93: =H70*H73*H75/(1+H61) -> 66.415662 | I93: =I70*I73*I75/(1+I61) -> 69.647361 | J93: =J70*J73*J75/(1+J61) -> 72.296526 | K93: =K70*K73*K75/(1+K61) -> 75.969916
A94: 光伏收入 | B94: 亿元 | E94: =E71*E74/E72*E75/(1+E61) -> 66.066303 | F94: =F71*F74/F72*F75/(1+F61) -> 78.952182 | G94: =G71*G73*G75/(1+G61) -> 78.346052 | H94: =H71*H73*H75/(1+H61) -> 82.286568 | I94: =I71*I73*I75/(1+I61) -> 85.637774 | J94: =J71*J73*J75/(1+J61) -> 88.357901 | K94: =K71*K73*K75/(1+K61) -> 92.337408
A95: 新能源收入 Renewables revenue | B95: 亿元 | E95: =E93+E94 -> 121.48902 | F95: =F93+F94 -> 141.68389 | G95: =G93+G94 -> 140.84776 | H95: =H93+H94 -> 148.70223 | I95: =I93+I94 -> 155.28513 | J95: =J93+J94 -> 160.65443 | K95: =K93+K94 -> 168.30732
A96: 同比 YoY | B96: % | F96: =F95/E95-1 -> 0.16622801 | G96: =G95/F95-1 -> -0.0059014047 | H96: =H95/G95-1 -> 0.055765674 | I96: =I95/H95-1 -> 0.044269038 | J96: =J95/I95-1 -> 0.034576988 | K96: =K95/J95-1 -> 0.047635769
A97: 电力收入合计（主营业务） | B97: 亿元 | C97: 699.43 | D97: 732.66 | E97: =E91+E95 -> 750.60429 | F97: 796.22 | G97: =G91+G95 -> 781.66547 | H97: =H91+H95 -> 881.665 | I97: =I91+I95 -> 986.27162 | J97: =J91+J95 -> 1066.3011 | K97: =K91+K95 -> 1140.9631 | L97: 2023A/2025A=年报主营业务分行业；2022A=2023 年值/(1+4.75%)；2024A=分产品加总
A98: 其他业务收入增速 | B98: % | G98: 0.05 | H98: 0.05 | I98: 0.05 | J98: 0.05 | K98: 0.05 | L98: 技术服务、核能供热、同位素等
A99: 其他业务收入 Other revenue | B99: 亿元 | C99: ='Income Statement'!C7-C97 -> 13.426008 | D99: ='Income Statement'!D7-D97 -> 16.911803 | E99: ='Income Statement'!E7-E97 -> 22.116294 | F99: ='Income Statement'!F7-F97 -> 24.534952 | G99: =F99*(1+G98) -> 25.7617 | H99: =G99*(1+H98) -> 27.049785 | I99: =H99*(1+I98) -> 28.402274 | J99: =I99*(1+J98) -> 29.822388 | K99: =J99*(1+K98) -> 31.313507
A100: 营业收入合计 Total revenue | B100: 亿元 | C100: =C97+C99 -> 712.85601 | D100: =D97+D99 -> 749.5718 | E100: =E97+E99 -> 772.72059 | F100: =F97+F99 -> 820.75495 | G100: =G97+G99 -> 807.42717 | H100: =H97+H99 -> 908.71479 | I100: =I97+I99 -> 1014.6739 | J100: =J97+J99 -> 1096.1235 | K100: =K97+K99 -> 1172.2766
A101: 同比 YoY | B101: % | D101: =D100/C100-1 -> 0.051505204 | E101: =E100/D100-1 -> 0.030882675 | F101: =F100/E100-1 -> 0.06216266 | G101: =G100/F100-1 -> -0.016238441 | H101: =H100/G100-1 -> 0.12544489 | I101: =I100/H100-1 -> 0.11660327 | J101: =J100/I100-1 -> 0.080271703 | K101: =K100/J100-1 -> 0.069474913
A102: 核电收入占比 | B102: % | E102: =E91/E100 -> 0.81415622 | F102: =F91/F100 -> 0.79740274 | G102: =G91/G100 -> 0.79365389 | H102: =H91/H100 -> 0.80659276 | I102: =I91/I100 -> 0.81896902 | J102: =J91/J100 -> 0.82622687 | K102: =K91/K100 -> 0.82971524
A103: 新能源收入占比 | B103: % | E103: =E95/E100 -> 0.15722244 | F103: =F95/F100 -> 0.1726263 | G103: =G95/G100 -> 0.1744402 | H103: =H95/H100 -> 0.16364016 | I103: =I95/I100 -> 0.15303945 | J103: =J95/J100 -> 0.14656599 | K103: =K95/K100 -> 0.14357305
A105: E. 分地区收入 Revenue by region（年报主营业务分地区；2022A/2024A 按同比增速倒推）
A106: 华东 新能源收入占比（假设） | B106: % | G106: 0.162 | H106: 0.162 | I106: 0.162 | J106: 0.162 | K106: 0.162 | L106: 2025A 推算：地区收入−地区核电收入
...

Sheet Income Statement
A1: 利润表 Income Statement（合并口径）
A2: 单位：亿元人民币（另有注明除外）｜蓝色=硬编码输入 黑色=公式 绿色=跨表链接｜A=实际 E=预测
A3: 项目 / Line item | B3: 单位 | C3: 2022 | D3: 2023 | E3: 2024 | F3: 2025 | G3: 2026 | H3: 2027 | I3: 2028 | J3: 2029 | K3: 2030 | L3: 来源 / 说明 | M3: 2026H1A | N3: H1/2026E
A6: 收入 Revenue
A7: 营业收入 Operating revenue | B7: 亿元 | C7: 712.85601 | D7: 749.5718 | E7: 772.72059 | F7: 820.75495 | G7: ='Revenue Model'!G100 -> 807.42717 | H7: ='Revenue Model'!H100 -> 908.71479 | I7: ='Revenue Model'!I100 -> 1014.6739 | J7: ='Revenue Model'!J100 -> 1096.1235 | K7: ='Revenue Model'!K100 -> 1172.2766 | L7: 历史：年报合并利润表；预测：Revenue Model | M7: 383.97892 | N7: =IFERROR(M7/G7,"") -> 0.47555859
A8: 同比 YoY | B8: % | D8: =D7/C7-1 -> 0.051505204 | E8: =E7/D7-1 -> 0.030882675 | F8: =F7/E7-1 -> 0.06216266 | G8: =G7/F7-1 -> -0.016238441 | H8: =H7/G7-1 -> 0.12544489 | I8: =I7/H7-1 -> 0.11660327 | J8: =J7/I7-1 -> 0.080271703 | K8: =K7/J7-1 -> 0.069474913
A9: 其中：核电 | B9: 亿元 | E9: ='Revenue Model'!E91 -> 629.11527 | F9: ='Revenue Model'!F91 -> 654.47225 | G9: ='Revenue Model'!G91 -> 640.81771 | H9: ='Revenue Model'!H91 -> 732.96277 | I9: ='Revenue Model'!I91 -> 830.98649 | J9: ='Revenue Model'!J91 -> 905.64668 | K9: ='Revenue Model'!K91 -> 972.65575
A10: 其中：新能源 | B10: 亿元 | E10: ='Revenue Model'!E95 -> 121.48902 | F10: ='Revenue Model'!F95 -> 141.68389 | G10: ='Revenue Model'!G95 -> 140.84776 | H10: ='Revenue Model'!H95 -> 148.70223 | I10: ='Revenue Model'!I95 -> 155.28513 | J10: ='Revenue Model'!J95 -> 160.65443 | K10: ='Revenue Model'!K95 -> 168.30732
A11: 其中：其他业务 | B11: 亿元 | C11: ='Revenue Model'!C99 -> 13.426008 | D11: ='Revenue Model'!D99 -> 16.911803 | E11: ='Revenue Model'!E99 -> 22.116294 | F11: ='Revenue Model'!F99 -> 24.534952 | G11: ='Revenue Model'!G99 -> 25.7617 | H11: ='Revenue Model'!H99 -> 27.049785 | I11: ='Revenue Model'!I99 -> 28.402274 | J11: ='Revenue Model'!J99 -> 29.822388 | K11: ='Revenue Model'!K99 -> 31.313507
A13: 营业成本驱动 COGS drivers（成本分析表口径）
A14: 核燃料单位成本 | B14: 元/kWh | E14: =E24/'Revenue Model'!E57 -> 0.041262437 | F14: =F24/'Revenue Model'!F57 -> 0.043348987 | G14: =F14*(1+'Scenarios'!G66) -> 0.045082946 | H14: =G14*(1+'Scenarios'!H66) -> 0.046886264 | I14: =H14*(1+'Scenarios'!I66) -> 0.048761715 | J14: =I14*(1+'Scenarios'!J66) -> 0.050712183 | K14: =J14*(1+'Scenarios'!K66) -> 0.052740671
A15: 乏燃料处置基金 | B15: 元/kWh | E15: =E25/'Revenue Model'!E57 -> 0.019228492 | F15: =F25/'Revenue Model'!F57 -> 0.018591932 | G15: 0.0186 | H15: 0.0186 | I15: 0.0186 | J15: 0.0186 | K15: 0.0186 | L15: 国家标准 0.026 元/kWh（投运满 5 年机组）；2025A 全机队平均 0.0186
A16: 人员费用（每千瓦核电装机） | B16: 元/kW | E16: =E27*10000/'Revenue Model'!E41 -> 255.17684 | F16: =F27*10000/'Revenue Model'!F41 -> 249.1084 | G16: =F16*(1+G18) -> 254.09057 | H16: =G16*(1+H18) -> 259.17238 | I16: =H16*(1+I18) -> 264.35583 | J16: =I16*(1+J18) -> 269.64294 | K16: =J16*(1+K18) -> 275.0358
A17: 运维及其他（每千瓦核电+新能源平均装机） | B17: 元/kW | E17: =E28*10000/('Revenue Model'!E41+('Revenue Model'!E66+'Revenue Model'!D66)/2) -> 202.36665 | F17: =F28*10000/('Revenue Model'!F41+('Revenue Model'!F66+'Revenue Model'!E66)/2) -> 162.9763 | G17: =F17*(1+G19) -> 156.45725 | H17: =G17*(1+H19) -> 156.45725 | I17: =H17*(1+I19) -> 158.02182 | J17: =I17*(1+J19) -> 159.60204 | K17: =J17*(1+K19) -> 161.19806
A18: 人员成本通胀 | B18: % | G18: 0.02 | H18: 0.02 | I18: 0.02 | J18: 0.02 | K18: 0.02
A19: 运维单位成本变动 | B19: % | G19: -0.04 | H19: 0 | I19: 0.01 | J19: 0.01 | K19: 0.01 | L19: 2025A 运维及其他 -4.62%（装机增长下仍下降，规模效应）
A20: 核电平均装机（存量+新机组加权） | B20: 万千瓦 | G20: ='Revenue Model'!G40+'Revenue Model'!G29 -> 2676.8 | H20: ='Revenue Model'!H40+'Revenue Model'!H29 -> 2961.84 | I20: ='Revenue Model'!I40+'Revenue Model'!I29 -> 3366.9 | J20: ='Revenue Model'!J40+'Revenue Model'!J29 -> 3669.4 | K20: ='Revenue Model'!K40+'Revenue Model'!K29 -> 3940.9
A21: 新能源平均装机 | B21: 万千瓦 | G21: =('Revenue Model'!F66+'Revenue Model'!G66)/2 -> 3539.1 | H21: =('Revenue Model'!G66+'Revenue Model'!H66)/2 -> 3839.1 | I21: =('Revenue Model'!H66+'Revenue Model'!I66)/2 -> 4064.1 | J21: =('Revenue Model'!I66+'Revenue Model'!J66)/2 -> 4264.1 | K21: =('Revenue Model'!J66+'Revenue Model'!K66)/2 -> 4464.1
A23: 营业成本 Cost of revenue
A24: 核燃料成本 | B24: 亿元 | C24: 85.8463 | D24: 92.1016 | E24: 75.5606 | F24: 87.0478 | G24: ='Revenue Model'!G57*G14 -> 92.318693 | H24: ='Revenue Model'!H57*H14 -> 110.40134 | I24: ='Revenue Model'!I57*I14 -> 130.51977 | J24: ='Revenue Model'!J57*J14 -> 147.93621 | K24: ='Revenue Model'!K57*K14 -> 165.23734 | L24: 2022–23A 为年报“燃料及其他材料”口径（含非核材料，乏燃料基金含于其他成本），与 2024 年后不完全可比
A25: 乏燃料处置基金 | B25: 亿元 | E25: 35.2116 | F25: 37.3339 | G25: ='Revenue Model'!G57*G15 -> 38.088187 | H25: ='Revenue Model'!H57*H15 -> 43.796728 | I25: ='Revenue Model'!I57*I15 -> 49.78635 | J25: ='Revenue Model'!J57*J15 -> 54.259418 | K25: ='Revenue Model'!K57*K15 -> 58.274088
A26: 固定资产折旧（计入成本） | B26: 亿元 | C26: 148.7413 | D26: 160.5377 | E26: 173.0367 | F26: 202.6774 | G26: ='Balance Sheet'!G76 -> 220.58518 | H26: ='Balance Sheet'!H76 -> 252.47745 | I26: ='Balance Sheet'!I76 -> 286.34412 | J26: ='Balance Sheet'!J76 -> 306.71429 | K26: ='Balance Sheet'!K76 -> 318.40202 | L26: 预测=Balance Sheet 固定资产折旧
A27: 人员费用 | B27: 亿元 | C27: 52.8459 | D27: 56.9412 | E27: 60.6045 | F27: 62.2771 | G27: =G20*G16/10000 -> 68.014963 | H27: =H20*H16/10000 -> 76.762712 | I27: =I20*I16/10000 -> 89.005963 | J27: =J20*J16/10000 -> 98.942782 | K27: =K20*K16/10000 -> 108.38886
A28: 运维及其他 | B28: 亿元 | C28: 100.1361 | D28: 105.5163 | E28: 96.7435 | F28: 92.2749 | G28: =(G20+G21)*G17/10000 -> 97.252261 | H28: =(H20+H21)*H17/10000 -> 106.40564 | I28: =(I20+I21)*I17/10000 -> 117.42602 | J28: =(J20+J21)*J17/10000 -> 126.62028 | K28: =(K20+K21)*K17/10000 -> 135.48697 | L28: 2022–23A=电厂运行维护费+其他成本（年报成本分析表）
A29: 营业成本合计 | B29: 亿元 | C29: 387.56965 | D29: 415.09673 | E29: 441.15696 | F29: 481.61107 | G29: =SUM(G24:G28) -> 516.25928 | H29: =SUM(H24:H28) -> 589.84386 | I29: =SUM(I24:I28) -> 673.08222 | J29: =SUM(J24:J28) -> 734.47298 | K29: =SUM(K24:K28) -> 785.78927 | M29: 243.92926 | N29: =IFERROR(M29/G29,"") -> 0.4724937
A30: 毛利 Gross profit | B30: 亿元 | C30: =C7-C29 -> 325.28636 | D30: =D7-D29 -> 334.47507 | E30: =E7-E29 -> 331.56363 | F30: =F7-F29 -> 339.14388 | G30: =G7-G29 -> 291.16789 | H30: =H7-H29 -> 318.87092 | I30: =I7-I29 -> 341.59168 | J30: =J7-J29 -> 361.65052 | K30: =K7-K29 -> 386.48731
A31: 毛利率 | B31: % | C31: =C30/C7 -> 0.45631426 | D31: =D30/D7 -> 0.44622152 | E31: =E30/E7 -> 0.42908606 | F31: =F30/F7 -> 0.41320967 | G31: =G30/G7 -> 0.36061195 | H31: =H30/H7 -> 0.3509032 | I31: =I30/I7 -> 0.33665168 | J31: =J30/J7 -> 0.32993593 | K31: =K30/K7 -> 0.32968953
A33: 期间费用及其他 Opex & other items
A34: 税金及附加/收入 | B34: % | C34: =C35/C7 -> 0.012235276 | D34: =D35/D7 -> 0.013763407 | E34: =E35/E7 -> 0.013934421 | F34: =F35/F7 -> 0.015066874 | G34: 0.0151 | H34: 0.0151 | I34: 0.0151 | J34: 0.0151 | K34: 0.0151
A35: 税金及附加 | B35: 亿元 | C35: 8.7219897 | D35: 10.316661 | E35: 10.767414 | F35: 12.366211 | G35: =G7*G34 -> 12.19215 | H35: =H7*H34 -> 13.721593 | I35: =I7*I34 -> 15.321576 | J35: =J7*J34 -> 16.551465 | K35: =K7*K34 -> 17.701376 | M35: 6.3786891 | N35: =IFERROR(M35/G35,"") -> 0.52317999
A36: 销售费用/收入 | B36: % | C36: =C37/C7 -> 0.0010903126 | D36: =D37/D7 -> 0.001535668 | E36: =E37/E7 -> 0.00080872319 | F36: =F37/F7 -> 0.0012144612 | G36: 0.0012 | H36: 0.0012 | I36: 0.0012 | J36: 0.0012 | K36: 0.0012
A37: 销售费用 | B37: 亿元 | C37: 0.7772359 | D37: 1.1510935 | E37: 0.62491706 | F37: 0.99677502 | G37: =G7*G36 -> 0.96891261 | H37: =H7*H36 -> 1.0904577 | I37: =I7*I36 -> 1.2176087 | J37: =J7*J36 -> 1.3153482 | K37: =K7*K36 -> 1.4067319
A38: 管理费用增速 | B38: % | G38: -0.12 | H38: 0.03 | I38: 0.03 | J38: 0.03 | K38: 0.03 | L38: 2026H1 管理费用 -14.68%（薪酬结构调整、成本管控）
A39: 管理费用 | B39: 亿元 | C39: 46.185416 | D39: 38.282356 | E39: 40.270412 | F39: 41.186341 | G39: =F39*(1+G38) -> 36.24398 | H39: =G39*(1+H38) -> 37.331299 | I39: =H39*(1+I38) -> 38.451238 | J39: =I39*(1+J38) -> 39.604775 | K39: =J39*(1+K38) -> 40.792919 | M39: 15.347234 | N39: =IFERROR(M39/G39,"") -> 0.4234423
A40: 研发费用/收入 | B40: % | C40: =C41/C7 -> 0.019610064 | D40: =D41/D7 -> 0.01846106 | E40: =E41/E7 -> 0.017788808 | F40: =F41/F7 -> 0.017540044 | G40: 0.016 | H40: 0.0175 | I40: 0.0175 | J40: 0.0175 | K40: 0.0175 | L40: 2026H1 研发 3.62 亿（研发支出下半年集中）
A41: 研发费用 | B41: 亿元 | C41: 13.979152 | D41: 13.83789 | E41: 13.745778 | F41: 14.396078 | G41: =G7*G40 -> 12.918835 | H41: =H7*H40 -> 15.902509 | I41: =I7*I40 -> 17.756793 | J41: =J7*J40 -> 19.182161 | K41: =K7*K40 -> 20.51484 | M41: 3.620268 | N41: =IFERROR(M41/G41,"") -> 0.28023177
A42: 有息负债综合利率（期初余额） | B42: % | G42: 0.023 | H42: 0.022 | I42: 0.0215 | J42: 0.0215 | K42: 0.0215 | L42: 2025A 校准：(65.40 利息费用+约 31 资本化)/期初有息负债 3,839 ≈ 2.45%；新增借款利率约 1.6–2.3%
A43: 利息资本化率（期初在建工程） | B43: % | G43: 0.013 | H43: 0.013 | I43: 0.013 | J43: 0.013 | K43: 0.013 | L43: 2025 年报：重大在建工程本期利息资本化 31.87 亿
A44: 其中：利息费用 | B44: 亿元 | C44: 76.409893 | D44: 69.337257 | E44: 67.099447 | F44: 65.398222 | G44: ='Balance Sheet'!F77*G42-'Balance Sheet'!F20*G43 -> 71.160934 | H44: ='Balance Sheet'!G77*H42-'Balance Sheet'!G20*H43 -> 72.316708 | I44: ='Balance Sheet'!H77*I42-'Balance Sheet'!H20*I43 -> 83.877339 | J44: ='Balance Sheet'!I77*J42-'Balance Sheet'!I20*J43 -> 89.676515 | K44: ='Balance Sheet'!J77*K42-'Balance Sheet'!J20*K43 -> 97.027885 | M44: 33.786572 | N44: =IFERROR(M44/G44,"") -> 0.47479101
A45: 存款利率（期初货币资金） | B45: % | G45: 0.009 | H45: 0.009 | I45: 0.009 | J45: 0.009 | K45: 0.009 | L45: 2025A 1.45/197.38≈0.7%–0.9%
A46: 减：利息收入 | B46: 亿元 | C46: 2.0783818 | D46: 1.8277831 | E46: 1.5554526 | F46: 1.449198 | G46: ='Balance Sheet'!F7*G45 -> 1.4023478 | H46: ='Balance Sheet'!G7*H45 -> 1.308032 | I46: ='Balance Sheet'!H7*I45 -> 1.472118 | J46: ='Balance Sheet'!I7*J45 -> 1.6437717 | K46: ='Balance Sheet'!J7*K45 -> 1.7757201
A47: 其他财务费用（汇兑、手续费等） | B47: 亿元 | C47: =C48-C44+C46 -> 7.1135988 | D47: =D48-D44+D46 -> 5.5079639 | E47: =E48-E44+E46 -> 2.8919786 | F47: =F48-F44+F46 -> 4.3958126 | G47: 4 | H47: 4 | I47: 4 | J47: 4 | K47: 4
A48: 财务费用 | B48: 亿元 | C48: 81.44511 | D48: 73.017438 | E48: 68.435973 | F48: 68.344836 | G48: =G44-G46+G47 -> 73.758586 | H48: =H44-H46+H47 -> 75.008676 | I48: =I44-I46+I47 -> 86.405221 | J48: =J44-J46+J47 -> 92.032743 | K48: =K44-K46+K47 -> 99.252165 | M48: 35.072999 | N48: =IFERROR(M48/G48,"") -> 0.47551072
A49: 加：其他收益（增值税退税等） | B49: 亿元 | C49: 21.113832 | D49: 27.107082 | E49: 27.526228 | F49: 31.503853 | G49: =G9*'Scenarios'!G60 -> 29.477615 | H49: =H9*'Scenarios'!H60 -> 32.983325 | I49: =I9*'Scenarios'!I60 -> 36.563405 | J49: =J9*'Scenarios'!J60 -> 38.942807 | K49: =K9*'Scenarios'!K60 -> 40.851542 | M49: 12.315323 | N49: =IFERROR(M49/G49,"") -> 0.41778562
A50: 投资收益 | B50: 亿元 | C50: 2.752364 | D50: 3.8207071 | E50: 4.1072614 | F50: 3.0864305 | G50: =G52+G53 -> 3.20943 | H50: =H52+H53 -> 3.3549015 | I50: =I52+I53 -> 3.5076465 | J50: =J52+J53 -> 3.6680289 | K50: =K52+K53 -> 3.8364303 | M50: 0.84907574 | N50: =IFERROR(M50/G50,"") -> 0.26455656
A51: 联营合营收益增速 | B51: % | G51: 0.05 | H51: 0.05 | I51: 0.05 | J51: 0.05 | K51: 0.05
A52: 其中：对联营合营企业投资收益 | B52: 亿元 | C52: 2.6904652 | D52: 3.7636824 | E52: 3.3882882 | F52: 2.7708857 | G52: =F52*(1+G51) -> 2.90943 | H52: =G52*(1+H51) -> 3.0549015 | I52: =H52*(1+I51) -> 3.2076465 | J52: =I52*(1+J51) -> 3.3680289 | K52: =J52*(1+K51) -> 3.5364303
A53: 其他投资收益（现金） | B53: 亿元 | C53: =C50-C52 -> 0.061898834 | D53: =D50-D52 -> 0.057024684 | E53: =E50-E52 -> 0.71897321 | F53: =F50-F52 -> 0.31554478 | G53: 0.3 | H53: 0.3 | I53: 0.3 | J53: 0.3 | K53: 0.3
A54: 公允价值变动收益 | B54: 亿元 | C54: 0.0004824547 | D54: 0.0015586998 | E54: 0 | F54: 0 | G54: 0 | H54: 0 | I54: 0 | J54: 0 | K54: 0
A55: 信用减值损失 | B55: 亿元 | C55: 0.87265327 | D55: -0.83733888 | E55: -0.65902374 | F55: -0.23533976 | G55: -0.3 | H55: -0.3 | I55: -0.3 | J55: -0.3 | K55: -0.3
A56: 资产减值损失 | B56: 亿元 | C56: -2.4754308 | D56: -2.0821848 | E56: -4.9857074 | F56: -4.9585678 | G56: -5 | H56: -5 | I56: -5 | J56: -5 | K56: -5 | L56: 主要为新能源项目及在建工程减值
A57: 资产处置收益 | B57: 亿元 | C57: 0.010422017 | D57: 0.57929545 | E57: 0.1123051 | F57: -0.027292034 | G57: 0 | H57: 0 | I57: 0 | J57: 0 | K57: 0
A58: 其他（报表其余项目） | B58: 亿元 | C58: =C59-(C7-C29-C35-C37-C39-C41-C48+C49+C50+C54+C55+C56+C57) -> 1.7053026e-13 | D58: =D59-(D7-D29-D35-D37-D39-D41-D48+D49+D50+D54+D55+D56+D57) -> -5.6843419e-14 | E58: =E59-(E7-E29-E35-E37-E39-E41-E48+E49+E50+E54+E55+E56+E57) -> 2.8421709e-14 | F58: =F59-(F7-F29-F35-F37-F39-F41-F48+F49+F50+F54+F55+F56+F57) -> 0 | G58: 0 | H58: 0 | I58: 0 | J58: 0 | K58: 0
A59: 营业利润 Operating profit | B59: 亿元 | C59: 196.45178 | D59: 226.45875 | E59: 223.8202 | F59: 231.22273 | G59: =G7-G29-G35-G37-G39-G41-G48+G49+G50+G54+G55+G56+G57+G58 -> 182.47247 | H59: =H7-H29-H35-H37-H39-H41-H48+H49+H50+H54+H55+H56+H57+H58 -> 206.85461 | I59: =I7-I29-I35-I37-I39-I41-I48+I49+I50+I54+I55+I56+I57+I58 -> 217.21029 | J59: =J7-J29-J35-J37-J39-J41-J48+J49+J50+J54+J55+J56+J57+J58 -> 230.27487 | K59: =K7-K29-K35-K37-K39-K41-K48+K49+K50+K54+K55+K56+K57+K58 -> 246.20725 | M59: 92.149505 | N59: =IFERROR(M59/G59,"") -> 0.50500497
A60: 加：营业外收入 | B60: 亿元 | C60: 0.43656631 | D60: 4.5910363 | E60: 2.600014 | F60: 2.7670827 | G60: 2.5 | H60: 2.5 | I60: 2.5 | J60: 2.5 | K60: 2.5
A61: 减：营业外支出 | B61: 亿元 | C61: 1.1905966 | D61: 1.2382113 | E61: 0.78106216 | F61: 1.0991295 | G61: 1 | H61: 1 | I61: 1 | J61: 1 | K61: 1
A62: 利润总额 Pre-tax profit | B62: 亿元 | C62: 195.69775 | D62: 229.81158 | E62: 225.63915 | F62: 232.89068 | G62: =G59+G60-G61 -> 183.97247 | H62: =H59+H60-H61 -> 208.35461 | I62: =I59+I60-I61 -> 218.71029 | J62: =J59+J60-J61 -> 231.77487 | K62: =K59+K60-K61 -> 247.70725 | M62: 92.916684 | N62: =IFERROR(M62/G62,"") -> 0.50505754
A63: 实际税率 | B63: % | C63: =C64/C62 -> 0.16591482 | D63: =D64/D62 -> 0.15536802 | E63: =E64/E62 -> 0.26639082 | F63: =F64/F62 -> 0.22836854 | G63: 0.235 | H63: 0.235 | I63: 0.235 | J63: 0.235 | K63: 0.235 | L63: 2024A 26.6% / 2025A 22.8%；部分子公司享受西部大开发/高新技术 15% 及三免三减半
A64: 减：所得税费用 | B64: 亿元 | C64: 32.469156 | D64: 35.705371 | E64: 60.108199 | F64: 53.184904 | G64: =G62*G63 -> 43.233531 | H64: =H62*H63 -> 48.963334 | I64: =I62*I63 -> 51.396919 | J64: =J62*J63 -> 54.467094 | K64: =K62*K63 -> 58.211204 | M64: 21.827606 | N64: =IFERROR(M64/G64,"") -> 0.50487679
A65: 净利润 Net profit | B65: 亿元 | C65: 163.22859 | D65: 194.10621 | E65: 165.53095 | F65: 179.70578 | G65: =G62-G64 -> 140.73894 | H65: =H62-H64 -> 159.39128 | I65: =I62-I64 -> 167.31337 | J65: =J62-J64 -> 177.30777 | K65: =K62-K64 -> 189.49605 | M65: 71.089078 | N65: =IFERROR(M65/G65,"") -> 0.50511307
A66: 少数股东损益占比 | B66: % | C66: =C67/C65 -> 0.44799214 | D66: =D67/D65 -> 0.4526797 | E66: =E67/E65 -> 0.46974617 | F66: =F67/F65 -> 0.48225306 | G66: 0.485 | H66: 0.485 | I66: 0.485 | J66: 0.485 | K66: 0.485 | L66: 2024A 47.0% / 2025A 48.2% / 2026H1 48.8%；核电项目多为 50–72% 控股，中核汇能持股 62.71%
A67: 少数股东损益 | B67: 亿元 | C67: 73.125126 | D67: 87.86794 | E67: 77.75753 | F67: 86.663661 | G67: =G65*G66 -> 68.258386 | H67: =H65*H66 -> 77.30477 | I67: =I65*I66 -> 81.146986 | J67: =J65*J66 -> 85.99427 | K67: =K65*K66 -> 91.905583 | M67: 34.67754 | N67: =IFERROR(M67/G67,"") -> 0.50803341
A68: 归属于母公司股东的净利润 | B68: 亿元 | C68: 90.103466 | D68: 106.23827 | E68: 87.773421 | F68: 93.042115 | G68: =G65-G67 -> 72.480554 | H68: =H65-H67 -> 82.086509 | I68: =I65-I67 -> 86.166387 | J68: =J65-J67 -> 91.313503 | K68: =K65-K67 -> 97.590465 | M68: 36.411537 | N68: =IFERROR(M68/G68,"") -> 0.50236285
A69: 同比 YoY | B69: % | D69: =D68/C68-1 -> 0.1790697 | E69: =E68/D68-1 -> -0.17380598 | F69: =F68/E68-1 -> 0.060026086 | G69: =G68/F68-1 -> -0.22099198 | H69: =H68/G68-1 -> 0.13253147 | I69: =I68/H68-1 -> 0.04970218 | J69: =J68/I68-1 -> 0.059734619 | K69: =K68/J68-1 -> 0.068740776
A70: 减：永续债持有人分配 | B70: 亿元 | F70: 0.2626 | G70: 0.2626 | H70: 0.2626 | I70: 0.2626 | J70: 0.2626 | K70: 0.2626 | L70: 永续债 10 亿元；2025A 归母 93.04 − 普通股东 92.78
A71: 归属于普通股股东净利润 | B71: 亿元 | C71: =C68 -> 90.103466 | D71: =D68 -> 106.23827 | E71: =E68 -> 87.773421 | F71: =F68-F70 -> 92.779515 | G71: =G68-G70 -> 72.217954 | H71: =H68-H70 -> 81.823909 | I71: =I68-I70 -> 85.903787 | J71: =J68-J70 -> 91.050903 | K71: =K68-K70 -> 97.327865
A73: 每股数据 Per share
A74: 加权平均股本 | B74: 亿股 | C74: 188.83 | D74: 188.83 | E74: 188.83 | F74: 204.82 | G74: 205.14 | H74: 205.14 | I74: 205.14 | J74: 205.14 | K74: 205.14 | L74: 2025 年 1 月定增后总股本 205.68 亿；剔除库存股约 0.54 亿（2026 中期分红股本基数 205.14 亿）
A75: 基本每股收益 EPS | B75: 元/股 | C75: 0.468 | D75: 0.554 | E75: 0.463 | F75: 0.453 | G75: =G71/G74 -> 0.35204228 | H75: =H71/H74 -> 0.39886862 | I75: =I71/I74 -> 0.41875688 | J75: =J71/J74 -> 0.44384763 | K75: =K71/K74 -> 0.47444606
A76: 稀释每股收益 Diluted EPS | B76: 元/股 | C76: 0.467 | D76: 0.554 | E76: 0.463 | F76: 0.453 | G76: =G75 -> 0.35204228 | H76: =H75 -> 0.39886862 | I76: =I75 -> 0.41875688 | J76: =J75 -> 0.44384763 | K76: =K75 -> 0.47444606
A77: 现金分红率（归属普通股） | B77: % | D77: 0.352 | F77: 0.398 | G77: 0.4 | H77: 0.4 | I77: 0.4 | J77: 0.4 | K77: 0.4 | L77: 公司承诺≥35%；2025A 39.80%（含中期 0.02 元）
A78: 每股股利 DPS | B78: 元/股 | D78: 0.195 | F78: 0.18 | G78: =G75*G77 -> 0.14081691 | H78: =H75*H77 -> 0.15954745 | I78: =I75*I77 -> 0.16750275 | J78: =J75*J77 -> 0.17753905 | K78: =K75*K77 -> 0.18977842
A80: 利润率与 EBITDA Margins
A81: 折旧摊销合计 D&A | B81: 亿元 | C81: ='Cash Flow'!C8+'Cash Flow'!C9 -> 158.68314 | D81: ='Cash Flow'!D8+'Cash Flow'!D9 -> 167.86841 | E81: ='Cash Flow'!E8+'Cash Flow'!E9 -> 183.09572 | F81: ='Cash Flow'!F8+'Cash Flow'!F9 -> 216.02631 | G81: ='Cash Flow'!G8+'Cash Flow'!G9 -> 233.18518 | H81: ='Cash Flow'!H8+'Cash Flow'!H9 -> 265.07745 | I81: ='Cash Flow'!I8+'Cash Flow'!I9 -> 298.94412 | J81: ='Cash Flow'!J8+'Cash Flow'!J9 -> 319.31429 | K81: ='Cash Flow'!K8+'Cash Flow'!K9 -> 331.00202
A82: EBIT（经营口径：利润总额+财务费用−投资收益−营业外净额） | B82: 亿元 | C82: =C62+C48-C50-C60+C61 -> 275.14452 | D82: =D62+D48-D50-D60+D61 -> 295.65548 | E82: =E62+E48-E50-E60+E61 -> 288.14891 | F82: =F62+F48-F50-F60+F61 -> 296.48113 | G82: =G62+G48-G50-G60+G61 -> 253.02163 | H82: =H62+H48-H50-H60+H61 -> 278.50839 | I82: =I62+I48-I50-I60+I61 -> 300.10787 | J82: =J62+J48-J50-J60+J61 -> 318.63958 | K82: =K62+K48-K50-K60+K61 -> 341.62299
A83: EBITDA | B83: 亿元 | C83: =C82+C81 -> 433.82767 | D83: =D82+D81 -> 463.52389 | E83: =E82+E81 -> 471.24463 | F83: =F82+F81 -> 512.50744 | G83: =G82+G81 -> 486.2068 | H83: =H82+H81 -> 543.58583 | I83: =I82+I81 -> 599.05198 | J83: =J82+J81 -> 637.95387 | K83: =K82+K81 -> 672.625
A84: EBITDA 利润率 | B84: % | C84: =C83/C7 -> 0.60857685 | D84: =D83/D7 -> 0.61838491 | E84: =E83/E7 -> 0.60985127 | F84: =F83/F7 -> 0.62443417 | G84: =G83/G7 -> 0.602168 | H84: =H83/H7 -> 0.59819191 | I84: =I83/I7 -> 0.59038868 | J84: =J83/J7 -> 0.58200911 | K84: =K83/K7 -> 0.57377671
A85: EBIT 利润率 | B85: % | C85: =C82/C7 -> 0.3859749 | D85: =D82/D7 -> 0.3944325 | E85: =E82/E7 -> 0.37290182 | F85: =F82/F7 -> 0.36122978 | G85: =G82/G7 -> 0.31336774 | H85: =H82/H7 -> 0.30648603 | I85: =I82/I7 -> 0.2957678 | J85: =J82/J7 -> 0.29069679 | K85: =K82/K7 -> 0.29141842
A86: 净利率（归母） | B86: % | C86: =C68/C7 -> 0.12639785 | D86: =D68/D7 -> 0.14173194 | E86: =E68/E7 -> 0.11359012 | F86: =F68/F7 -> 0.11336163 | G86: =G68/G7 -> 0.089767296 | H86: =H68/H7 -> 0.090332533 | I86: =I68/I7 -> 0.084920276 | J86: =J68/J7 -> 0.083305853 | K86: =K68/K7 -> 0.083248668
A87: ROE（归母，期末） | B87: % | C87: =C68/'Balance Sheet'!C57 -> 0.1015445 | D87: =D68/'Balance Sheet'!D57 -> 0.11681001 | E87: =E68/'Balance Sheet'!E57 -> 0.079636897 | F87: =F68/'Balance Sheet'!F57 -> 0.078372635 | G87: =G68/'Balance Sheet'!G57 -> 0.05929036 | H87: =H68/'Balance Sheet'!H57 -> 0.064361157 | I87: =I68/'Balance Sheet'!I57 -> 0.064856065 | J87: =J68/'Balance Sheet'!J57 -> 0.065917567 | K87: =K68/'Balance Sheet'!K57 -> 0.067481753

Sheet Cash Flow
A1: 现金流量表 Cash Flow Statement（间接法；历史期取自年报补充资料与主表）
A2: 单位：亿元人民币（另有注明除外）｜蓝色=硬编码输入 黑色=公式 绿色=跨表链接｜A=实际 E=预测
A3: 项目 / Line item | B3: 单位 | C3: 2022 | D3: 2023 | E3: 2024 | F3: 2025 | G3: 2026 | H3: 2027 | I3: 2028 | J3: 2029 | K3: 2030 | L3: 来源 / 说明
A6: 经营活动 Operating activities
A7: 净利润 | B7: 亿元 | C7: 163.22859 | D7: 194.10621 | E7: 165.53095 | F7: 179.70578 | G7: ='Income Statement'!G65 -> 140.73894 | H7: ='Income Statement'!H65 -> 159.39128 | I7: ='Income Statement'!I65 -> 167.31337 | J7: ='Income Statement'!J65 -> 177.30777 | K7: ='Income Statement'!K65 -> 189.49605
A8: 固定资产折旧 | B8: 亿元 | C8: 152.0272 | D8: 160.82455 | E8: 173.32044 | F8: 203.40667 | G8: ='Balance Sheet'!G76 -> 220.58518 | H8: ='Balance Sheet'!H76 -> 252.47745 | I8: ='Balance Sheet'!I76 -> 286.34412 | J8: ='Balance Sheet'!J76 -> 306.71429 | K8: ='Balance Sheet'!K76 -> 318.40202
A9: 使用权资产、无形资产及长期待摊摊销 | B9: 亿元 | C9: =3.1243855123000004+2.1659168306+1.3656393399000002 -> 6.6559417 | D9: =2.9154197232+2.7385706627999995+1.3898663386 -> 7.0438567 | E9: =4.4977654722+3.6613896102999997+1.6161274546000002 -> 9.7752825 | F9: =5.646995999+5.0982287977+1.8744145096 -> 12.619639 | G9: 12.6 | H9: 12.6 | I9: 12.6 | J9: 12.6 | K9: 12.6 | L9: 预测期假设由等额“其他长期资产支出”补充，相关资产余额持平
A10: 资产及信用减值准备 | B10: 亿元 | C10: =-0.8726532698+2.4754308076 -> 1.6027775 | D10: =0.8373388797+2.0821847893000003 -> 2.9195237 | E10: =4.9857073546+0.6590237433 -> 5.6447311 | F10: =4.9585677513999995+0.23533976269999998 -> 5.1939075 | G10: =-('Income Statement'!G56+'Income Statement'!G55) -> 5.3 | H10: =-('Income Statement'!H56+'Income Statement'!H55) -> 5.3 | I10: =-('Income Statement'!I56+'Income Statement'!I55) -> 5.3 | J10: =-('Income Statement'!J56+'Income Statement'!J55) -> 5.3 | K10: =-('Income Statement'!K56+'Income Statement'!K55) -> 5.3
A11: 财务费用（加回，利息在筹资活动列示） | B11: 亿元 | C11: 83.465484 | D11: 74.749879 | E11: 69.842419 | F11: 69.650334 | G11: ='Income Statement'!G48 -> 73.758586 | H11: ='Income Statement'!H48 -> 75.008676 | I11: ='Income Statement'!I48 -> 86.405221 | J11: ='Income Statement'!J48 -> 92.032743 | K11: ='Income Statement'!K48 -> 99.252165
A12: 投资损失（收益以“－”填列） | B12: 亿元 | C12: -2.752364 | D12: -3.8207071 | E12: -4.1072614 | F12: -3.0864305 | G12: =-'Income Statement'!G52*(1-G13) -> -1.454715 | H12: =-'Income Statement'!H52*(1-H13) -> -1.5274507 | I12: =-'Income Statement'!I52*(1-I13) -> -1.6038233 | J12: =-'Income Statement'!J52*(1-J13) -> -1.6840144 | K12: =-'Income Statement'!K52*(1-K13) -> -1.7682151 | L12: 预测：剔除未收现的权益法收益
A13: 联营合营企业收益现金分红比例 | B13: % | G13: 0.5 | H13: 0.5 | I13: 0.5 | J13: 0.5 | K13: 0.5
A14: 存货的减少（增加以“－”） | B14: 亿元 | C14: -18.029645 | D14: -16.451731 | E14: -40.701709 | F14: -56.114369 | G14: ='Balance Sheet'!F13-'Balance Sheet'!G13 -> -37.01244 | H14: ='Balance Sheet'!G13-'Balance Sheet'!H13 -> -73.0945 | I14: ='Balance Sheet'!H13-'Balance Sheet'!I13 -> -37.1925 | J14: ='Balance Sheet'!I13-'Balance Sheet'!J13 -> -53.8675 | K14: ='Balance Sheet'!J13-'Balance Sheet'!K13 -> -17.6175
A15: 经营性应收项目的减少 | B15: 亿元 | C15: 38.297491 | D15: -26.625806 | E15: -53.904374 | F15: -8.3936219 | G15: ='Balance Sheet'!F9+'Balance Sheet'!F11-'Balance Sheet'!G9-'Balance Sheet'!G11 -> 10.715465 | H15: ='Balance Sheet'!G9+'Balance Sheet'!G11-'Balance Sheet'!H9-'Balance Sheet'!H11 -> -33.867526 | I15: ='Balance Sheet'!H9+'Balance Sheet'!H11-'Balance Sheet'!I9-'Balance Sheet'!I11 -> -35.429534 | J15: ='Balance Sheet'!I9+'Balance Sheet'!I11-'Balance Sheet'!J9-'Balance Sheet'!J11 -> -27.234292 | K15: ='Balance Sheet'!J9+'Balance Sheet'!J11-'Balance Sheet'!K9-'Balance Sheet'!K11 -> -25.463296
A16: 经营性应付项目的增加 | B16: 亿元 | C16: 40.527873 | D16: 37.387495 | E16: 81.270713 | F16: -30.025707 | G16: ='Balance Sheet'!G32+'Balance Sheet'!G34-'Balance Sheet'!F32-'Balance Sheet'!F34 -> -27.952632 | H16: ='Balance Sheet'!H32+'Balance Sheet'!H34-'Balance Sheet'!G32-'Balance Sheet'!G34 -> 22.211203 | I16: ='Balance Sheet'!I32+'Balance Sheet'!I34-'Balance Sheet'!H32-'Balance Sheet'!H34 -> 27.602426 | J16: ='Balance Sheet'!J32+'Balance Sheet'!J34-'Balance Sheet'!I32-'Balance Sheet'!I34 -> 21.165715 | K16: ='Balance Sheet'!K32+'Balance Sheet'!K34-'Balance Sheet'!J32-'Balance Sheet'!J34 -> 18.880812
A17: 其他（递延税、处置损益等） | B17: 亿元 | C17: =C18-SUM(C7:C11)-C12-C14-C15-C16 -> 1.9548267 | D17: =D18-SUM(D7:D11)-D12-D14-D15-D16 -> 1.1274806 | E17: =E18-SUM(E7:E11)-E12-E14-E15-E16 -> 0.53414032 | F17: =F18-SUM(F7:F11)-F12-F14-F15-F16 -> 1.1277717 | G17: 0 | H17: 0 | I17: 0 | J17: 0 | K17: 0
A18: 经营活动现金流量净额 CFO | B18: 亿元 | C18: 466.97817 | D18: 431.26075 | E18: 407.20533 | F18: 374.08397 | G18: =SUM(G7:G11)+G12+G14+G15+G16+G17 -> 397.27838 | H18: =SUM(H7:H11)+H12+H14+H15+H16+H17 -> 418.49913 | I18: =SUM(I7:I11)+I12+I14+I15+I16+I17 -> 511.33928 | J18: =SUM(J7:J11)+J12+J14+J15+J16+J17 -> 532.33471 | K18: =SUM(K7:K11)+K12+K14+K15+K16+K17 -> 599.08203
A20: 投资活动 Investing activities
A21: 核电基础资本开支计划（正数） | B21: 亿元 | G21: 700 | H21: 740 | I21: 780 | J21: 800 | K21: 820 | L21: 在建及核准 22 台、预算合计约 4,900 亿；2026H1 购建长期资产 346 亿（-19.5%）。牛/熊情景超支见 Scenarios
A22: 核电资本开支 | B22: 亿元 | G22: =-G21*(1+'Scenarios'!G72) -> -700 | H22: =-H21*(1+'Scenarios'!H72) -> -740 | I22: =-I21*(1+'Scenarios'!I72) -> -780 | J22: =-J21*(1+'Scenarios'!J72) -> -800 | K22: =-K21*(1+'Scenarios'!K72) -> -820
A23: 新能源单位造价 | B23: 元/kW | G23: 3400 | H23: 3400 | I23: 3400 | J23: 3400 | K23: 3400 | L23: 风光综合；含配储
A24: 新能源资本开支 | B24: 亿元 | G24: =-'Scenarios'!G54*G23/10000 -> -119 | H24: =-'Scenarios'!H54*H23/10000 -> -85 | I24: =-'Scenarios'!I54*I23/10000 -> -68 | J24: =-'Scenarios'!J54*J23/10000 -> -68 | K24: =-'Scenarios'!K54*K23/10000 -> -68
A25: 维护性资本开支（计入固定资产） | B25: 亿元 | G25: 20 | H25: 20 | I25: 20 | J25: 20 | K25: 20
A26: 维护性及其他长期资产支出 | B26: 亿元 | G26: =-(G25+G9) -> -32.6 | H26: =-(H25+H9) -> -32.6 | I26: =-(I25+I9) -> -32.6 | J26: =-(J25+J9) -> -32.6 | K26: =-(K25+K9) -> -32.6 | L26: 维护性 + 补充使用权资产/无形资产/长期待摊（使其余额持平）
A27: 购建固定资产、无形资产和其他长期资产支付的现金 | B27: 亿元 | C27: -505.09691 | D27: -671.00346 | E27: -907.08324 | F27: -936.83638 | G27: =G22+G24+G26 -> -851.6 | H27: =H22+H24+H26 -> -857.6 | I27: =I22+I24+I26 -> -880.6 | J27: =J22+J24+J26 -> -900.6 | K27: =K22+K24+K26 -> -920.6
A28: 股权投资（投资支付及取得子公司） | B28: 亿元 | C28: =-(7.609885+23.571262316) -> -31.181147 | D28: =-(16.82098266+35.5248451362) -> -52.345828 | E28: =-(10.7057562237+20.9380719869) -> -31.643828 | F28: =-(17.04755449+1.5061814588999998) -> -18.553736 | G28: -15 | H28: -15 | I28: -15 | J28: -15 | K28: -15
A29: 其他投资活动净额 | B29: 亿元 | C29: =C30-C27-C28 -> 6.1932474 | D29: =D30-D27-D28 -> 6.2339509 | E29: =E30-E27-E28 -> -10.719436 | F29: =F30-F27-F28 -> 8.6050851 | G29: 0 | H29: 0 | I29: 0 | J29: 0 | K29: 0
A30: 投资活动现金流量净额 CFI | B30: 亿元 | C30: -530.08481 | D30: -717.11534 | E30: -949.44651 | F30: -946.78503 | G30: =G27+G28+G29 -> -866.6 | H30: =H27+H28+H29 -> -872.6 | I30: =I27+I28+I29 -> -895.6 | J30: =J27+J28+J29 -> -915.6 | K30: =K27+K28+K29 -> -935.6
A32: 筹资活动 Financing activities
A33: 吸收投资（母公司层面） | B33: 亿元 | C33: =111.76312647209998-101.09238802700001 -> 10.670738 | D33: =120.3587552135-119.2940258486 -> 1.0647294 | E33: =409.34007602180003-269.34307612009997 -> 139.997 | F33: =195.24447228830002-185.24447228830002 -> 10 | G33: 0 | H33: 0 | I33: 0 | J33: 0 | K33: 0 | L33: 2024A 含 140 亿元定增（社保基金会 120 亿 + 中核集团 20 亿）
A34: 少数股东注资/资本开支 | B34: % | C34: =C35/-C27 -> 0.20014454 | D34: =D35/-D27 -> 0.17778452 | E34: =E35/-E27 -> 0.29693314 | F34: =F35/-F27 -> 0.19773407 | G34: 0.15 | H34: 0.15 | I34: 0.15 | J34: 0.15 | K34: 0.15 | L34: 合资方按持股比例出资：2024A 29.7% / 2025A 19.8%
A35: 子公司吸收少数股东投资 | B35: 亿元 | C35: 101.09239 | D35: 119.29403 | E35: 269.34308 | F35: 185.24447 | G35: =-G27*G34 -> 127.74 | H35: =-H27*H34 -> 128.64 | I35: =-I27*I34 -> 132.09 | J35: =-J27*J34 -> 135.09 | K35: =-K27*K34 -> 138.09
A36: 借款净额（取得−偿还） | B36: 亿元 | C36: =1171.6124658227-876.4772562478 -> 295.13521 | D36: =1399.874911287-923.5427706697 -> 476.33214 | E36: =1701.424257634-1140.7662032525 -> 560.65805 | F36: =1948.272447305-1371.5801507603999 -> 576.6923 | G36: =G52-('Balance Sheet'!F7+G18+G30+G33+G35+G37+G39+G40+G42+G43) -> 496.65622 | H36: =H52-('Balance Sheet'!G7+H18+H30+H33+H35+H37+H39+H40+H42+H43) -> 509.69492 | I36: =I52-('Balance Sheet'!H7+I18+I30+I33+I35+I37+I39+I40+I42+I43) -> 455.55833 | J36: =J52-('Balance Sheet'!I7+J18+J30+J33+J35+J37+J39+J40+J42+J43) -> 458.28849 | K36: =K52-('Balance Sheet'!J7+K18+K30+K33+K35+K37+K39+K40+K42+K43) -> 421.59512 | L36: 平衡项：使期末现金=目标现金
A37: 支付普通股股利 | B37: 亿元 | G37: =-'Income Statement'!F71*'Income Statement'!F77 -> -36.926247 | H37: =-'Income Statement'!G71*'Income Statement'!G77 -> -28.887182 | I37: =-'Income Statement'!H71*'Income Statement'!H77 -> -32.729563 | J37: =-'Income Statement'!I71*'Income Statement'!I77 -> -34.361515 | K37: =-'Income Statement'!J71*'Income Statement'!J77 -> -36.420361 | L37: 按上年归属普通股净利润×分红率（次年支付）
A38: 少数股东分红/少数股东损益 | B38: % | G38: 0.8 | H38: 0.8 | I38: 0.8 | J38: 0.8 | K38: 0.8 | L38: 2025A 72.87/86.66=84%
A39: 支付少数股东股利 | B39: 亿元 | C39: -56.677178 | D39: -69.007765 | E39: -69.512489 | F39: -72.86849 | G39: =-'Income Statement'!G67*G38 -> -54.606709 | H39: =-'Income Statement'!H67*H38 -> -61.843816 | I39: =-'Income Statement'!I67*I38 -> -64.917589 | J39: =-'Income Statement'!J67*J38 -> -68.795416 | K39: =-'Income Statement'!K67*K38 -> -73.524466
A40: 偿付利息（=财务费用） | B40: 亿元 | G40: =-'Income Statement'!G48 -> -73.758586 | H40: =-'Income Statement'!H48 -> -75.008676 | I40: =-'Income Statement'!I48 -> -86.405221 | J40: =-'Income Statement'!J48 -> -92.032743 | K40: =-'Income Statement'!K48 -> -99.252165
A41: 历史：分配股利、利润或偿付利息（含少数股东） | B41: 亿元 | C41: -223.1462 | D41: -202.50292 | E41: -219.37495 | F41: -209.25515 | L41: 历史期报表合并列示，预测期拆分为上面三行；本行不参与预测期合计
A42: 永续债分配 | B42: 亿元 | G42: =-'Income Statement'!G70 -> -0.2626 | H42: =-'Income Statement'!H70 -> -0.2626 | I42: =-'Income Statement'!I70 -> -0.2626 | J42: =-'Income Statement'!J70 -> -0.2626 | K42: =-'Income Statement'!K70 -> -0.2626
A43: 其他筹资活动净额 | B43: 亿元 | C43: =C44-C33-C35-C36-C41 -> -89.392652 | D43: =D44-D33-D35-D36-D41 -> -170.86728 | E43: =E44-E33-E35-E36-E41 -> -105.72688 | F43: =F44-F33-F35-F36-F41 -> -32.281557 | G43: 0 | H43: 0 | I43: 0 | J43: 0 | K43: 0
A44: 筹资活动现金流量净额 CFF | B44: 亿元 | C44: 94.359486 | D44: 223.3207 | E44: 644.89631 | F44: 530.40006 | G44: =G33+G35+G36+G37+G39+G40+G42+G43 -> 458.84208 | H44: =H33+H35+H36+H37+H39+H40+H42+H43 -> 472.33264 | I44: =I33+I35+I36+I37+I39+I40+I42+I43 -> 403.33336 | J44: =J33+J35+J36+J37+J39+J40+J42+J43 -> 397.92622 | K44: =K33+K35+K36+K37+K39+K40+K42+K43 -> 350.22553
A46: 现金 Cash
A47: 汇率变动影响 | B47: 亿元 | C47: -0.066036729 | D47: -0.093224326 | E47: -0.1811467 | F47: -0.081181313 | G47: 0 | H47: 0 | I47: 0 | J47: 0 | K47: 0
A48: 现金净增加额 | B48: 亿元 | C48: 31.186818 | D48: -62.627118 | E48: 102.47398 | F48: -42.382187 | G48: =G18+G30+G44+G47 -> -10.479537 | H48: =H18+H30+H44+H47 -> 18.23177 | I48: =I18+I30+I44+I47 -> 19.07264 | J48: =J18+J30+J44+J47 -> 14.660928 | K48: =K18+K30+K44+K47 -> 13.707555
A49: 期初现金 | B49: 亿元 | C49: 124.66737 | D49: 155.85419 | E49: 93.227069 | F49: 195.70105 | G49: ='Balance Sheet'!F7 -> 155.81643 | H49: ='Balance Sheet'!G7 -> 145.33689 | I49: ='Balance Sheet'!H7 -> 163.56866 | J49: ='Balance Sheet'!I7 -> 182.6413 | K49: ='Balance Sheet'!J7 -> 197.30223 | L49: 预测期以资产负债表货币资金为口径（含少量受限资金）
A50: 期末现金 | B50: 亿元 | C50: 155.85419 | D50: 93.227069 | E50: 195.70105 | F50: 153.31887 | G50: =G49+G48 -> 145.33689 | H50: =H49+H48 -> 163.56866 | I50: =I49+I48 -> 182.6413 | J50: =J49+J48 -> 197.30223 | K50: =K49+K48 -> 211.00979
A51: 目标现金/营业收入 | B51: % | G51: 0.18 | H51: 0.18 | I51: 0.18 | J51: 0.18 | K51: 0.18 | L51: 2025A 19.0%
A52: 目标现金余额 | B52: 亿元 | G52: ='Income Statement'!G7*G51 -> 145.33689 | H52: ='Income Statement'!H7*H51 -> 163.56866 | I52: ='Income Statement'!I7*I51 -> 182.6413 | J52: ='Income Statement'!J7*J51 -> 197.30223 | K52: ='Income Statement'!K7*K51 -> 211.00979
A54: 自由现金流 Free cash flow
A55: FCF（CFO+资本开支） | B55: 亿元 | C55: =C18+C27 -> -38.118731 | D55: =D18+D27 -> -239.74271 | E55: =E18+E27 -> -499.87791 | F55: =F18+F27 -> -562.75241 | G55: =G18+G27 -> -454.32162 | H55: =H18+H27 -> -439.10087 | I55: =I18+I27 -> -369.26072 | J55: =J18+J27 -> -368.26529 | K55: =K18+K27 -> -321.51797
A56: FCF/营业收入 | B56: % | C56: =C55/'Income Statement'!C7 -> -0.053473255 | D56: =D55/'Income Statement'!D7 -> -0.31983956 | E56: =E55/'Income Statement'!E7 -> -0.64690642 | F56: =F55/'Income Statement'!F7 -> -0.68565217 | G56: =G55/'Income Statement'!G7 -> -0.56267814 | H56: =H55/'Income Statement'!H7 -> -0.48321088 | I56: =I55/'Income Statement'!I7 -> -0.36392059 | J56: =J55/'Income Statement'!J7 -> -0.33597062 | K56: =K55/'Income Statement'!K7 -> -0.27426801
A57: 资本开支/营业收入 | B57: % | C57: =-C27/'Income Statement'!C7 -> 0.7085539 | D57: =-D27/'Income Statement'!D7 -> 0.89518237 | E57: =-E27/'Income Statement'!E7 -> 1.1738826 | F57: =-F27/'Income Statement'!F7 -> 1.1414325 | G57: =-G27/'Income Statement'!G7 -> 1.0547081 | H57: =-H27/'Income Statement'!H7 -> 0.94375046 | I57: =-I27/'Income Statement'!I7 -> 0.86786504 | J57: =-J27/'Income Statement'!J7 -> 0.82162275 | K57: =-K27/'Income Statement'!K7 -> 0.78530955

Sheet Balance Sheet
A1: 资产负债表 Balance Sheet（合并口径，年末）
A2: 单位：亿元人民币（另有注明除外）｜蓝色=硬编码输入 黑色=公式 绿色=跨表链接｜A=实际 E=预测
A3: 项目 / Line item | B3: 单位 | C3: 2022 | D3: 2023 | E3: 2024 | F3: 2025 | G3: 2026 | H3: 2027 | I3: 2028 | J3: 2029 | K3: 2030 | L3: 来源 / 说明
A6: 流动资产 Current assets
A7: 货币资金 | B7: 亿元 | C7: 161.61672 | D7: 97.738191 | E7: 197.38017 | F7: 155.81643 | G7: ='Cash Flow'!G50 -> 145.33689 | H7: ='Cash Flow'!H50 -> 163.56866 | I7: ='Cash Flow'!I50 -> 182.6413 | J7: ='Cash Flow'!J50 -> 197.30223 | K7: ='Cash Flow'!K50 -> 211.00979 | L7: 预测=现金流量表期末现金（借款为平衡项）
A8: 应收账款周转天数（期末/收入×365） | B8: 天 | C8: =C9/'Income Statement'!C7*365 -> 88.124154 | D8: =D9/'Income Statement'!D7*365 -> 104.03673 | E8: =E9/'Income Statement'!E7*365 -> 116.44048 | F8: =F9/'Income Statement'!F7*365 -> 112.8379 | G8: 110 | H8: 110 | I8: 110 | J8: 110 | K8: 110 | L8: 2025A 112.8 天；含可再生能源补贴应收
A9: 应收账款 | B9: 亿元 | C9: 172.10913 | D9: 213.65205 | E9: 246.50948 | F9: 253.73224 | G9: ='Income Statement'!G7*G8/365 -> 243.33422 | H9: ='Income Statement'!H7*H8/365 -> 273.85925 | I9: ='Income Statement'!I7*I8/365 -> 305.79213 | J9: ='Income Statement'!J7*J8/365 -> 330.33859 | K9: ='Income Statement'!K7*K8/365 -> 353.28883
A10: 预付款项/收入 | B10: % | C10: =C11/'Income Statement'!C7 -> 0.039193036 | D10: =D11/'Income Statement'!D7 -> 0.064639039 | E10: =E11/'Income Statement'!E7 -> 0.035503402 | F10: =F11/'Income Statement'!F7 -> 0.032850903 | G10: 0.033 | H10: 0.033 | I10: 0.033 | J10: 0.033 | K10: 0.033
A11: 预付款项 | B11: 亿元 | C11: 27.938991 | D11: 48.451601 | E11: 27.43421 | F11: 26.962542 | G11: ='Income Statement'!G7*G10 -> 26.645097 | H11: ='Income Statement'!H7*H10 -> 29.987588 | I11: ='Income Statement'!I7*I10 -> 33.484239 | J11: ='Income Statement'!J7*J10 -> 36.172075 | K11: ='Income Statement'!K7*K10 -> 38.685127
A12: 存货/核电年末装机 | B12: 元/kW | C12: =C13*10000/'Revenue Model'!C41 -> 1044.5991 | D12: =D13*10000/'Revenue Model'!D41 -> 1112.5311 | E12: =E13*10000/'Revenue Model'!E41 -> 1299.3708 | F12: =F13*10000/'Revenue Model'!F41 -> 1452.8662 | G12: 1450 | H12: 1450 | I12: 1450 | J12: 1450 | K12: 1450 | L12: 存货主要为核燃料（含新机组首炉料）；2025A 1,453 元/kW
A13: 存货 | B13: 亿元 | C13: 248.09228 | D13: 264.22613 | E13: 308.60056 | F13: 363.21656 | G13: ='Revenue Model'!G41*G12/10000 -> 400.229 | H13: ='Revenue Model'!H41*H12/10000 -> 473.3235 | I13: ='Revenue Model'!I41*I12/10000 -> 510.516 | J13: ='Revenue Model'!J41*J12/10000 -> 564.3835 | K13: ='Revenue Model'!K41*K12/10000 -> 582.001
A14: 其他流动资产项目（票据、其他应收、合同资产、其他流动资产等） | B14: 亿元 | C14: =C64-C7-C9-C11-C13 -> 47.847053 | D14: =D64-D7-D9-D11-D13 -> 58.335359 | E14: =E64-E7-E9-E11-E13 -> 61.892359 | F14: =F64-F7-F9-F11-F13 -> 61.046516 | G14: =F14 -> 61.046516 | H14: =G14 -> 61.046516 | I14: =H14 -> 61.046516 | J14: =I14 -> 61.046516 | K14: =J14 -> 61.046516
A15: 流动资产合计 | B15: 亿元 | C15: =C7+C9+C11+C13+C14 -> 657.60417 | D15: =D7+D9+D11+D13+D14 -> 682.40333 | E15: =E7+E9+E11+E13+E14 -> 841.81678 | F15: =F7+F9+F11+F13+F14 -> 860.77428 | G15: =G7+G9+G11+G13+G14 -> 876.59172 | H15: =H7+H9+H11+H13+H14 -> 1001.7855 | I15: =I7+I9+I11+I13+I14 -> 1093.4802 | J15: =J7+J9+J11+J13+J14 -> 1189.2429 | K15: =K7+K9+K11+K13+K14 -> 1246.0313
A17: 非流动资产 Non-current assets
A18: 长期股权投资 | B18: 亿元 | C18: 56.845889 | D18: 75.799619 | E18: 84.11163 | F18: 103.85289 | G18: =F18+'Cash Flow'!G28*-1+'Income Statement'!G52*(1-'Cash Flow'!G13) -> 120.3076 | H18: =G18+'Cash Flow'!H28*-1+'Income Statement'!H52*(1-'Cash Flow'!H13) -> 136.83505 | I18: =H18+'Cash Flow'!I28*-1+'Income Statement'!I52*(1-'Cash Flow'!I13) -> 153.43887 | J18: =I18+'Cash Flow'!J28*-1+'Income Statement'!J52*(1-'Cash Flow'!J13) -> 170.12289 | K18: =J18+'Cash Flow'!K28*-1+'Income Statement'!K52*(1-'Cash Flow'!K13) -> 186.8911
A19: 固定资产 | B19: 亿元 | C19: 2690.3165 | D19: 2769.2238 | E19: 2992.3683 | F19: 3520.164 | G19: =F19+G74-G76+'Income Statement'!G56+'Income Statement'!G55 -> 3731.4144 | H19: =G19+H74-H76+'Income Statement'!H56+'Income Statement'!H55 -> 4569.3656 | I19: =H19+I74-I76+'Income Statement'!I56+'Income Statement'!I55 -> 4845.5705 | J19: =I19+J74-J76+'Income Statement'!J56+'Income Statement'!J55 -> 5239.5096 | K19: =J19+K74-K76+'Income Statement'!K56+'Income Statement'!K55 -> 5230.077 | L19: 减值（含信用减值，简化处理）冲减固定资产
A20: 在建工程 | B20: 亿元 | C20: 1015.1365 | D20: 1535.7484 | E20: 2157.6575 | F20: 2400.7903 | G20: =F20+'Cash Flow'!G22*-1-G73 -> 2810.0012 | H20: =G20+'Cash Flow'!H22*-1-H73 -> 2573.3874 | I20: =H20+'Cash Flow'!I22*-1-I73 -> 2880.7203 | J20: =I20+'Cash Flow'!J22*-1-J73 -> 3073.169 | K20: =J20+'Cash Flow'!K22*-1-K73 -> 3670.3015
A21: 使用权资产 | B21: 亿元 | C21: 36.654379 | D21: 53.931421 | E21: 75.194289 | F21: 65.056554 | G21: =F21 -> 65.056554 | H21: =G21 -> 65.056554 | I21: =H21 -> 65.056554 | J21: =I21 -> 65.056554 | K21: =J21 -> 65.056554
A22: 无形资产及开发支出 | B22: 亿元 | C22: =21.3415446971+10.1131972989 -> 31.454742 | D22: =27.3593504756+10.6744070449 -> 38.033758 | E22: =61.6184069488+12.552001311 -> 74.170408 | F22: =76.7969866952+17.0364609441 -> 93.833448 | G22: =F22 -> 93.833448 | H22: =G22 -> 93.833448 | I22: =H22 -> 93.833448 | J22: =I22 -> 93.833448 | K22: =J22 -> 93.833448
A23: 商誉 | B23: 亿元 | C23: 39.368934 | D23: 56.105702 | E23: 57.705712 | F23: 54.188855 | G23: =F23 -> 54.188855 | H23: =G23 -> 54.188855 | I23: =H23 -> 54.188855 | J23: =I23 -> 54.188855 | K23: =J23 -> 54.188855
A24: 其他非流动资产 | B24: 亿元 | C24: 85.317455 | D24: 147.57203 | E24: 278.68643 | F24: 357.6013 | G24: =F24 -> 357.6013 | H24: =G24 -> 357.6013 | I24: =H24 -> 357.6013 | J24: =I24 -> 357.6013 | K24: =J24 -> 357.6013 | L24: 含预付设备款、待抵扣进项税等
A25: 其余非流动资产项目（递延所得税资产、长期待摊、投资性房地产等） | B25: 亿元 | C25: =C65-C18-C19-C20-C21-C22-C23-C24 -> 35.813105 | D25: =D65-D18-D19-D20-D21-D22-D23-D24 -> 33.854377 | E25: =E65-E18-E19-E20-E21-E22-E23-E24 -> 35.68066 | F25: =F65-F18-F19-F20-F21-F22-F23-F24 -> 36.358254 | G25: =F25 -> 36.358254 | H25: =G25 -> 36.358254 | I25: =H25 -> 36.358254 | J25: =I25 -> 36.358254 | K25: =J25 -> 36.358254
A26: 非流动资产合计 | B26: 亿元 | C26: =SUM(C18:C25) -> 3990.9075 | D26: =SUM(D18:D25) -> 4710.2692 | E26: =SUM(E18:E25) -> 5755.5749 | F26: =SUM(F18:F25) -> 6631.8457 | G26: =SUM(G18:G25) -> 7268.7616 | H26: =SUM(H18:H25) -> 7886.6264 | I26: =SUM(I18:I25) -> 8486.7681 | J26: =SUM(J18:J25) -> 9089.8399 | K26: =SUM(K18:K25) -> 9694.3081
A27: 资产总计 Total assets | B27: 亿元 | C27: =C15+C26 -> 4648.5117 | D27: =D15+D26 -> 5392.6725 | E27: =E15+E26 -> 6597.3917 | F27: =F15+F26 -> 7492.6199 | G27: =G15+G26 -> 8145.3534 | H27: =H15+H26 -> 8888.412 | I27: =I15+I26 -> 9580.2483 | J27: =J15+J26 -> 10279.083 | K27: =K15+K26 -> 10940.339
A29: 流动负债 Current liabilities
A30: 短期借款 | B30: 亿元 | C30: 153.64517 | D30: 198.64355 | E30: 290.75734 | F30: 252.71883 | G30: =F30 -> 252.71883 | H30: =G30 -> 252.71883 | I30: =H30 -> 252.71883 | J30: =I30 -> 252.71883 | K30: =J30 -> 252.71883
A31: 应付票据及账款/(营业成本+资本开支) | B31: % | C31: =C32/('Income Statement'!C29+'Cash Flow'!C27*-1) -> 0.23008577 | D31: =D32/('Income Statement'!D29+'Cash Flow'!D27*-1) -> 0.20631221 | E31: =E32/('Income Statement'!E29+'Cash Flow'!E27*-1) -> 0.19926978 | F31: =F32/('Income Statement'!F29+'Cash Flow'!F27*-1) -> 0.20208528 | G31: 0.19 | H31: 0.19 | I31: 0.19 | J31: 0.19 | K31: 0.19 | L31: 应付账款中工程款占比高，故与成本+资本开支挂钩
A32: 应付票据及应付账款 | B32: 亿元 | C32: =1.5756649677+203.8142032266 -> 205.38987 | D32: =21.9199185291+202.1558134566 -> 224.07573 | E32: =17.843259445+250.82026161459999 -> 268.66352 | F32: =20.5764810348+266.0708726469 -> 286.64735 | G32: =('Income Statement'!G29-'Cash Flow'!G27)*G31 -> 259.89326 | H32: =('Income Statement'!H29-'Cash Flow'!H27)*H31 -> 275.01433 | I32: =('Income Statement'!I29-'Cash Flow'!I27)*I31 -> 295.19962 | J32: =('Income Statement'!J29-'Cash Flow'!J27)*J31 -> 310.66387 | K32: =('Income Statement'!K29-'Cash Flow'!K27)*K31 -> 324.21396
A33: 应交税费/收入 | B33: % | C33: =C34/'Income Statement'!C7 -> 0.054814688 | D33: =D34/'Income Statement'!D7 -> 0.056979586 | E33: =E34/'Income Statement'!E7 -> 0.091351132 | F33: =F34/'Income Statement'!F7 -> 0.070323601 | G33: 0.07 | H33: 0.07 | I33: 0.07 | J33: 0.07 | K33: 0.07
A34: 应交税费 | B34: 亿元 | C34: 39.07498 | D34: 42.710291 | E34: 70.5889 | F34: 57.718444 | G34: ='Income Statement'!G7*G33 -> 56.519902 | H34: ='Income Statement'!H7*H33 -> 63.610035 | I34: ='Income Statement'!I7*I33 -> 71.027173 | J34: ='Income Statement'!J7*J33 -> 76.728645 | K34: ='Income Statement'!K7*K33 -> 82.059361
A35: 一年内到期的非流动负债 | B35: 亿元 | C35: 234.19187 | D35: 395.08372 | E35: 313.19101 | F35: 399.54136 | G35: =F35 -> 399.54136 | H35: =G35 -> 399.54136 | I35: =H35 -> 399.54136 | J35: =I35 -> 399.54136 | K35: =J35 -> 399.54136
A36: 其他流动负债项目（合同负债、职工薪酬、其他应付款等） | B36: 亿元 | C36: =C67-C30-C32-C34-C35 -> 107.06797 | D36: =D67-D30-D32-D34-D35 -> 115.4665 | E36: =E67-E30-E32-E34-E35 -> 74.230382 | F36: =F67-F30-F32-F34-F35 -> 58.508759 | G36: =F36 -> 58.508759 | H36: =G36 -> 58.508759 | I36: =H36 -> 58.508759 | J36: =I36 -> 58.508759 | K36: =J36 -> 58.508759
A37: 流动负债合计 | B37: 亿元 | C37: =C30+C32+C34+C35+C36 -> 739.36986 | D37: =D30+D32+D34+D35+D36 -> 975.97979 | E37: =E30+E32+E34+E35+E36 -> 1017.4312 | F37: =F30+F32+F34+F35+F36 -> 1055.1347 | G37: =G30+G32+G34+G35+G36 -> 1027.1821 | H37: =H30+H32+H34+H35+H36 -> 1049.3933 | I37: =I30+I32+I34+I35+I36 -> 1076.9957 | J37: =J30+J32+J34+J35+J36 -> 1098.1615 | K37: =K30+K32+K34+K35+K36 -> 1117.0423
A39: 非流动负债 Non-current liabilities
A40: 长期借款 | B40: 亿元 | C40: 2085.1127 | D40: 2448.5336 | E40: 3043.039 | F40: 3631.7595 | G40: =F40+'Cash Flow'!G36 -> 4128.4158 | H40: =G40+'Cash Flow'!H36 -> 4638.1107 | I40: =H40+'Cash Flow'!I36 -> 5093.669 | J40: =I40+'Cash Flow'!J36 -> 5551.9575 | K40: =J40+'Cash Flow'!K36 -> 5973.5526 | L40: 平衡项：满足目标现金余额所需的净借款
A41: 应付债券 | B41: 亿元 | C41: 89.99286 | D41: 84.017267 | E41: 149.63679 | F41: 119.63885 | G41: =F41 -> 119.63885 | H41: =G41 -> 119.63885 | I41: =H41 -> 119.63885 | J41: =I41 -> 119.63885 | K41: =J41 -> 119.63885
A42: 租赁负债 | B42: 亿元 | C42: 27.897705 | D42: 36.237348 | E42: 42.079935 | F42: 47.263524 | G42: =F42 -> 47.263524 | H42: =G42 -> 47.263524 | I42: =H42 -> 47.263524 | J42: =I42 -> 47.263524 | K42: =J42 -> 47.263524
A43: 长期应付款 | B43: 亿元 | C43: 156.48043 | D43: 151.91175 | E43: 177.73875 | F43: 235.12448 | G43: =F43 -> 235.12448 | H43: =G43 -> 235.12448 | I43: =H43 -> 235.12448 | J43: =I43 -> 235.12448 | K43: =J43 -> 235.12448 | L43: 含融资租赁款、专项应付款
A44: 预计负债/核电年末装机 | B44: 元/kW | C44: =C45*10000/'Revenue Model'!C41 -> 250.59677 | D44: =D45*10000/'Revenue Model'!D41 -> 257.17046 | E44: =E45*10000/'Revenue Model'!E41 -> 266.32076 | F44: =F45*10000/'Revenue Model'!F41 -> 279.75666 | G44: 280 | H44: 280 | I44: 280 | J44: 280 | K44: 280 | L44: 核电站弃置费用；2025A 280 元/kW
A45: 预计负债（核电站弃置费用等） | B45: 亿元 | C45: 59.516733 | D45: 61.077983 | E45: 63.25118 | F45: 69.939165 | G45: ='Revenue Model'!G41*G44/10000 -> 77.2856 | H45: ='Revenue Model'!H41*H44/10000 -> 91.4004 | I45: ='Revenue Model'!I41*I44/10000 -> 98.5824 | J45: ='Revenue Model'!J41*J44/10000 -> 108.9844 | K45: ='Revenue Model'!K41*K44/10000 -> 112.3864 | L45: 增量计入固定资产（弃置成本资本化，非现金）
A46: 其余非流动负债项目（递延收益、递延所得税负债、长期应付职工薪酬等） | B46: 亿元 | C46: =C68-C40-C41-C42-C43-C45 -> 10.53023 | D46: =D68-D40-D41-D42-D43-D45 -> 6.9346938 | E46: =E68-E40-E41-E42-E43-E45 -> 10.53531 | F46: =F68-F40-F41-F42-F43-F45 -> 11.502175 | G46: =F46 -> 11.502175 | H46: =G46 -> 11.502175 | I46: =H46 -> 11.502175 | J46: =I46 -> 11.502175 | K46: =J46 -> 11.502175
A47: 非流动负债合计 | B47: 亿元 | C47: =C40+C41+C42+C43+C45+C46 -> 2429.5306 | D47: =D40+D41+D42+D43+D45+D46 -> 2788.7127 | E47: =E40+E41+E42+E43+E45+E46 -> 3486.2809 | F47: =F40+F41+F42+F43+F45+F46 -> 4115.2277 | G47: =G40+G41+G42+G43+G45+G46 -> 4619.2304 | H47: =H40+H41+H42+H43+H45+H46 -> 5143.0401 | I47: =I40+I41+I42+I43+I45+I46 -> 5605.7805 | J47: =J40+J41+J42+J43+J45+J46 -> 6074.4709 | K47: =K40+K41+K42+K43+K45+K46 -> 6499.4681
A48: 负债合计 Total liabilities | B48: 亿元 | C48: =C37+C47 -> 3168.9005 | D48: =D37+D47 -> 3764.6925 | E48: =E37+E47 -> 4503.7121 | F48: =F37+F47 -> 5170.3625 | G48: =G37+G47 -> 5646.4125 | H48: =H37+H47 -> 6192.4334 | I48: =I37+I47 -> 6682.7762 | J48: =J37+J47 -> 7172.6324 | K48: =K37+K47 -> 7616.5103
A50: 所有者权益 Equity
A51: 股本 | B51: 亿元 | C51: 188.60704 | D51: 188.83285 | E51: 205.68002 | F51: 205.68002 | G51: =F51 -> 205.68002 | H51: =G51 -> 205.68002 | I51: =H51 -> 205.68002 | J51: =I51 -> 205.68002 | K51: =J51 -> 205.68002
A52: 其他权益工具（永续债） | B52: 亿元 | C52: 60 | D52: 10 | E52: 10 | F52: 10 | G52: =F52 -> 10 | H52: =G52 -> 10 | I52: =H52 -> 10 | J52: =I52 -> 10 | K52: =J52 -> 10
A53: 资本公积 | B53: 亿元 | C53: 274.00131 | D53: 273.36443 | E53: 402.06008 | F53: 434.44432 | G53: =F53 -> 434.44432 | H53: =G53 -> 434.44432 | I53: =H53 -> 434.44432 | J53: =I53 -> 434.44432 | K53: =J53 -> 434.44432
A54: 减：库存股 | B54: 亿元 | C54: 0 | D54: 0 | E54: 0 | F54: 3.7484054 | G54: =F54 -> 3.7484054 | H54: =G54 -> 3.7484054 | I54: =H54 -> 3.7484054 | J54: =I54 -> 3.7484054 | K54: =J54 -> 3.7484054
A55: 其他综合收益、专项储备、盈余公积 | B55: 亿元 | C55: =-0.7839573769+3.2207165952+48.9400332354 -> 51.376792 | D55: =-0.8598535365000001+4.04939622+56.6075192696 -> 59.797062 | E55: =-1.2960421002+4.7054495888+64.44059555689999 -> 67.850003 | F55: =-1.2394426115000001+5.2412027074+71.6640645916 -> 75.665825 | G55: =F55 -> 75.665825 | H55: =G55 -> 75.665825 | I55: =H55 -> 75.665825 | J55: =I55 -> 75.665825 | K55: =J55 -> 75.665825 | L55: 预测期盈余公积提取视为权益内部结转，合并列示
A56: 未分配利润 | B56: 亿元 | C56: 313.3447 | D56: 377.5019 | E56: 416.58018 | F56: 465.1343 | G56: =F56+'Income Statement'!G68-'Income Statement'!G70+'Cash Flow'!G37 -> 500.426 | H56: =G56+'Income Statement'!H68-'Income Statement'!H70+'Cash Flow'!H37 -> 553.36273 | I56: =H56+'Income Statement'!I68-'Income Statement'!I70+'Cash Flow'!I37 -> 606.53695 | J56: =I56+'Income Statement'!J68-'Income Statement'!J70+'Cash Flow'!J37 -> 663.22634 | K56: =J56+'Income Statement'!K68-'Income Statement'!K70+'Cash Flow'!K37 -> 724.13385
A57: 归属于母公司所有者权益合计 | B57: 亿元 | C57: =C51+C52+C53-C54+C55+C56 -> 887.32984 | D57: =D51+D52+D53-D54+D55+D56 -> 909.49624 | E57: =E51+E52+E53-E54+E55+E56 -> 1102.1703 | F57: =F51+F52+F53-F54+F55+F56 -> 1187.1761 | G57: =G51+G52+G53-G54+G55+G56 -> 1222.4678 | H57: =H51+H52+H53-H54+H55+H56 -> 1275.4045 | I57: =I51+I52+I53-I54+I55+I56 -> 1328.5787 | J57: =J51+J52+J53-J54+J55+J56 -> 1385.2681 | K57: =K51+K52+K53-K54+K55+K56 -> 1446.1756
A58: 少数股东权益 | B58: 亿元 | C58: 592.28137 | D58: 718.48379 | E58: 991.50932 | F58: 1135.0814 | G58: =F58+'Income Statement'!G67+'Cash Flow'!G35+'Cash Flow'!G39 -> 1276.4731 | H58: =G58+'Income Statement'!H67+'Cash Flow'!H35+'Cash Flow'!H39 -> 1420.574 | I58: =H58+'Income Statement'!I67+'Cash Flow'!I35+'Cash Flow'!I39 -> 1568.8934 | J58: =I58+'Income Statement'!J67+'Cash Flow'!J35+'Cash Flow'!J39 -> 1721.1823 | K58: =J58+'Income Statement'!K67+'Cash Flow'!K35+'Cash Flow'!K39 -> 1877.6534
A59: 所有者权益合计 | B59: 亿元 | C59: =C57+C58 -> 1479.6112 | D59: =D57+D58 -> 1627.98 | E59: =E57+E58 -> 2093.6796 | F59: =F57+F58 -> 2322.2575 | G59: =G57+G58 -> 2498.9408 | H59: =H57+H58 -> 2695.9785 | I59: =I57+I58 -> 2897.4721 | J59: =J57+J58 -> 3106.4504 | K59: =K57+K58 -> 3323.829
A60: 负债和所有者权益总计 | B60: 亿元 | C60: =C48+C59 -> 4648.5117 | D60: =D48+D59 -> 5392.6725 | E60: =E48+E59 -> 6597.3917 | F60: =F48+F59 -> 7492.6199 | G60: =G48+G59 -> 8145.3534 | H60: =H48+H59 -> 8888.412 | I60: =I48+I59 -> 9580.2483 | J60: =J48+J59 -> 10279.083 | K60: =K48+K59 -> 10940.339
A61: 平衡校验（资产−负债−权益） | B61: 亿元 | C61: =ROUND(C27-C60,3) -> 0 | D61: =ROUND(D27-D60,3) -> 0 | E61: =ROUND(E27-E60,3) -> 0 | F61: =ROUND(F27-F60,3) -> 0 | G61: =ROUND(G27-G60,3) -> 0 | H61: =ROUND(H27-H60,3) -> 0 | I61: =ROUND(I27-I60,3) -> 0 | J61: =ROUND(J27-J60,3) -> 0 | K61: =ROUND(K27-K60,3) -> 0
A63: 报告值（用于历史期分项轧差与校验）Reported subtotals
A64: 报告：流动资产合计 | B64: 亿元 | C64: 657.60417 | D64: 682.40333 | E64: 841.81678 | F64: 860.77428
A65: 报告：非流动资产合计 | B65: 亿元 | C65: 3990.9075 | D65: 4710.2692 | E65: 5755.5749 | F65: 6631.8457
A66: 报告：资产总计 | B66: 亿元 | C66: 4648.5117 | D66: 5392.6725 | E66: 6597.3917 | F66: 7492.6199
A67: 报告：流动负债合计 | B67: 亿元 | C67: 739.36986 | D67: 975.97979 | E67: 1017.4312 | F67: 1055.1347
A68: 报告：非流动负债合计 | B68: 亿元 | C68: 2429.5306 | D68: 2788.7127 | E68: 3486.2809 | F68: 4115.2277
A69: 报告：负债合计 | B69: 亿元 | C69: 3168.9005 | D69: 3764.6925 | E69: 4503.7121 | F69: 5170.3625
A70: 报告：所有者权益（或股东权益）合计 | B70: 亿元 | C70: 1479.6112 | D70: 1627.98 | E70: 2093.6796 | F70: 2322.2575
A72: 固定资产与在建工程 Fixed-asset & CIP schedule
A73: 核电新机组转固（在建工程→固定资产） | B73: 亿元 | G73: ='Revenue Model'!G31 -> 290.78915 | H73: ='Revenue Model'!H31 -> 976.61381 | I73: ='Revenue Model'!I31 -> 472.66705 | J73: ='Revenue Model'!J31 -> 607.55137 | K73: ='Revenue Model'!K31 -> 222.86745
A74: 固定资产增加合计 | B74: 亿元 | G74: =G73-'Cash Flow'!G24+'Cash Flow'!G25+(G45-F45) -> 437.13559 | H74: =H73-'Cash Flow'!H24+'Cash Flow'!H25+(H45-G45) -> 1095.7286 | I74: =I73-'Cash Flow'!I24+'Cash Flow'!I25+(I45-H45) -> 567.84905 | J74: =J73-'Cash Flow'!J24+'Cash Flow'!J25+(J45-I45) -> 705.95337 | K74: =K73-'Cash Flow'!K24+'Cash Flow'!K25+(K45-J45) -> 314.26945 | L74: 说明：=核电转固 + 新能源资本开支（建成即转固）+ 维护性资本开支 + 弃置费用资本化
A75: 折旧率（期初固定资产+½当年增加） | B75: % | G75: 0.059 | H75: 0.059 | I75: 0.059 | J75: 0.059 | K75: 0.059 | L75: 2025A 203.41/(2,992.37+½×731)=6.06%；2026H1 折旧 107.85 亿（年化约 216 亿）→ 5.9%；核电按工作量法折旧
A76: 固定资产折旧 | B76: 亿元 | C76: ='Cash Flow'!C8 -> 152.0272 | D76: ='Cash Flow'!D8 -> 160.82455 | E76: ='Cash Flow'!E8 -> 173.32044 | F76: ='Cash Flow'!F8 -> 203.40667 | G76: =(F19+G74/2)*G75 -> 220.58518 | H76: =(G19+H74/2)*H75 -> 252.47745 | I76: =(H19+I74/2)*I75 -> 286.34412 | J76: =(I19+J74/2)*J75 -> 306.71429 | K76: =(J19+K74/2)*K75 -> 318.40202
A77: 有息负债合计（短借+一年内到期+长借+债券+租赁） | B77: 亿元 | C77: =C30+C35+C40+C41+C42 -> 2590.8403 | D77: =D30+D35+D40+D41+D42 -> 3162.5155 | E77: =E30+E35+E40+E41+E42 -> 3838.704 | F77: =F30+F35+F40+F41+F42 -> 4450.9221 | G77: =G30+G35+G40+G41+G42 -> 4947.5783 | H77: =H30+H35+H40+H41+H42 -> 5457.2733 | I77: =I30+I35+I40+I41+I42 -> 5912.8316 | J77: =J30+J35+J40+J41+J42 -> 6371.1201 | K77: =K30+K35+K40+K41+K42 -> 6792.7152
A78: 净负债 Net debt | B78: 亿元 | C78: =C77-C7 -> 2429.2236 | D78: =D77-D7 -> 3064.7773 | E78: =E77-E7 -> 3641.3239 | F78: =F77-F7 -> 4295.1057 | G78: =G77-G7 -> 4802.2414 | H78: =H77-H7 -> 5293.7046 | I78: =I77-I7 -> 5730.1903 | J78: =J77-J7 -> 6173.8179 | K78: =K77-K7 -> 6581.7054
A79: 资产负债率 | B79: % | C79: =C48/C27 -> 0.68170216 | D79: =D48/D27 -> 0.69811257 | E79: =E48/E27 -> 0.6826504 | F79: =F48/F27 -> 0.69006069 | G79: =G48/G27 -> 0.69320658 | H79: =H48/H27 -> 0.69668614 | I79: =I48/I27 -> 0.69755772 | J79: =J48/J27 -> 0.69778915 | K79: =K48/K27 -> 0.69618593
A80: 净负债/EBITDA | B80: x | C80: =C78/'Income Statement'!C83 -> 5.5995128 | D80: =D78/'Income Statement'!D83 -> 6.611908 | E80: =E78/'Income Statement'!E83 -> 7.7270353 | F80: =F78/'Income Statement'!F83 -> 8.3805724 | G80: =G78/'Income Statement'!G83 -> 9.8769524 | H80: =H78/'Income Statement'!H83 -> 9.7384889 | I80: =I78/'Income Statement'!I83 -> 9.5654308 | J80: =J78/'Income Statement'!J83 -> 9.6775303 | K80: =K78/'Income Statement'!K83 -> 9.7851037

Sheet Scenarios
A1: 情景假设 Scenarios — 牛 / 基准 / 熊（切换 C4 选择器驱动全模型）
A2: 单位：亿元人民币（另有注明除外）｜蓝色=硬编码输入 黑色=公式 绿色=跨表链接｜A=实际 E=预测
A3: 项目 / Line item | B3: 单位 | C3: 2022 | D3: 2023 | E3: 2024 | F3: 2025 | G3: 2026 | H3: 2027 | I3: 2028 | J3: 2029 | K3: 2030 | L3: 来源 / 说明
A4: 情景选择器 Scenario selector（1=Bull 牛市, 2=Base 基准, 3=Bear 熊市） | C4: 2 | D4: =CHOOSE($C$4,"Bull 牛市","Base 基准","Bear 熊市") -> Base 基准
A6: 驱动因素（2026E–2030E 每年） | G6: 2026 | H6: 2027 | I6: 2028 | J6: 2029 | K6: 2030
A8: 核电综合电价（含增值税）Nuclear realized tariff incl. VAT
A9: Bull 牛市 | B9: 元/kWh | G9: 0.383 | H9: 0.385 | I9: 0.388 | J9: 0.39 | K9: 0.39
A10: Base 基准 | B10: 元/kWh | G10: 0.378 | H10: 0.376 | I10: 0.375 | J10: 0.375 | K10: 0.375
A11: Bear 熊市 | B11: 元/kWh | G11: 0.372 | H11: 0.362 | I11: 0.355 | J11: 0.35 | K11: 0.35
A12: Live 当前情景 | B12: 元/kWh | G12: =CHOOSE($C$4,G9,G10,G11) -> 0.378 | H12: =CHOOSE($C$4,H9,H10,H11) -> 0.376 | I12: =CHOOSE($C$4,I9,I10,I11) -> 0.375 | J12: =CHOOSE($C$4,J9,J10,J11) -> 0.375 | K12: =CHOOSE($C$4,K9,K10,K11) -> 0.375 | L12: 2024A 0.4151 / 2025A 0.3937（年报 售电业务经营情况）；2026H1 推算约 0.377。牛=机制电价全国推广；熊=市场化继续下行
A14: 核电存量机组平均利用小时 Nuclear fleet utilisation hours
A15: Bull 牛市 | B15: 小时 | G15: 7800 | H15: 8050 | I15: 8050 | J15: 8050 | K15: 8050
A16: Base 基准 | B16: 小时 | G16: 7650 | H16: 7950 | I16: 7950 | J16: 7950 | K16: 7950
A17: Bear 熊市 | B17: 小时 | G17: 7500 | H17: 7750 | I17: 7750 | J17: 7750 | K17: 7750
A18: Live 当前情景 | B18: 小时 | G18: =CHOOSE($C$4,G15,G16,G17) -> 7650 | H18: =CHOOSE($C$4,H15,H16,H17) -> 7950 | I18: =CHOOSE($C$4,I15,I16,I17) -> 7950 | J18: =CHOOSE($C$4,J15,J16,J17) -> 7950 | K18: =CHOOSE($C$4,K15,K16,K17) -> 7950 | L18: 2023A 7,852 / 2024A 7,710 / 2025A 8,038（年报 发电效率表）；2026H1 3,738h（大修 10 次）；公司 2026 计划核电发电 2,100 亿 kWh
A20: 新机组投产延迟（年）COD delay vs company schedule
A21: Bull 牛市 | B21: 年 | G21: 0 | H21: 0 | I21: 0 | J21: 0 | K21: 0
A22: Base 基准 | B22: 年 | G22: 0 | H22: 0 | I22: 0 | J22: 0 | K22: 0
A23: Bear 熊市 | B23: 年 | G23: 1 | H23: 1 | I23: 1 | J23: 1 | K23: 1
A24: Live 当前情景 | B24: 年 | G24: =CHOOSE($C$4,G21,G22,G23) -> 0 | H24: =CHOOSE($C$4,H21,H22,H23) -> 0 | I24: =CHOOSE($C$4,I21,I22,I23) -> 0 | J24: =CHOOSE($C$4,J21,J22,J23) -> 0 | K24: =CHOOSE($C$4,K21,K22,K23) -> 0 | L24: 公司计划商运时间见 Revenue Model 机组清单（年报 2025 第 17 页）；熊市情景整体推迟 1 年。仅 2026E 列生效
A26: 投产当年容量计入比例 COD-year capacity weight
A27: Bull 牛市 | B27: % | G27: 0.5 | H27: 0.5 | I27: 0.5 | J27: 0.5 | K27: 0.5
A28: Base 基准 | B28: % | G28: 0.4 | H28: 0.4 | I28: 0.4 | J28: 0.4 | K28: 0.4
A29: Bear 熊市 | B29: % | G29: 0.35 | H29: 0.35 | I29: 0.35 | J29: 0.35 | K29: 0.35
A30: Live 当前情景 | B30: % | G30: =CHOOSE($C$4,G27,G28,G29) -> 0.4 | H30: =CHOOSE($C$4,H27,H28,H29) -> 0.4 | I30: =CHOOSE($C$4,I27,I28,I29) -> 0.4 | J30: =CHOOSE($C$4,J27,J28,J29) -> 0.4 | K30: =CHOOSE($C$4,K27,K28,K29) -> 0.4 | L30: 新机组投产当年按此比例计入平均装机（投产月份不确定）
A32: 新能源综合电价（含增值税）Renewables realized tariff incl. VAT
A33: Bull 牛市 | B33: 元/kWh | G33: 0.36 | H33: 0.355 | I33: 0.35 | J33: 0.35 | K33: 0.35
A34: Base 基准 | B34: 元/kWh | G34: 0.355 | H34: 0.345 | I34: 0.34 | J34: 0.335 | K34: 0.335
A35: Bear 熊市 | B35: 元/kWh | G35: 0.345 | H35: 0.33 | I35: 0.32 | J35: 0.315 | K35: 0.315
A36: Live 当前情景 | B36: 元/kWh | G36: =CHOOSE($C$4,G33,G34,G35) -> 0.355 | H36: =CHOOSE($C$4,H33,H34,H35) -> 0.345 | I36: =CHOOSE($C$4,I33,I34,I35) -> 0.34 | J36: =CHOOSE($C$4,J33,J34,J35) -> 0.335 | K36: =CHOOSE($C$4,K33,K34,K35) -> 0.335 | L36: 2024A 0.4203 / 2025A 0.3732（-11.2%）；136 号文后增量项目全面入市
A38: 风电利用小时 Wind hours
A39: Bull 牛市 | B39: 小时 | G39: 1880 | H39: 1880 | I39: 1880 | J39: 1880 | K39: 1880
A40: Base 基准 | B40: 小时 | G40: 1800 | H40: 1800 | I40: 1800 | J40: 1800 | K40: 1800
A41: Bear 熊市 | B41: 小时 | G41: 1720 | H41: 1720 | I41: 1720 | J41: 1720 | K41: 1720
A42: Live 当前情景 | B42: 小时 | G42: =CHOOSE($C$4,G39,G40,G41) -> 1800 | H42: =CHOOSE($C$4,H39,H40,H41) -> 1800 | I42: =CHOOSE($C$4,I39,I40,I41) -> 1800 | J42: =CHOOSE($C$4,J39,J40,J41) -> 1800 | K42: =CHOOSE($C$4,K39,K40,K41) -> 1800 | L42: 2025A 推算约 1,928h（2024 年末风电容量按比例估算）；2026H1 风电发电量 -6.09%，弃风上升
A44: 光伏利用小时 Solar hours
A45: Bull 牛市 | B45: 小时 | G45: 1100 | H45: 1100 | I45: 1100 | J45: 1100 | K45: 1100
A46: Base 基准 | B46: 小时 | G46: 1050 | H46: 1050 | I46: 1050 | J46: 1050 | K46: 1050
A47: Bear 熊市 | B47: 小时 | G47: 1000 | H47: 1000 | I47: 1000 | J47: 1000 | K47: 1000
A48: Live 当前情景 | B48: 小时 | G48: =CHOOSE($C$4,G45,G46,G47) -> 1050 | H48: =CHOOSE($C$4,H45,H46,H47) -> 1050 | I48: =CHOOSE($C$4,I45,I46,I47) -> 1050 | J48: =CHOOSE($C$4,J45,J46,J47) -> 1050 | K48: =CHOOSE($C$4,K45,K46,K47) -> 1050 | L48: 2025A 推算约 1,126h
A50: 新能源年新增装机 Renewables capacity additions
A51: Bull 牛市 | B51: 万千瓦 | G51: 400 | H51: 300 | I51: 300 | J51: 300 | K51: 300
A52: Base 基准 | B52: 万千瓦 | G52: 350 | H52: 250 | I52: 200 | J52: 200 | K52: 200
A53: Bear 熊市 | B53: 万千瓦 | G53: 300 | H53: 150 | I53: 100 | J53: 100 | K53: 100
A54: Live 当前情景 | B54: 万千瓦 | G54: =CHOOSE($C$4,G51,G52,G53) -> 350 | H54: =CHOOSE($C$4,H51,H52,H53) -> 250 | I54: =CHOOSE($C$4,I51,I52,I53) -> 200 | J54: =CHOOSE($C$4,J51,J52,J53) -> 200 | K54: =CHOOSE($C$4,K51,K52,K53) -> 200 | L54: 2025 年新增 404.5 万千瓦；2026H1 已新增 136.3 万千瓦；年末在建 793.17 万千瓦。风电占新增比例见 Revenue Model
A56: 其他收益（增值税退税等）占核电收入 Other income % nuclear rev.
A57: Bull 牛市 | B57: % | G57: 0.047 | H57: 0.0465 | I57: 0.046 | J57: 0.0455 | K57: 0.045
A58: Base 基准 | B58: % | G58: 0.046 | H58: 0.045 | I58: 0.044 | J58: 0.043 | K58: 0.042
A59: Bear 熊市 | B59: % | G59: 0.045 | H59: 0.043 | I59: 0.041 | J59: 0.039 | K59: 0.037
A60: Live 当前情景 | B60: % | G60: =CHOOSE($C$4,G57,G58,G59) -> 0.046 | H60: =CHOOSE($C$4,H57,H58,H59) -> 0.045 | I60: =CHOOSE($C$4,I57,I58,I59) -> 0.044 | J60: =CHOOSE($C$4,J57,J58,J59) -> 0.043 | K60: =CHOOSE($C$4,K57,K58,K59) -> 0.042 | L60: 2025A 31.50/654.5=4.8%；新核准机组退税减半/取消（财税 2025 新政）→ 占比逐步下降
A62: 核燃料单位成本增速 Nuclear fuel cost/kWh growth
A63: Bull 牛市 | B63: % | G63: 0.02 | H63: 0.02 | I63: 0.02 | J63: 0.02 | K63: 0.02
A64: Base 基准 | B64: % | G64: 0.04 | H64: 0.04 | I64: 0.04 | J64: 0.04 | K64: 0.04
A65: Bear 熊市 | B65: % | G65: 0.07 | H65: 0.07 | I65: 0.06 | J65: 0.06 | K65: 0.05
A66: Live 当前情景 | B66: % | G66: =CHOOSE($C$4,G63,G64,G65) -> 0.04 | H66: =CHOOSE($C$4,H63,H64,H65) -> 0.04 | I66: =CHOOSE($C$4,I63,I64,I65) -> 0.04 | J66: =CHOOSE($C$4,J63,J64,J65) -> 0.04 | K66: =CHOOSE($C$4,K63,K64,K65) -> 0.04 | L66: 2025A 0.0434 元/kWh（成本分析表 87.05 亿 / 2,008 亿 kWh）；中国铀业 2026 长协基价 +42%，长协平滑传导
A68: 核电资本开支超支 Nuclear capex overrun
A69: Bull 牛市 | B69: % | G69: 0 | H69: 0 | I69: 0 | J69: 0 | K69: 0
A70: Base 基准 | B70: % | G70: 0 | H70: 0 | I70: 0 | J70: 0 | K70: 0
A71: Bear 熊市 | B71: % | G71: 0.05 | H71: 0.05 | I71: 0.05 | J71: 0.05 | K71: 0.05
A72: Live 当前情景 | B72: % | G72: =CHOOSE($C$4,G69,G70,G71) -> 0 | H72: =CHOOSE($C$4,H69,H70,H71) -> 0 | I72: =CHOOSE($C$4,I69,I70,I71) -> 0 | J72: =CHOOSE($C$4,J69,J70,J71) -> 0 | K72: =CHOOSE($C$4,K69,K70,K71) -> 0 | L72: 相对基础资本开支计划的超支比例
A74: 情景输出（静态快照：分别以 C4=1/2/3 全模型重算后写入。切换 C4 时其余各表实时更新，但本表为静态值，修改假设后需重新生成）
A75: 指标 Metric | C75: Bull 牛市 | D75: Base 基准 | E75: Bear 熊市
A76: 2030E 营业收入（亿元） | C76: 1257.3597 | D76: 1172.2766 | E76: 988.369
A77: 2026–30E 收入 CAGR（vs 2025A） | C77: 0.089053471 | D77: 0.073898697 | E77: 0.037865607
A78: 2030E 毛利率 | C78: 0.37456523 | D78: 0.32968953 | E78: 0.25536163
A79: 2030E EBITDA（亿元） | C79: 766.06334 | D79: 672.625 | E79: 508.73396
A80: 2030E EBITDA 利润率 | C80: 0.60926348 | D80: 0.57377671 | E80: 0.51472068
A81: 2026E 归母净利润（亿元） | C81: 85.129041 | D81: 72.480554 | E81: 59.552186
A82: 2027E 归母净利润（亿元） | C82: 101.94732 | D82: 82.086509 | E82: 58.000652
A83: 2030E 归母净利润（亿元） | C83: 131.71367 | D83: 97.590465 | E83: 45.633535
A84: 2026E EPS（元） | C84: 0.41370011 | D84: 0.35204228 | E84: 0.28902011
A85: 2030E EPS（元） | C85: 0.64078712 | D85: 0.47444606 | E85: 0.22117059
A86: 2030E FCF（亿元） | C86: -283.52231 | D86: -321.51797 | E86: -494.30422
A87: 2026–30E 累计 FCF（亿元） | C87: -1847.1987 | D87: -1952.4665 | E87: -2446.1012
... A91: DCF 目标价（元） | C91: 13.798035 | D91: 7.4882047 | E91: -2.8366691
A93: 情景说明 Scenario rationale：
A94: Bull 牛市：核电“机制电价/差价合约”2027 年前推广至浙江、江苏、福建，核电综合电价企稳回升至 0.39 元；利用小时恢复至 8,050；新机组按期投产；铀价温和；新能源限电缓解。
A95: Base 基准：电价 2026 年再降约 4% 后企稳于 0.375 元（市场化+部分省份机制电价托底）；2026 年大修集中致利用小时 7,750，此后 7,950；新机组按公司计划投产（投产当年计 40%）；燃料成本年增 4%。
A96: Bear 熊市：电价持续下行至 0.35 元（无全国性托底机制）；利用小时 7,600–7,750；全部新机组推迟 1 年、资本开支超支 5%；新能源电价降至 0.315 元、利用小时继续下降；铀价长协快速传导（燃料成本年增 5–7%）。

Sheet DCF Inputs
A1: DCF 输入 DCF Inputs（供 Task 3 估值使用）
A2: 单位：亿元人民币（另有注明除外）｜蓝色=硬编码输入 黑色=公式 绿色=跨表链接｜A=实际 E=预测
A3: 项目 / Line item | B3: 单位 | C3: 2022 | D3: 2023 | E3: 2024 | F3: 2025 | G3: 2026 | H3: 2027 | I3: 2028 | J3: 2029 | K3: 2030 | L3: 来源 / 说明
A6: 无杠杆自由现金流 Unlevered FCF（合并口径）
A7: 营业收入 | B7: 亿元 | C7: ='Income Statement'!C7 -> 712.85601 | D7: ='Income Statement'!D7 -> 749.5718 | E7: ='Income Statement'!E7 -> 772.72059 | F7: ='Income Statement'!F7 -> 820.75495 | G7: ='Income Statement'!G7 -> 807.42717 | H7: ='Income Statement'!H7 -> 908.71479 | I7: ='Income Statement'!I7 -> 1014.6739 | J7: ='Income Statement'!J7 -> 1096.1235 | K7: ='Income Statement'!K7 -> 1172.2766
A8: EBITDA | B8: 亿元 | C8: ='Income Statement'!C83 -> 433.82767 | D8: ='Income Statement'!D83 -> 463.52389 | E8: ='Income Statement'!E83 -> 471.24463 | F8: ='Income Statement'!F83 -> 512.50744 | G8: ='Income Statement'!G83 -> 486.2068 | H8: ='Income Statement'!H83 -> 543.58583 | I8: ='Income Statement'!I83 -> 599.05198 | J8: ='Income Statement'!J83 -> 637.95387 | K8: ='Income Statement'!K83 -> 672.625
A9: EBIT（经营口径） | B9: 亿元 | C9: ='Income Statement'!C82 -> 275.14452 | D9: ='Income Statement'!D82 -> 295.65548 | E9: ='Income Statement'!E82 -> 288.14891 | F9: ='Income Statement'!F82 -> 296.48113 | G9: ='Income Statement'!G82 -> 253.02163 | H9: ='Income Statement'!H82 -> 278.50839 | I9: ='Income Statement'!I82 -> 300.10787 | J9: ='Income Statement'!J82 -> 318.63958 | K9: ='Income Statement'!K82 -> 341.62299
A10: 税率 | B10: % | C10: ='Income Statement'!C63 -> 0.16591482 | D10: ='Income Statement'!D63 -> 0.15536802 | E10: ='Income Statement'!E63 -> 0.26639082 | F10: ='Income Statement'!F63 -> 0.22836854 | G10: ='Income Statement'!G63 -> 0.235 | H10: ='Income Statement'!H63 -> 0.235 | I10: ='Income Statement'!I63 -> 0.235 | J10: ='Income Statement'!J63 -> 0.235 | K10: ='Income Statement'!K63 -> 0.235
A11: NOPAT | B11: 亿元 | C11: =C9*(1-C10) -> 229.49397 | D11: =D9*(1-D10) -> 249.72008 | E11: =E9*(1-E10) -> 211.38868 | F11: =F9*(1-F10) -> 228.77417 | G11: =G9*(1-G10) -> 193.56154 | H11: =H9*(1-H10) -> 213.05892 | I11: =I9*(1-I10) -> 229.58252 | J11: =J9*(1-J10) -> 243.75928 | K11: =K9*(1-K10) -> 261.34158
A12: 加：折旧摊销 | B12: 亿元 | C12: ='Income Statement'!C81 -> 158.68314 | D12: ='Income Statement'!D81 -> 167.86841 | E12: ='Income Statement'!E81 -> 183.09572 | F12: ='Income Statement'!F81 -> 216.02631 | G12: ='Income Statement'!G81 -> 233.18518 | H12: ='Income Statement'!H81 -> 265.07745 | I12: ='Income Statement'!I81 -> 298.94412 | J12: ='Income Statement'!J81 -> 319.31429 | K12: ='Income Statement'!K81 -> 331.00202
A13: 减：资本开支 | B13: 亿元 | C13: ='Cash Flow'!C27 -> -505.09691 | D13: ='Cash Flow'!D27 -> -671.00346 | E13: ='Cash Flow'!E27 -> -907.08324 | F13: ='Cash Flow'!F27 -> -936.83638 | G13: ='Cash Flow'!G27 -> -851.6 | H13: ='Cash Flow'!H27 -> -857.6 | I13: ='Cash Flow'!I27 -> -880.6 | J13: ='Cash Flow'!J27 -> -900.6 | K13: ='Cash Flow'!K27 -> -920.6
A14: 减：营运资本增加 | B14: 亿元 | C14: ='Cash Flow'!C14+'Cash Flow'!C15+'Cash Flow'!C16 -> 60.795718 | D14: ='Cash Flow'!D14+'Cash Flow'!D15+'Cash Flow'!D16 -> -5.690042 | E14: ='Cash Flow'!E14+'Cash Flow'!E15+'Cash Flow'!E16 -> -13.33537 | F14: ='Cash Flow'!F14+'Cash Flow'!F15+'Cash Flow'!F16 -> -94.533699 | G14: ='Cash Flow'!G14+'Cash Flow'!G15+'Cash Flow'!G16 -> -54.249607 | H14: ='Cash Flow'!H14+'Cash Flow'!H15+'Cash Flow'!H16 -> -84.750822 | I14: ='Cash Flow'!I14+'Cash Flow'!I15+'Cash Flow'!I16 -> -45.019608 | J14: ='Cash Flow'!J14+'Cash Flow'!J15+'Cash Flow'!J16 -> -59.936077 | K14: ='Cash Flow'!K14+'Cash Flow'!K15+'Cash Flow'!K16 -> -24.199984
A15: 无杠杆自由现金流 UFCF | B15: 亿元 | C15: =C11+C12+C13+C14 -> -56.124076 | D15: =D11+D12+D13+D14 -> -259.10502 | E15: =E11+E12+E13+E14 -> -525.93421 | F15: =F11+F12+F13+F14 -> -586.5696 | G15: =G11+G12+G13+G14 -> -479.10289 | H15: =H11+H12+H13+H14 -> -464.21446 | I15: =I11+I12+I13+I14 -> -397.09297 | J15: =J11+J12+J13+J14 -> -397.46251 | K15: =K11+K12+K13+K14 -> -352.45638
A16: 少数股东损益占比（用于折算归母价值） | B16: % | C16: ='Income Statement'!C66 -> 0.44799214 | D16: ='Income Statement'!D66 -> 0.4526797 | E16: ='Income Statement'!E66 -> 0.46974617 | F16: ='Income Statement'!F66 -> 0.48225306 | G16: ='Income Statement'!G66 -> 0.485 | H16: ='Income Statement'!H66 -> 0.485 | I16: ='Income Statement'!I66 -> 0.485 | J16: ='Income Statement'!J66 -> 0.485 | K16: ='Income Statement'!K66 -> 0.485
A18: 股权价值桥 Equity bridge items（年末）
A19: 有息负债合计 | B19: 亿元 | C19: ='Balance Sheet'!C77 -> 2590.8403 | D19: ='Balance Sheet'!D77 -> 3162.5155 | E19: ='Balance Sheet'!E77 -> 3838.704 | F19: ='Balance Sheet'!F77 -> 4450.9221 | G19: ='Balance Sheet'!G77 -> 4947.5783 | H19: ='Balance Sheet'!H77 -> 5457.2733 | I19: ='Balance Sheet'!I77 -> 5912.8316 | J19: ='Balance Sheet'!J77 -> 6371.1201 | K19: ='Balance Sheet'!K77 -> 6792.7152
A20: 货币资金 | B20: 亿元 | C20: ='Balance Sheet'!C7 -> 161.61672 | D20: ='Balance Sheet'!D7 -> 97.738191 | E20: ='Balance Sheet'!E7 -> 197.38017 | F20: ='Balance Sheet'!F7 -> 155.81643 | G20: ='Balance Sheet'!G7 -> 145.33689 | H20: ='Balance Sheet'!H7 -> 163.56866 | I20: ='Balance Sheet'!I7 -> 182.6413 | J20: ='Balance Sheet'!J7 -> 197.30223 | K20: ='Balance Sheet'!K7 -> 211.00979
A21: 净负债 | B21: 亿元 | C21: ='Balance Sheet'!C78 -> 2429.2236 | D21: ='Balance Sheet'!D78 -> 3064.7773 | E21: ='Balance Sheet'!E78 -> 3641.3239 | F21: ='Balance Sheet'!F78 -> 4295.1057 | G21: ='Balance Sheet'!G78 -> 4802.2414 | H21: ='Balance Sheet'!H78 -> 5293.7046 | I21: ='Balance Sheet'!I78 -> 5730.1903 | J21: ='Balance Sheet'!J78 -> 6173.8179 | K21: ='Balance Sheet'!K78 -> 6581.7054
A22: 少数股东权益（账面） | B22: 亿元 | C22: ='Balance Sheet'!C58 -> 592.28137 | D22: ='Balance Sheet'!D58 -> 718.48379 | E22: ='Balance Sheet'!E58 -> 991.50932 | F22: ='Balance Sheet'!F58 -> 1135.0814 | G22: ='Balance Sheet'!G58 -> 1276.4731 | H22: ='Balance Sheet'!H58 -> 1420.574 | I22: ='Balance Sheet'!I58 -> 1568.8934 | J22: ='Balance Sheet'!J58 -> 1721.1823 | K22: ='Balance Sheet'!K58 -> 1877.6534
A23: 永续债 | B23: 亿元 | C23: ='Balance Sheet'!C52 -> 60 | D23: ='Balance Sheet'!D52 -> 10 | E23: ='Balance Sheet'!E52 -> 10 | F23: ='Balance Sheet'!F52 -> 10 | G23: ='Balance Sheet'!G52 -> 10 | H23: ='Balance Sheet'!H52 -> 10 | I23: ='Balance Sheet'!I52 -> 10 | J23: ='Balance Sheet'!J52 -> 10 | K23: ='Balance Sheet'!K52 -> 10
A24: 长期股权投资 | B24: 亿元 | C24: ='Balance Sheet'!C18 -> 56.845889 | D24: ='Balance Sheet'!D18 -> 75.799619 | E24: ='Balance Sheet'!E18 -> 84.11163 | F24: ='Balance Sheet'!F18 -> 103.85289 | G24: ='Balance Sheet'!G18 -> 120.3076 | H24: ='Balance Sheet'!H18 -> 136.83505 | I24: ='Balance Sheet'!I18 -> 153.43887 | J24: ='Balance Sheet'!J18 -> 170.12289 | K24: ='Balance Sheet'!K18 -> 186.8911
A25: 归母净资产 | B25: 亿元 | C25: ='Balance Sheet'!C57 -> 887.32984 | D25: ='Balance Sheet'!D57 -> 909.49624 | E25: ='Balance Sheet'!E57 -> 1102.1703 | F25: ='Balance Sheet'!F57 -> 1187.1761 | G25: ='Balance Sheet'!G57 -> 1222.4678 | H25: ='Balance Sheet'!H57 -> 1275.4045 | I25: ='Balance Sheet'!I57 -> 1328.5787 | J25: ='Balance Sheet'!J57 -> 1385.2681 | K25: ='Balance Sheet'!K57 -> 1446.1756
A26: 股本（剔除库存股） | B26: 亿股 | F26: 205.14 | G26: ='Income Statement'!G74 -> 205.14 | H26: ='Income Statement'!H74 -> 205.14 | I26: ='Income Statement'!I74 -> 205.14 | J26: ='Income Statement'!J74 -> 205.14 | K26: ='Income Statement'!K74 -> 205.14
A27: 每股归母净资产（不含永续债） | B27: 元/股 | F27: =(F25-F23)/F26 -> 5.7384033 | G27: =(G25-G23)/G26 -> 5.9104405 | H27: =(H25-H23)/H26 -> 6.1684922 | I27: =(I25-I23)/I26 -> 6.4277017 | J27: =(J25-J23)/J26 -> 6.7040465 | K27: =(K25-K23)/K26 -> 7.0009535
A29: 市场数据 Market data（2026-09-24）
A30: 股价 | B30: 元/股 | F30: 8.9 | L30: 同花顺 F10（2026-09-24 收盘），Task 1 [S18]
A31: 市值 | B31: 亿元 | F31: =F30*F26 -> 1825.746
A32: 市盈率（股价/EPS） | B32: x | F32: =$F$30/'Income Statement'!F75 -> 19.646799 | G32: =$F$30/'Income Statement'!G75 -> 25.281054 | H32: =$F$30/'Income Statement'!H75 -> 22.313112 | I32: =$F$30/'Income Statement'!I75 -> 21.253382 | J32: =$F$30/'Income Statement'!J75 -> 20.051926 | K32: =$F$30/'Income Statement'!K75 -> 18.758718
A33: 市净率 | B33: x | F33: =$F$30/F27 -> 1.5509541 | G33: =$F$30/G27 -> 1.5058099 | H33: =$F$30/H27 -> 1.4428161 | I33: =$F$30/I27 -> 1.3846318 | J33: =$F$30/J27 -> 1.3275564 | K33: =$F$30/K27 -> 1.2712554
A34: 股息率 | B34: % | G34: ='Income Statement'!G78/$F$30 -> 0.015822125 | H34: ='Income Statement'!H78/$F$30 -> 0.01792668 | I34: ='Income Statement'!I78/$F$30 -> 0.018820534 | J34: ='Income Statement'!J78/$F$30 -> 0.019948208 | K34: ='Income Statement'!K78/$F$30 -> 0.021323418
A35: EV/EBITDA（EV=市值+净负债+少数股东权益+永续债−长期股权投资） | B35: x | F35: =(F31+F21+F22+F23-F24)/F8 -> 13.974588 | G35: =($F$31+G21+G22+G23-G24)/G8 -> 16.03053 | H35: =($F$31+H21+H22+H23-H24)/H8 -> 15.477205 | I35: =($F$31+I21+I22+I23-I24)/I8 -> 14.992674 | J35: =($F$31+J21+J22+J23-J24)/J8 -> 14.986387 | K35: =($F$31+K21+K22+K23-K24)/K8 -> 15.028008
A37: 终值年指标 Terminal-year metrics（2030E）
A38: 2030E 营业收入 | B38: 亿元 | K38: ='Income Statement'!K7 -> 1172.2766
A39: 2030E EBITDA | B39: 亿元 | K39: ='Income Statement'!K83 -> 672.625
A40: 2030E EBIT | B40: 亿元 | K40: ='Income Statement'!K82 -> 341.62299
A41: 2030E UFCF | B41: 亿元 | K41: =K15 -> -352.45638
A42: 2030E 归母净利润 | B42: 亿元 | K42: ='Income Statement'!K68 -> 97.590465
A43: 2030E 折旧摊销 | B43: 亿元 | K43: ='Income Statement'!K81 -> 331.00202
A44: 注：2030E 资本开支仍处于建设高峰（UFCF 为负），终值不宜直接以 2030E UFCF 永续化；Task 3 建议采用：①延长至机组建成后的稳态期（维护性资本开支≈折旧），或 ②EV/EBITDA、PE、PB 及股利折现交叉验证。
A45: 少数股东占净利润约 48%：合并口径 DCF 得到的企业价值须扣除少数股东权益价值（建议按少数股东损益×归母 PE 或账面值×PB 估算），再扣净负债、永续债，加长期股权投资。

Sheet DCF
A1: 现金流折现 DCF — 三阶段（2026–30E 模型明细｜2031–45E 在建及核准机组投产后延伸｜终值）
A2: 单位：亿元人民币（另有注明除外）｜蓝色=输入 黑色=公式 绿色=跨表链接
A4: A. 资本成本 WACC
A5: 无风险利率（10 年期国债） | C5: 0.0168 | D5: 中国 10 年期国债收益率，2026-09-30；来源见 market_data
A6: Beta | C6: 0.65
A7: 股权风险溢价 ERP | C7: 0.065 | D7: A 股常用 6–7%
A8: 股权成本 Ke = rf + β×ERP | C8: =C5+C6*C7 -> 0.05905
A9: 税前债务成本 Kd | C9: ='Income Statement'!$G$42 -> 0.023 | D9: 说明：模型 2026E 有息负债综合利率（含资本化部分）
A10: 税率 | C10: ='Income Statement'!$K$63 -> 0.235
A11: 税后债务成本 | C11: =C9*(1-C10) -> 0.017595
A12: 归母市值 E（2026-09-24） | C12: ='DCF Inputs'!$F$31 -> 1825.746
A13: 少数股东权益市值（账面×公司 P/B） | C13: ='DCF Inputs'!$F$22*'DCF Inputs'!$F$33 -> 1760.4591 | D13: 合并口径 WACC 需包含少数股东资本
A14: 有息负债 D（2025A） | C14: ='DCF Inputs'!$F$19 -> 4450.9221
A15: D/(D+E) 债务权重 | C15: =C14/(C14+C12+C13) -> 0.55379515 | D15: 市值权重
A16: WACC（计算值） | C16: =(1-C15)*C8+C15*C11 -> 0.036092422
A17: WACC（采用） | C17: =ROUND(C16/0.0005,0)*0.0005 -> 0.036 | D17: 说明：计算值四舍五入至 0.05%
A18: 永续增长率 g | C18: 0.01 | D18: 电价与 CPI 挂钩的长期名义增速；低于名义 GDP
A19: 新增投资回报率 RONIC（终值价值驱动公式） | C19: 0.055 | D19: 终值 = NOPAT×(1+g)×(1−g/RONIC)/(WACC−g)
A21: B. 二阶段假设 Stage-2 assumptions（2031–2045E）
A22: 核电电价年增速（含税） | C22: 0 | D22: 2030E 后电价持平（机制电价/中长期合约稳定）
A23: 新能源收入年增速 | C23: 0.02
A24: 其他业务收入年增速 | C24: 0.03
A25: 维护性资本开支/折旧摊销 | C25: 0.6 | D25: 建成期后仅维持性投资；未计入 22 台之外的新核准机组（保守，增长价值≈0 当 RONIC≈WACC）
A26: 2031E 收尾资本开支（在建机组） | C26: 650 | D26: 徐圩一期、金七门 2–4、三门 5–6、庄河 1–2 剩余投资
A27: 2032E 收尾资本开支 | C27: 450
A28: 2033E 收尾资本开支 | C28: 250
A30: C. 无杠杆自由现金流 Unlevered FCF
A31: 项目 | B31: 单位 | C31: 2026 | D31: 2027 | E31: 2028 | F31: 2029 | G31: 2030 | H31: 2031 | I31: 2032 | J31: 2033 | K31: 2034 | L31: 2035 | M31: 2036 | N31: 2037 | O31: 2038 | P31: 2039 | Q31: 2040 | R31: 2041 | S31: 2042 | T31: 2043 | U31: 2044 | V31: 2045 | W31: 说明
A32: 核电新增投产容量 | B32: 万千瓦 | C32: =SUMPRODUCT(('Revenue Model'!$E$8:$E$28=C$31)*'Revenue Model'!$C$8:$C$28) -> 139 | D32: =SUMPRODUCT(('Revenue Model'!$E$8:$E$28=D$31)*'Revenue Model'!$C$8:$C$28) -> 504.1 | E32: =SUMPRODUCT(('Revenue Model'!$E$8:$E$28=E$31)*'Revenue Model'!$C$8:$C$28) -> 256.5 | F32: =SUMPRODUCT(('Revenue Model'!$E$8:$E$28=F$31)*'Revenue Model'!$C$8:$C$28) -> 371.5 | G32: =SUMPRODUCT(('Revenue Model'!$E$8:$E$28=G$31)*'Revenue Model'!$C$8:$C$28) -> 121.5 | H32: =SUMPRODUCT(('Revenue Model'!$E$8:$E$28=H$31)*'Revenue Model'!$C$8:$C$28) -> 365.2 | I32: =SUMPRODUCT(('Revenue Model'!$E$8:$E$28=I$31)*'Revenue Model'!$C$8:$C$28) -> 557.7 | J32: =SUMPRODUCT(('Revenue Model'!$E$8:$E$28=J$31)*'Revenue Model'!$C$8:$C$28) -> 248 | ... V32: =SUMPRODUCT(('Revenue Model'!$E$8:$E$28=V$31)*'Revenue Model'!$C$8:$C$28) -> 0 | W32: 链接 Revenue Model 机组清单（含情景延迟）
A33: 核电年末装机 | B33: 万千瓦 | C33: ='Revenue Model'!G41 -> 2760.2 | D33: ='Revenue Model'!H41 -> 3264.3 | E33: ='Revenue Model'!I41 -> 3520.8 | F33: ='Revenue Model'!J41 -> 3892.3 | G33: ='Revenue Model'!K41 -> 4013.8 | H33: =G33+H32 -> 4379 | I33: =H33+I32 -> 4936.7 | J33: =I33+J32 -> 5184.7 | K33: =J33+K32 -> 5184.7 | L33: =K33+L32 -> 5184.7 | M33: =L33+M32 -> 5184.7 | N33: =M33+N32 -> 5184.7 | O33: =N33+O32 -> 5184.7 | ... V33: =U33+V32 -> 5184.7
A34: 核电平均装机 | B34: 万千瓦 | C34: ='Income Statement'!G20 -> 2676.8 | D34: ='Income Statement'!H20 -> 2961.84 | E34: ='Income Statement'!I20 -> 3366.9 | F34: ='Income Statement'!J20 -> 3669.4 | G34: ='Income Statement'!K20 -> 3940.9 | H34: =G33+H32*'Scenarios'!$K$30 -> 4159.88 | I34: =H33+I32*'Scenarios'!$K$30 -> 4602.08 | J34: =I33+J32*'Scenarios'!$K$30 -> 5035.9 | K34: =J33+K32*'Scenarios'!$K$30 -> 5184.7 | L34: =K33+L32*'Scenarios'!$K$30 -> 5184.7 | M34: =L33+M32*'Scenarios'!$K$30 -> 5184.7 | N34: =M33+N32*'Scenarios'!$K$30 -> 5184.7 | O34: =N33+O32*'Scenarios'!$K$30 -> 5184.7 | ... V34: =U33+V32*'Scenarios'!$K$30 -> 5184.7
A35: 利用小时 | B35: 小时 | C35: ='Revenue Model'!G42 -> 7650 | D35: ='Revenue Model'!H42 -> 7950 | E35: ='Revenue Model'!I42 -> 7950 | F35: ='Revenue Model'!J42 -> 7950 | G35: ='Revenue Model'!K42 -> 7950 | H35: =G35 -> 7950 | I35: =H35 -> 7950 | J35: =I35 -> 7950 | K35: =J35 -> 7950 | L35: =K35 -> 7950 | M35: =L35 -> 7950 | N35: =M35 -> 7950 | O35: =N35 -> 7950 | ... V35: =U35 -> 7950
A36: 核电电价（不含税） | B36: 元/kWh | C36: ='Revenue Model'!G60/(1+'Revenue Model'!G61) -> 0.33451327 | D36: ='Revenue Model'!H60/(1+'Revenue Model'!H61) -> 0.33274336 | E36: ='Revenue Model'!I60/(1+'Revenue Model'!I61) -> 0.33185841 | F36: ='Revenue Model'!J60/(1+'Revenue Model'!J61) -> 0.33185841 | G36: ='Revenue Model'!K60/(1+'Revenue Model'!K61) -> 0.33185841 | H36: =G36*(1+'DCF'!$C$22) -> 0.33185841 | I36: =H36*(1+'DCF'!$C$22) -> 0.33185841 | J36: =I36*(1+'DCF'!$C$22) -> 0.33185841 | K36: =J36*(1+'DCF'!$C$22) -> 0.33185841 | L36: =K36*(1+'DCF'!$C$22) -> 0.33185841 | M36: =L36*(1+'DCF'!$C$22) -> 0.33185841 | N36: =M36*(1+'DCF'!$C$22) -> 0.33185841 | O36: =N36*(1+'DCF'!$C$22) -> 0.33185841 | ... V36: =U36*(1+'DCF'!$C$22) -> 0.33185841
A37: 核电收入 | B37: 亿元 | C37: ='Revenue Model'!G91 -> 640.81771 | D37: ='Revenue Model'!H91 -> 732.96277 | E37: ='Revenue Model'!I91 -> 830.98649 | F37: ='Revenue Model'!J91 -> 905.64668 | G37: ='Revenue Model'!K91 -> 972.65575 | H37: =H34*H35/10000*'Revenue Model'!$K$58*H36 -> 1026.7023 | I37: =I34*I35/10000*'Revenue Model'!$K$58*I36 -> 1135.842 | J37: =J34*J35/10000*'Revenue Model'!$K$58*J36 -> 1242.9133 | K37: =K34*K35/10000*'Revenue Model'!$K$58*K36 -> 1279.6387 | L37: =L34*L35/10000*'Revenue Model'!$K$58*L36 -> 1279.6387 | M37: =M34*M35/10000*'Revenue Model'!$K$58*M36 -> 1279.6387 | N37: =N34*N35/10000*'Revenue Model'!$K$58*N36 -> 1279.6387 | O37: =O34*O35/10000*'Revenue Model'!$K$58*O36 -> 1279.6387 | ... V37: =V34*V35/10000*'Revenue Model'!$K$58*V36 -> 1279.6387
A38: 新能源收入 | B38: 亿元 | C38: ='Revenue Model'!G95 -> 140.84776 | D38: ='Revenue Model'!H95 -> 148.70223 | E38: ='Revenue Model'!I95 -> 155.28513 | F38: ='Revenue Model'!J95 -> 160.65443 | G38: ='Revenue Model'!K95 -> 168.30732 | H38: =G38*(1+'DCF'!$C$23) -> 171.67347 | I38: =H38*(1+'DCF'!$C$23) -> 175.10694 | J38: =I38*(1+'DCF'!$C$23) -> 178.60908 | K38: =J38*(1+'DCF'!$C$23) -> 182.18126 | L38: =K38*(1+'DCF'!$C$23) -> 185.82489 | M38: =L38*(1+'DCF'!$C$23) -> 189.54138 | N38: =M38*(1+'DCF'!$C$23) -> 193.33221 | O38: =N38*(1+'DCF'!$C$23) -> 197.19885 | ... V38: =U38*(1+'DCF'!$C$23) -> 226.5195
A39: 其他业务收入 | B39: 亿元 | C39: ='Revenue Model'!G99 -> 25.7617 | D39: ='Revenue Model'!H99 -> 27.049785 | E39: ='Revenue Model'!I99 -> 28.402274 | F39: ='Revenue Model'!J99 -> 29.822388 | G39: ='Revenue Model'!K99 -> 31.313507 | H39: =G39*(1+'DCF'!$C$24) -> 32.252913 | I39: =H39*(1+'DCF'!$C$24) -> 33.2205 | J39: =I39*(1+'DCF'!$C$24) -> 34.217115 | K39: =J39*(1+'DCF'!$C$24) -> 35.243629 | L39: =K39*(1+'DCF'!$C$24) -> 36.300937 | M39: =L39*(1+'DCF'!$C$24) -> 37.389965 | N39: =M39*(1+'DCF'!$C$24) -> 38.511664 | O39: =N39*(1+'DCF'!$C$24) -> 39.667014 | ... V39: =U39*(1+'DCF'!$C$24) -> 48.785424
A40: 营业收入 | B40: 亿元 | C40: =C37+C38+C39 -> 807.42717 | D40: =D37+D38+D39 -> 908.71479 | E40: =E37+E38+E39 -> 1014.6739 | F40: =F37+F38+F39 -> 1096.1235 | G40: =G37+G38+G39 -> 1172.2766 | H40: =H37+H38+H39 -> 1230.6287 | I40: =I37+I38+I39 -> 1344.1694 | J40: =J37+J38+J39 -> 1455.7395 | ... V40: =V37+V38+V39 -> 1554.9437
A41: EBITDA 利润率 | B41: % | C41: ='Income Statement'!G84 -> 0.602168 | D41: ='Income Statement'!H84 -> 0.59819191 | E41: ='Income Statement'!I84 -> 0.59038868 | F41: ='Income Statement'!J84 -> 0.58200911 | G41: ='Income Statement'!K84 -> 0.57377671 | H41: =G41 -> 0.57377671 | I41: =H41 -> 0.57377671 | J41: =I41 -> 0.57377671 | K41: =J41 -> 0.57377671 | L41: =K41 -> 0.57377671 | M41: =L41 -> 0.57377671 | N41: =M41 -> 0.57377671 | O41: =N41 -> 0.57377671 | ... V41: =U41 -> 0.57377671 | W41: 二阶段沿用 2030E 利润率
A42: EBITDA | B42: 亿元 | C42: ='DCF Inputs'!G8 -> 486.2068 | D42: ='DCF Inputs'!H8 -> 543.58583 | E42: ='DCF Inputs'!I8 -> 599.05198 | F42: ='DCF Inputs'!J8 -> 637.95387 | G42: ='DCF Inputs'!K8 -> 672.625 | H42: =H40*H41 -> 706.1061 | I42: =I40*I41 -> 771.2531 | J42: =J40*J41 -> 835.26943 | K42: =K40*K41 -> 858.98024 | L42: =L40*L41 -> 861.67753 | M42: =M40*M41 -> 864.43483 | N42: =N40*N41 -> 867.25352 | O42: =O40*O41 -> 870.13502 | ... V42: =V40*V41 -> 892.19046
A43: 折旧摊销 | B43: 亿元 | C43: ='DCF Inputs'!G12 -> 233.18518 | D43: ='DCF Inputs'!H12 -> 265.07745 | E43: ='DCF Inputs'!I12 -> 298.94412 | F43: ='DCF Inputs'!J12 -> 319.31429 | G43: ='DCF Inputs'!K12 -> 331.00202 | H43: =G43*H34/G34 -> 349.39447 | I43: =H43*I34/H34 -> 386.5355 | J43: =I43*J34/I34 -> 422.97268 | K43: =J43*K34/J34 -> 435.47062 | L43: =K43*L34/K34 -> 435.47062 | M43: =L43*M34/L34 -> 435.47062 | N43: =M43*N34/M34 -> 435.47062 | O43: =N43*O34/N34 -> 435.47062 | ... V43: =U43*V34/U34 -> 435.47062 | W43: 二阶段随平均装机增长
A44: EBIT | B44: 亿元 | C44: ='DCF Inputs'!G9 -> 253.02163 | D44: ='DCF Inputs'!H9 -> 278.50839 | E44: ='DCF Inputs'!I9 -> 300.10787 | F44: ='DCF Inputs'!J9 -> 318.63958 | G44: ='DCF Inputs'!K9 -> 341.62299 | H44: =H42-H43 -> 356.71163 | I44: =I42-I43 -> 384.7176 | J44: =J42-J43 -> 412.29675 | K44: =K42-K43 -> 423.50962 | L44: =L42-L43 -> 426.20691 | M44: =M42-M43 -> 428.96421 | N44: =N42-N43 -> 431.7829 | O44: =O42-O43 -> 434.66441 | ... V44: =V42-V43 -> 456.71984
A45: 税率 | B45: % | C45: ='DCF Inputs'!G10 -> 0.235 | D45: ='DCF Inputs'!H10 -> 0.235 | E45: ='DCF Inputs'!I10 -> 0.235 | F45: ='DCF Inputs'!J10 -> 0.235 | G45: ='DCF Inputs'!K10 -> 0.235 | H45: =G45 -> 0.235 | I45: =H45 -> 0.235 | J45: =I45 -> 0.235 | K45: =J45 -> 0.235 | L45: =K45 -> 0.235 | M45: =L45 -> 0.235 | N45: =M45 -> 0.235 | O45: =N45 -> 0.235 | ... V45: =U45 -> 0.235
A46: NOPAT | B46: 亿元 | C46: =C44*(1-C45) -> 193.56154 | D46: =D44*(1-D45) -> 213.05892 | E46: =E44*(1-E45) -> 229.58252 | F46: =F44*(1-F45) -> 243.75928 | G46: =G44*(1-G45) -> 261.34158 | H46: =H44*(1-H45) -> 272.88439 | I46: =I44*(1-I45) -> 294.30896 | J46: =J44*(1-J45) -> 315.40701 | ... V46: =V44*(1-V45) -> 349.39068
A47: 资本开支 | B47: 亿元 | C47: ='DCF Inputs'!G13 -> -851.6 | D47: ='DCF Inputs'!H13 -> -857.6 | E47: ='DCF Inputs'!I13 -> -880.6 | F47: ='DCF Inputs'!J13 -> -900.6 | G47: ='DCF Inputs'!K13 -> -920.6 | H47: =-('DCF'!$C$26+'DCF'!$C$25*H43) -> -859.63668 | I47: =-('DCF'!$C$27+'DCF'!$C$25*I43) -> -681.9213 | J47: =-('DCF'!$C$28+'DCF'!$C$25*J43) -> -503.78361 | K47: =-(0+'DCF'!$C$25*K43) -> -261.28237 | L47: =-(0+'DCF'!$C$25*L43) -> -261.28237 | M47: =-(0+'DCF'!$C$25*M43) -> -261.28237 | N47: =-(0+'DCF'!$C$25*N43) -> -261.28237 | O47: =-(0+'DCF'!$C$25*O43) -> -261.28237 | P47: =-(0+'DCF'!$C$25*P43) -> -261.28237 | Q47: =-(0+'DCF'!$C$25*Q43) -> -261.28237 | R47: =-(0+'DCF'!$C$25*R43) -> -261.28237 | ... V47: =-(0+'DCF'!$C$25*V43) -> -261.28237
A48: 营运资本变动 | B48: 亿元 | C48: ='DCF Inputs'!G14 -> -54.249607 | D48: ='DCF Inputs'!H14 -> -84.750822 | E48: ='DCF Inputs'!I14 -> -45.019608 | F48: ='DCF Inputs'!J14 -> -59.936077 | G48: ='DCF Inputs'!K14 -> -24.199984 | H48: =0 -> 0 | I48: =0 -> 0 | J48: =0 -> 0 | K48: =0 -> 0 | L48: =0 -> 0 | M48: =0 -> 0 | N48: =0 -> 0 | O48: =0 -> 0 | ... V48: =0 -> 0
A49: 无杠杆自由现金流 UFCF | B49: 亿元 | C49: =C46+C43+C47+C48 -> -479.10289 | D49: =D46+D43+D47+D48 -> -464.21446 | E49: =E46+E43+E47+E48 -> -397.09297 | F49: =F46+F43+F47+F48 -> -397.46251 | G49: =G46+G43+G47+G48 -> -352.45638 | H49: =H46+H43+H47+H48 -> -237.35782 | I49: =I46+I43+I47+I48 -> -1.0768382 | J49: =J46+J43+J47+J48 -> 234.59608 | ... V49: =V46+V43+V47+V48 -> 523.57892
A50: 折现期（年末，估值基准日 2025-12-31） | B50: 年 | C50: =C$31-2025 -> 1 | D50: =D$31-2025 -> 2 | E50: =E$31-2025 -> 3 | F50: =F$31-2025 -> 4 | G50: =G$31-2025 -> 5 | H50: =H$31-2025 -> 6 | I50: =I$31-2025 -> 7 | J50: =J$31-2025 -> 8 | ... V50: =V$31-2025 -> 20
A51: 折现因子 | C51: =1/(1+'DCF'!$C$17)^C50 -> 0.96525097 | D51: =1/(1+'DCF'!$C$17)^D50 -> 0.93170943 | E51: =1/(1+'DCF'!$C$17)^E50 -> 0.89933342 | F51: =1/(1+'DCF'!$C$17)^F50 -> 0.86808245 | G51: =1/(1+'DCF'!$C$17)^G50 -> 0.83791743 | H51: =1/(1+'DCF'!$C$17)^H50 -> 0.80880061 | I51: =1/(1+'DCF'!$C$17)^I50 -> 0.78069556 | J51: =1/(1+'DCF'!$C$17)^J50 -> 0.75356715 | ... V51: =1/(1+'DCF'!$C$17)^V50 -> 0.49295229
A52: 现值 PV | B52: 亿元 | C52: =C49*C51 -> -462.45452 | D52: =D49*D51 -> -432.51299 | E52: =E49*E51 -> -357.11898 | F52: =F49*F51 -> -345.03023 | G52: =G49*G51 -> -295.32935 | H52: =H49*H51 -> -191.97515 | I52: =I49*I51 -> -0.84068283 | J52: =J49*J51 -> 176.7839 | ... V52: =V49*V51 -> 258.09943
A54: D. 企业价值→股权价值 EV to equity bridge
A55: 预测期现值合计（2026–45E） | C55: =SUM(C52:V52) -> 1779.5188
A56: 终值年 NOPAT（2045E） | C56: =V46 -> 349.39068
A57: 终值 TV（2045E） | C57: =C56*(1+'DCF'!$C$18)*(1-'DCF'!$C$18/'DCF'!$C$19)/('DCF'!$C$17-'DCF'!$C$18) -> 11104.76
A58: 终值现值 | C58: =C57*V51 -> 5474.1167
A59: 企业价值 EV | C59: =C55+C58 -> 7253.6355
A60: 终值占 EV 比例 | C60: =C58/C59 -> 0.75467215
A61: 减：有息负债（2025A） | C61: =-'DCF Inputs'!$F$19 -> -4450.9221
A62: 减：长期应付款（融资租赁等类债务） | C62: =-'Balance Sheet'!$F$43 -> -235.12448
A63: 加：货币资金 | C63: ='DCF Inputs'!$F$20 -> 155.81643
A64: 减：永续债 | C64: =-'DCF Inputs'!$F$23 -> -10
A65: 加：长期股权投资（账面） | C65: ='DCF Inputs'!$F$24 -> 103.85289
A66: 全体股东权益价值（母公司+少数股东） | C66: =C59+SUM(C61:C65) -> 2817.2582
A67: 少数股东权益占比（2030E 少数股东损益占比） | C67: ='Income Statement'!$K$66 -> 0.485
A68: 归母股权价值 | C68: =C66*(1-C67) -> 1450.888
A69: 股本（亿股） | C69: ='DCF Inputs'!$F$26 -> 205.14
A70: 每股价值（2025-12-31） | C70: =C68/C69 -> 7.0726723
A71: 股权成本 | C71: ='DCF'!$C$8 -> 0.05905
A72: 减：2026 年已派股利（中期 0.02+年末 0.16） | C72: 0.18
A73: 每股公允价值（2026-09-30） | C73: =C70*(1+C71)^0.75-C72 -> 7.2036463
A74: 减：未来 12 个月股利（≈2026E DPS） | C74: ='Income Statement'!$G$78 -> 0.14081691
A75: DCF 12 个月目标价（2027-09） | C75: =C73*(1+C71)-C74 -> 7.4882047
A76: 当前股价（2026-09-24） | C76: ='DCF Inputs'!$F$30 -> 8.9
A77: DCF 隐含空间 | C77: =C75/C76-1 -> -0.15862869
A79: 注：①少数股东分享约 48% 利润，归母价值按 2030E 少数股东损益占比分配（合资核电站多为 50–72% 控股）；②仅计入现有在运 + 22 台在建及核准机组，未计入“十五五”每年约 6 台新核准的增长价值；③终值采用价值驱动公式，避免 2045E 维护性资本开支低于折旧导致高估。

Sheet Sensitivity
A1: 敏感性分析 Sensitivity — DCF 每股价值（元，2027-09 目标价口径）
A2: 单位：亿元人民币（另有注明除外）｜蓝色=输入 黑色=公式 绿色=跨表链接
A4: 表 1：WACC × 永续增长率 g（实时公式）
A5: WACC ↓ / g → | B5: 0 | C5: 0.005 | D5: 0.01 | E5: 0.015 | F5: 0.02
A6: ='DCF'!$C$17+(-0.0075) -> 0.0285 | B6: =((((NPV($A6,'DCF'!$C$49:$V$49)+'DCF'!$V$46*(1+B$5)*(1-B$5/'DCF'!$C$19)/($A6-B$5)/(1+$A6)^20)+SUM('DCF'!$C$61:$C$65))*(1-'DCF'!$C$67)/'DCF'!$C$69)*(1+'DCF'!$C$8)^0.75-'DCF'!$C$72)*(1+'DCF'!$C$8)-'DCF'!$C$74 -> 12.70014 | C6: =((((NPV($A6,'DCF'!$C$49:$V$49)+'DCF'!$V$46*(1+C$5)*(1-C$5/'DCF'!$C$19)/($A6-C$5)/(1+$A6)^20)+SUM('DCF'!$C$61:$C$65))*(1-'DCF'!$C$67)/'DCF'!$C$69)*(1+'DCF'!$C$8)^0.75-'DCF'!$C$72)*(1+'DCF'!$C$8)-'DCF'!$C$74 -> 14.795573 | D6: =((((NPV($A6,'DCF'!$C$49:$V$49)+'DCF'!$V$46*(1+D$5)*(1-D$5/'DCF'!$C$19)/($A6-D$5)/(1+$A6)^20)+SUM('DCF'!$C$61:$C$65))*(1-'DCF'!$C$67)/'DCF'!$C$69)*(1+'DCF'!$C$8)^0.75-'DCF'!$C$72)*(1+'DCF'!$C$8)-'DCF'!$C$74 -> 17.996508 | E6: =((((NPV($A6,'DCF'!$C$49:$V$49)+'DCF'!$V$46*(1+E$5)*(1-E$5/'DCF'!$C$19)/($A6-E$5)/(1+$A6)^20)+SUM('DCF'!$C$61:$C$65))*(1-'DCF'!$C$67)/'DCF'!$C$69)*(1+'DCF'!$C$8)^0.75-'DCF'!$C$72)*(1+'DCF'!$C$8)-'DCF'!$C$74 -> 23.531277 | F6: =((((NPV($A6,'DCF'!$C$49:$V$49)+'DCF'!$V$46*(1+F$5)*(1-F$5/'DCF'!$C$19)/($A6-F$5)/(1+$A6)^20)+SUM('DCF'!$C$61:$C$65))*(1-'DCF'!$C$67)/'DCF'!$C$69)*(1+'DCF'!$C$8)^0.75-'DCF'!$C$72)*(1+'DCF'!$C$8)-'DCF'!$C$74 -> 35.518415
A7: ='DCF'!$C$17+(-0.005) -> 0.031 | B7: =((((NPV($A7,'DCF'!$C$49:$V$49)+'DCF'!$V$46*(1+B$5)*(1-B$5/'DCF'!$C$19)/($A7-B$5)/(1+$A7)^20)+SUM('DCF'!$C$61:$C$65))*(1-'DCF'!$C$67)/'DCF'!$C$69)*(1+'DCF'!$C$8)^0.75-'DCF'!$C$72)*(1+'DCF'!$C$8)-'DCF'!$C$74 -> 9.9402493 | C7: =((((NPV($A7,'DCF'!$C$49:$V$49)+'DCF'!$V$46*(1+C$5)*(1-C$5/'DCF'!$C$19)/($A7-C$5)/(1+$A7)^20)+SUM('DCF'!$C$61:$C$65))*(1-'DCF'!$C$67)/'DCF'!$C$69)*(1+'DCF'!$C$8)^0.75-'DCF'!$C$72)*(1+'DCF'!$C$8)-'DCF'!$C$74 -> 11.457865 | D7: =((((NPV($A7,'DCF'!$C$49:$V$49)+'DCF'!$V$46*(1+D$5)*(1-D$5/'DCF'!$C$19)/($A7-D$5)/(1+$A7)^20)+SUM('DCF'!$C$61:$C$65))*(1-'DCF'!$C$67)/'DCF'!$C$69)*(1+'DCF'!$C$8)^0.75-'DCF'!$C$72)*(1+'DCF'!$C$8)-'DCF'!$C$74 -> 13.675358 | E7: =((((NPV($A7,'DCF'!$C$49:$V$49)+'DCF'!$V$46*(1+E$5)*(1-E$5/'DCF'!$C$19)/($A7-E$5)/(1+$A7)^20)+SUM('DCF'!$C$61:$C$65))*(1-'DCF'!$C$67)/'DCF'!$C$69)*(1+'DCF'!$C$8)^0.75-'DCF'!$C$72)*(1+'DCF'!$C$8)-'DCF'!$C$74 -> 17.248862 | F7: =((((NPV($A7,'DCF'!$C$49:$V$49)+'DCF'!$V$46*(1+F$5)*(1-F$5/'DCF'!$C$19)/($A7-F$5)/(1+$A7)^20)+SUM('DCF'!$C$61:$C$65))*(1-'DCF'!$C$67)/'DCF'!$C$69)*(1+'DCF'!$C$8)^0.75-'DCF'!$C$72)*(1+'DCF'!$C$8)-'DCF'!$C$74 -> 24.027483
A8: ='DCF'!$C$17+(-0.0025) -> 0.0335 | B8: =((((NPV($A8,'DCF'!$C$49:$V$49)+'DCF'!$V$46*(1+B$5)*(1-B$5/'DCF'!$C$19)/($A8-B$5)/(1+$A8)^20)+SUM('DCF'!$C$61:$C$65))*(1-'DCF'!$C$67)/'DCF'!$C$69)*(1+'DCF'!$C$8)^0.75-'DCF'!$C$72)*(1+'DCF'!$C$8)-'DCF'!$C$74 -> 7.5931657 | C8: =((((NPV($A8,'DCF'!$C$49:$V$49)+'DCF'!$V$46*(1+C$5)*(1-C$5/'DCF'!$C$19)/($A8-C$5)/(1+$A8)^20)+SUM('DCF'!$C$61:$C$65))*(1-'DCF'!$C$67)/'DCF'!$C$69)*(1+'DCF'!$C$8)^0.75-'DCF'!$C$72)*(1+'DCF'!$C$8)-'DCF'!$C$74 -> 8.7002986 | D8: =((((NPV($A8,'DCF'!$C$49:$V$49)+'DCF'!$V$46*(1+D$5)*(1-D$5/'DCF'!$C$19)/($A8-D$5)/(1+$A8)^20)+SUM('DCF'!$C$61:$C$65))*(1-'DCF'!$C$67)/'DCF'!$C$69)*(1+'DCF'!$C$8)^0.75-'DCF'!$C$72)*(1+'DCF'!$C$8)-'DCF'!$C$74 -> 10.259143 | E8: =((((NPV($A8,'DCF'!$C$49:$V$49)+'DCF'!$V$46*(1+E$5)*(1-E$5/'DCF'!$C$19)/($A8-E$5)/(1+$A8)^20)+SUM('DCF'!$C$61:$C$65))*(1-'DCF'!$C$67)/'DCF'!$C$69)*(1+'DCF'!$C$8)^0.75-'DCF'!$C$72)*(1+'DCF'!$C$8)-'DCF'!$C$74 -> 12.635951 | F8: =((((NPV($A8,'DCF'!$C$49:$V$49)+'DCF'!$V$46*(1+F$5)*(1-F$5/'DCF'!$C$19)/($A8-F$5)/(1+$A8)^20)+SUM('DCF'!$C$61:$C$65))*(1-'DCF'!$C$67)/'DCF'!$C$69)*(1+'DCF'!$C$8)^0.75-'DCF'!$C$72)*(1+'DCF'!$C$8)-'DCF'!$C$74 -> 16.739573
A9: ='DCF'!$C$17+(0) -> 0.036 | B9: =((((NPV($A9,'DCF'!$C$49:$V$49)+'DCF'!$V$46*(1+B$5)*(1-B$5/'DCF'!$C$19)/($A9-B$5)/(1+$A9)^20)+SUM('DCF'!$C$61:$C$65))*(1-'DCF'!$C$67)/'DCF'!$C$69)*(1+'DCF'!$C$8)^0.75-'DCF'!$C$72)*(1+'DCF'!$C$8)-'DCF'!$C$74 -> 5.5733888 | C9: =((((NPV($A9,'DCF'!$C$49:$V$49)+'DCF'!$V$46*(1+C$5)*(1-C$5/'DCF'!$C$19)/($A9-C$5)/(1+$A9)^20)+SUM('DCF'!$C$61:$C$65))*(1-'DCF'!$C$67)/'DCF'!$C$69)*(1+'DCF'!$C$8)^0.75-'DCF'!$C$72)*(1+'DCF'!$C$8)-'DCF'!$C$74 -> 6.3833857 | D9: =((((NPV($A9,'DCF'!$C$49:$V$49)+'DCF'!$V$46*(1+D$5)*(1-D$5/'DCF'!$C$19)/($A9-D$5)/(1+$A9)^20)+SUM('DCF'!$C$61:$C$65))*(1-'DCF'!$C$67)/'DCF'!$C$69)*(1+'DCF'!$C$8)^0.75-'DCF'!$C$72)*(1+'DCF'!$C$8)-'DCF'!$C$74 -> 7.4882047 | E9: =((((NPV($A9,'DCF'!$C$49:$V$49)+'DCF'!$V$46*(1+E$5)*(1-E$5/'DCF'!$C$19)/($A9-E$5)/(1+$A9)^20)+SUM('DCF'!$C$61:$C$65))*(1-'DCF'!$C$67)/'DCF'!$C$69)*(1+'DCF'!$C$8)^0.75-'DCF'!$C$72)*(1+'DCF'!$C$8)-'DCF'!$C$74 -> 9.098433 | F9: =((((NPV($A9,'DCF'!$C$49:$V$49)+'DCF'!$V$46*(1+F$5)*(1-F$5/'DCF'!$C$19)/($A9-F$5)/(1+$A9)^20)+SUM('DCF'!$C$61:$C$65))*(1-'DCF'!$C$67)/'DCF'!$C$69)*(1+'DCF'!$C$8)^0.75-'DCF'!$C$72)*(1+'DCF'!$C$8)-'DCF'!$C$74 -> 11.687892
A10: ='DCF'!$C$17+(0.0025) -> 0.0385 | B10: =((((NPV($A10,'DCF'!$C$49:$V$49)+'DCF'!$V$46*(1+B$5)*(1-B$5/'DCF'!$C$19)/($A10-B$5)/(1+$A10)^20)+SUM('DCF'!$C$61:$C$65))*(1-'DCF'!$C$67)/'DCF'!$C$69)*(1+'DCF'!$C$8)^0.75-'DCF'!$C$72)*(1+'DCF'!$C$8)-'DCF'!$C$74 -> 3.81759 | C10: =((((NPV($A10,'DCF'!$C$49:$V$49)+'DCF'!$V$46*(1+C$5)*(1-C$5/'DCF'!$C$19)/($A10-C$5)/(1+$A10)^20)+SUM('DCF'!$C$61:$C$65))*(1-'DCF'!$C$67)/'DCF'!$C$69)*(1+'DCF'!$C$8)^0.75-'DCF'!$C$72)*(1+'DCF'!$C$8)-'DCF'!$C$74 -> 4.4092215 | D10: =((((NPV($A10,'DCF'!$C$49:$V$49)+'DCF'!$V$46*(1+D$5)*(1-D$5/'DCF'!$C$19)/($A10-D$5)/(1+$A10)^20)+SUM('DCF'!$C$61:$C$65))*(1-'DCF'!$C$67)/'DCF'!$C$69)*(1+'DCF'!$C$8)^0.75-'DCF'!$C$72)*(1+'DCF'!$C$8)-'DCF'!$C$74 -> 5.1939117 | E10: =((((NPV($A10,'DCF'!$C$49:$V$49)+'DCF'!$V$46*(1+E$5)*(1-E$5/'DCF'!$C$19)/($A10-E$5)/(1+$A10)^20)+SUM('DCF'!$C$61:$C$65))*(1-'DCF'!$C$67)/'DCF'!$C$69)*(1+'DCF'!$C$8)^0.75-'DCF'!$C$72)*(1+'DCF'!$C$8)-'DCF'!$C$74 -> 6.2948894 | F10: =((((NPV($A10,'DCF'!$C$49:$V$49)+'DCF'!$V$46*(1+F$5)*(1-F$5/'DCF'!$C$19)/($A10-F$5)/(1+$A10)^20)+SUM('DCF'!$C$61:$C$65))*(1-'DCF'!$C$67)/'DCF'!$C$69)*(1+'DCF'!$C$8)^0.75-'DCF'!$C$72)*(1+'DCF'!$C$8)-'DCF'!$C$74 -> 7.9686043
A11: ='DCF'!$C$17+(0.005) -> 0.041 | B11: =((((NPV($A11,'DCF'!$C$49:$V$49)+'DCF'!$V$46*(1+B$5)*(1-B$5/'DCF'!$C$19)/($A11-B$5)/(1+$A11)^20)+SUM('DCF'!$C$61:$C$65))*(1-'DCF'!$C$67)/'DCF'!$C$69)*(1+'DCF'!$C$8)^0.75-'DCF'!$C$72)*(1+'DCF'!$C$8)-'DCF'!$C$74 -> 2.2778547 | C11: =((((NPV($A11,'DCF'!$C$49:$V$49)+'DCF'!$V$46*(1+C$5)*(1-C$5/'DCF'!$C$19)/($A11-C$5)/(1+$A11)^20)+SUM('DCF'!$C$61:$C$65))*(1-'DCF'!$C$67)/'DCF'!$C$69)*(1+'DCF'!$C$8)^0.75-'DCF'!$C$72)*(1+'DCF'!$C$8)-'DCF'!$C$74 -> 2.7070485 | D11: =((((NPV($A11,'DCF'!$C$49:$V$49)+'DCF'!$V$46*(1+D$5)*(1-D$5/'DCF'!$C$19)/($A11-D$5)/(1+$A11)^20)+SUM('DCF'!$C$61:$C$65))*(1-'DCF'!$C$67)/'DCF'!$C$69)*(1+'DCF'!$C$8)^0.75-'DCF'!$C$72)*(1+'DCF'!$C$8)-'DCF'!$C$74 -> 3.2619597 | E11: =((((NPV($A11,'DCF'!$C$49:$V$49)+'DCF'!$V$46*(1+E$5)*(1-E$5/'DCF'!$C$19)/($A11-E$5)/(1+$A11)^20)+SUM('DCF'!$C$61:$C$65))*(1-'DCF'!$C$67)/'DCF'!$C$69)*(1+'DCF'!$C$8)^0.75-'DCF'!$C$72)*(1+'DCF'!$C$8)-'DCF'!$C$74 -> 4.0151176 | F11: =((((NPV($A11,'DCF'!$C$49:$V$49)+'DCF'!$V$46*(1+F$5)*(1-F$5/'DCF'!$C$19)/($A11-F$5)/(1+$A11)^20)+SUM('DCF'!$C$61:$C$65))*(1-'DCF'!$C$67)/'DCF'!$C$69)*(1+'DCF'!$C$8)^0.75-'DCF'!$C$72)*(1+'DCF'!$C$8)-'DCF'!$C$74 -> 5.1081269
A12: ='DCF'!$C$17+(0.0075) -> 0.0435 | B12: =((((NPV($A12,'DCF'!$C$49:$V$49)+'DCF'!$V$46*(1+B$5)*(1-B$5/'DCF'!$C$19)/($A12-B$5)/(1+$A12)^20)+SUM('DCF'!$C$61:$C$65))*(1-'DCF'!$C$67)/'DCF'!$C$69)*(1+'DCF'!$C$8)^0.75-'DCF'!$C$72)*(1+'DCF'!$C$8)-'DCF'!$C$74 -> 0.91725504 | C12: =((((NPV($A12,'DCF'!$C$49:$V$49)+'DCF'!$V$46*(1+C$5)*(1-C$5/'DCF'!$C$19)/($A12-C$5)/(1+$A12)^20)+SUM('DCF'!$C$61:$C$65))*(1-'DCF'!$C$67)/'DCF'!$C$69)*(1+'DCF'!$C$8)^0.75-'DCF'!$C$72)*(1+'DCF'!$C$8)-'DCF'!$C$74 -> 1.2244454 | D12: =((((NPV($A12,'DCF'!$C$49:$V$49)+'DCF'!$V$46*(1+D$5)*(1-D$5/'DCF'!$C$19)/($A12-D$5)/(1+$A12)^20)+SUM('DCF'!$C$61:$C$65))*(1-'DCF'!$C$67)/'DCF'!$C$69)*(1+'DCF'!$C$8)^0.75-'DCF'!$C$72)*(1+'DCF'!$C$8)-'DCF'!$C$74 -> 1.6121043 | E12: =((((NPV($A12,'DCF'!$C$49:$V$49)+'DCF'!$V$46*(1+E$5)*(1-E$5/'DCF'!$C$19)/($A12-E$5)/(1+$A12)^20)+SUM('DCF'!$C$61:$C$65))*(1-'DCF'!$C$67)/'DCF'!$C$69)*(1+'DCF'!$C$8)^0.75-'DCF'!$C$72)*(1+'DCF'!$C$8)-'DCF'!$C$74 -> 2.1225834 | F12: =((((NPV($A12,'DCF'!$C$49:$V$49)+'DCF'!$V$46*(1+F$5)*(1-F$5/'DCF'!$C$19)/($A12-F$5)/(1+$A12)^20)+SUM('DCF'!$C$61:$C$65))*(1-'DCF'!$C$67)/'DCF'!$C$69)*(1+'DCF'!$C$8)^0.75-'DCF'!$C$72)*(1+'DCF'!$C$8)-'DCF'!$C$74 -> 2.8342788
A13: 基准：WACC 与 g 见 DCF 工作表；中心格应等于 DCF 目标价
A15: 表 2：核电电价（含税，元/kWh，相对基准）× 利用小时（相对基准）— 全模型重算（静态）
A16: 电价变动 ↓ / 小时变动 → | B16: -300 | C16: -150 | D16: 0 | E16: 150 | F16: 300
A17: -0.02 | B17: 1.4445748 | C17: 2.4641674 | D17: 3.4837598 | E17: 4.5033521 | F17: 5.5229443
A18: -0.01 | B18: 3.3712107 | C18: 4.4285967 | D18: 5.4859826 | E18: 6.5433683 | F18: 7.6007539
A19: 0 | B19: 5.2978459 | C19: 6.3930253 | D19: 7.4882047 | E19: 8.5833839 | F19: 9.678563
A20: 0.01 | B20: 7.2244805 | C20: 8.3574535 | D20: 9.4904263 | E20: 10.623399 | F20: 11.756371
A21: 0.02 | B21: 9.1511146 | C21: 10.321881 | D21: 11.492647 | E21: 12.663413 | F21: 13.834179
A22: 每格为将基准情景 2026–30E 电价/小时整体平移后，全模型（收入→利润→现金流→DCF）重算的 DCF 目标价；静态快照。
A24: 表 3：资本开支超支 × 新机组延迟 — 全模型重算（静态）
A25: 资本开支超支 ↓ / 投产延迟（年） → | B25: 0 | C25: 1 | D25: 2
A26: 0 | B26: 7.4882047 | C26: 6.4890379 | D26: 5.9681434
A27: 0.05 | B27: 7.0303097 | C27: 6.0311429 | D27: 5.5102484
A28: 0.1 | B28: 6.5724147 | C28: 5.5732479 | D28: 5.0523534
A29: 基准情景下叠加资本开支超支与全部新机组延迟；静态快照。

Sheet Comps
A1: 可比公司 Comparable companies（市场数据为 2026 年 8–9 月快照；来源见 L 列）
A2: 单位：亿元人民币（另有注明除外）｜蓝色=输入 黑色=公式 绿色=跨表链接
A4: 公司 | B4: 代码 | C4: 类别 | D4: PE（动态/预测） | E4: PE TTM | F4: PB | G4: 股息率 | H4: 2026H1 归母净利同比 | I4: 计入统计 | L4: 来源 / 口径说明
A5: 中国广核 A | B5: 003816.SZ | C5: 核电 | D5: 17.9 | E5: 19 | F5: 1.6 | G5: 0.0223 | H5: 0.0266 | I5: 1 | L5: PE TTM 19.0、PB 1.60、股息率 2.23%（理杏仁/同花顺快照）；PE 预测=TTM×TTM 净利 99.2 亿/2026E 一致预期 105.35 亿（推算）
A6: 中广核电力 H | B6: 1816.HK | C6: 核电 | D6: 15 | E6: 15 | F6: 1.26 | G6: 0.0284 | H6: 0.0266 | I6: 1 | L6: PE TTM 14.05–15.94 取中值；PB 1.26；股息率 2.84%（gu.qq.com/investing）
A7: 电投产融 | B7: 000958.SZ | C7: 核电 | D7: 23 | E7: 31.2 | F7: 2.16 | I7: 1 | L7: 国家电投核电平台（2026-01 完成重组）；PE 动态 22.1–23.8、静态 30.0–32.3、PB 1.97–2.35 取中值
A8: 长江电力 | B8: 600900.SH | C8: 水电 | D8: 25.3 | E8: 19.8 | F8: 3 | G8: 0.0355 | H8: 0.1302 | I8: 1 | L8: PE 动态 25.3 / 静态 19.8；PB 3.00；股息率 3.55%
A9: 国投电力 | B9: 600886.SH | C9: 水电/综合 | D9: 15 | E9: 14.8 | F9: 1.63 | G9: 0.033 | H9: -0.0683 | I9: 1 | L9: PE 2026E 约 14.5–15.5（EPS 0.89–0.95 推算）；PB 1.60–1.67
A10: 川投能源 | B10: 600674.SH | C10: 水电 | D10: 15.9 | E10: 15.9 | F10: 1.69 | H10: -0.0534 | I10: 1 | L10: PE 静态 15.9；PB 1.69；承诺 2026–28 分红率≥50%
A11: 三峡能源 | B11: 600905.SH | C11: 新能源 | D11: 29.5 | E11: 33 | F11: 1.37 | G11: 0.011 | H11: -0.6805 | I11: 1 | L11: PE 动态 29.5 / 静态 33.0；PB 1.37；股息率 1.10%
A12: 龙源电力 | B12: 001289.SZ | C12: 新能源 | D12: 26 | F12: 1.62 | G12: 0.017 | H12: -0.291 | I12: 1 | L12: PE 动态 26.1；PB 1.62；股息率 1.28–2.14% 取中值
A13: 华能国际 | B13: 600011.SH | C13: 火电（参考） | D13: 8.5 | E13: 8.5 | F13: 0.84 | G13: 0.053 | H13: -0.2889 | I13: 0 | L13: 仅参考，不计入统计：火电周期属性
A14: Constellation | B14: CEG.US | C14: 美国核电（参考） | D14: 23.9 | I14: 0 | L14: FY26 远期 PE 23.9（gurufocus，2026-09-25）；美国核电享受数据中心购电溢价，不计入统计
A16: 统计（前 8 家，I 列=1）Statistical summary
A17: 最大值 Max | D17: =MAX(D5:D12) -> 29.5 | E17: =MAX(E5:E12) -> 33 | F17: =MAX(F5:F12) -> 3 | G17: =MAX(G5:G12) -> 0.0355 | H17: =MAX(H5:H12) -> 0.1302
A18: 75 分位 75th | D18: =PERCENTILE(D5:D12,0.75) -> 25.475 | E18: =PERCENTILE(E5:E12,0.75) -> 25.5 | F18: =PERCENTILE(F5:F12,0.75) -> 1.8075 | G18: =PERCENTILE(G5:G12,0.75) -> 0.03185 | H18: =PERCENTILE(H5:H12,0.75) -> 0.0266
A19: 中位数 Median | D19: =MEDIAN(D5:D12) -> 20.45 | E19: =MEDIAN(E5:E12) -> 19 | F19: =MEDIAN(F5:F12) -> 1.625 | G19: =MEDIAN(G5:G12) -> 0.02535 | H19: =MEDIAN(H5:H12) -> -0.0534
A20: 25 分位 25th | D20: =PERCENTILE(D5:D12,0.25) -> 15.675 | E20: =PERCENTILE(E5:E12,0.25) -> 15.45 | F20: =PERCENTILE(F5:F12,0.25) -> 1.5425 | G20: =PERCENTILE(G5:G12,0.25) -> 0.018325 | H20: =PERCENTILE(H5:H12,0.25) -> -0.17965
A21: 最小值 Min | D21: =MIN(D5:D12) -> 15 | E21: =MIN(E5:E12) -> 14.8 | F21: =MIN(F5:F12) -> 1.26 | G21: =MIN(G5:G12) -> 0.011 | H21: =MIN(H5:H12) -> -0.6805
A22: 核电同行均值（3 家） | D22: =AVERAGE(D5:D7) -> 18.633333 | E22: =AVERAGE(E5:E7) -> 21.733333 | F22: =AVERAGE(F5:F7) -> 1.6733333 | G22: =AVERAGE(G5:G7) -> 0.02535
A24: 中国核电（模型，基准情景） | D24: ='DCF Inputs'!$G$32 -> 25.281054 | E24: ='DCF'!$C$76/(('Income Statement'!$F$68-56.66+36.41)/'Income Statement'!$G$74) -> 25.081645 | F24: ='DCF Inputs'!$F$33 -> 1.5509541 | G24: ='DCF Inputs'!$G$34 -> 0.015822125 | H24: -0.3574 | L24: PE 预测=2026-09-24 股价 8.90 元 / 模型 2026E EPS；PE TTM 用 2025A 归母 − 2025H1 56.66 + 2026H1 36.41；历史 PE 区间 12.0–30.7 倍、均值 19.0 倍，当前处 5 年 97% 分位（亿牛网）
A26: 可比估值法 Implied share price
A27: 方法 | B27: 倍数列 | C27: 中国核电指标 | D27: 25 分位 | E27: 中位数 | F27: 75 分位 | G27: 隐含股价 低 | H27: 隐含股价 中 | I27: 隐含股价 高 | L27: 说明
A28: PE（2027E EPS） | B28: D | C28: ='Income Statement'!$H$75 -> 0.39886862 | D28: =D20 -> 15.675 | E28: =D19 -> 20.45 | F28: =D18 -> 25.475 | G28: =C28*D28 -> 6.2522656 | H28: =C28*E28 -> 8.1568633 | I28: =C28*F28 -> 10.161178 | L28: 以 2027E（12 个月后市场定价年份）EPS × 同行 PE
A29: PB（2026E BVPS） | B29: F | C29: =('Balance Sheet'!$G$57-'Balance Sheet'!$G$52)/'Income Statement'!$G$74 -> 5.9104405 | D29: =F20 -> 1.5425 | E29: =F19 -> 1.625 | F29: =F18 -> 1.8075 | G29: =C29*D29 -> 9.1168545 | H29: =C29*E29 -> 9.6044658 | I29: =C29*F29 -> 10.683121 | L29: 2026E 每股归母净资产（不含永续债）× 同行 PB
A30: 股息率（2026E DPS） | B30: G | C30: ='Income Statement'!$G$78 -> 0.14081691 | D30: =G20 -> 0.018325 | E30: =G19 -> 0.02535 | F30: =G18 -> 0.03185 | G30: =C30/F30 -> 4.4212532 | H30: =C30/E30 -> 5.5549078 | I30: =C30/D30 -> 7.6844155 | L30: DPS ÷ 同行股息率（高股息率对应低估值）
A32: 注：①A 股公用事业通常以 PE/PB/股息率定价，同行 EV/EBITDA 公开数据缺失，未采用；②同行 PE 口径混合（动态/静态/预测），已在 L 列标注；③数据通过检索摘要获取，未能逐一访问原始页面核对。

Sheet Precedents
A1: 可比交易 Precedent transactions（中国核电/清洁能源资产，2024–2026）
A2: 单位：亿元人民币（另有注明除外）｜蓝色=输入 黑色=公式 绿色=跨表链接
A4: 时间 | B4: 标的 | C4: 买方/投资方 | D4: 对价(亿元) | E4: 隐含 PB | F4: 计入 | G4: 说明与来源
A5: 2025-03 | B5: 电投核能 100% | C5: 电投产融（国家电投） | D5: 571.23 | E5: 1.47 | F5: 1 | G5: 资产基础法定价，增值率 46.95%（隐含 PB≈1.47，推算）；评估基准日 2024-09-30；在运装机 921 万kW。界面新闻/新浪财经
A6: 2024-12 | B6: 中国核电定增 16.85 亿股 | C6: 社保基金会 120 亿 + 中核集团 20 亿 | D6: 140 | E6: 1.56 | F6: 1 | G6: 发行价 8.31 元 ÷ 2024 年末每股归母净资产（不含永续债）5.31 元≈1.56x（推算）。新浪财经
A7: 2024-11 | B7: 中核汇能增资 7.29% | C7: 中核集团、国寿、川投、浙能等 | D7: 78.96 | E7: 2.18 | F7: 1 | G7: 投前估值 267.58 亿 ÷ 账面 122.86 亿≈2.18x；新能源平台。中国基金报/公告
A8: 2026-04 | B8: 苍南核电 46% + 苍南二核 51% | C8: 中国广核 | D8: 83.47 | F8: 0 | G8: 隐含 PB 未披露，不计入。中国能源新闻网
A9: 2025-01 | B9: 台山第二核电 100% | C9: 中国广核 | D9: 12.04 | F9: 0 | G9: 前期项目公司，不计入
B11: 隐含 PB 低 | E11: =MIN($E$5:$E$7) -> 1.47
B12: 隐含 PB 中位数 | E12: =MEDIAN($E$5:$E$7) -> 1.56
B13: 隐含 PB 高 | E13: =MAX($E$5:$E$7) -> 2.18
B14: 2026E 每股归母净资产 | E14: =('Balance Sheet'!$G$57-'Balance Sheet'!$G$52)/'Income Statement'!$G$74 -> 5.9104405
B15: 隐含股价 低 | E15: =E11*E14 -> 8.6883475
B16: 隐含股价 中 | E16: =E12*E14 -> 9.2202872
B17: 隐含股价 高 | E17: =E13*E14 -> 12.88476
A19: 注：中国核电为中核集团控股，控制权交易可能性极低；可比交易反映核电资产的一级市场定价锚，权重 10%。

Sheet Valuation Summary
A1: 估值汇总与评级 Valuation summary & recommendation
A2: 单位：亿元人民币（另有注明除外）｜蓝色=输入 黑色=公式 绿色=跨表链接
A4: 方法 | B4: 低 | C4: 基准 | D4: 高 | E4: 权重 | F4: 加权值 | I4: 依据
A5: DCF（三阶段） | B5: =MIN(Sensitivity!C8:E10) -> 4.4092215 | C5: ='DCF'!$C$75 -> 7.4882047 | D5: =MAX(Sensitivity!C8:E10) -> 12.635951 | E5: 0.4 | F5: =C5*E5 -> 2.9952819 | I5: 低/高=WACC±0.5%、g 0.5–1.5% 区间
A6: PE 可比（2027E） | B6: ='Comps'!G28 -> 6.2522656 | C6: ='Comps'!H28 -> 8.1568633 | D6: ='Comps'!I28 -> 10.161178 | E6: 0.25 | F6: =C6*E6 -> 2.0392158 | I6: 同行 PE 25/50/75 分位 × 2027E EPS
A7: PB 可比（2026E） | B7: ='Comps'!G29 -> 9.1168545 | C7: ='Comps'!H29 -> 9.6044658 | D7: ='Comps'!I29 -> 10.683121 | E7: 0.15 | F7: =C7*E7 -> 1.4406699 | I7: 同行 PB 25/50/75 分位 × 2026E BVPS
A8: 股息率（2026E） | B8: ='Comps'!G30 -> 4.4212532 | C8: ='Comps'!H30 -> 5.5549078 | D8: ='Comps'!I30 -> 7.6844155 | E8: 0.1 | F8: =C8*E8 -> 0.55549078 | I8: 2026E DPS ÷ 同行股息率
A9: 可比交易 PB | B9: ='Precedents'!$E$15 -> 8.6883475 | C9: ='Precedents'!$E$16 -> 9.2202872 | D9: ='Precedents'!$E$17 -> 12.88476 | E9: 0.1 | F9: =C9*E9 -> 0.92202872 | I9: 核电资产一级市场 PB 1.47–2.18x
A10: 加权目标价 Weighted value | E10: =SUM(E5:E9) -> 1 | F10: =SUM(F5:F9) -> 7.9526871
A12: 目标价（12 个月，取整至 0.1 元） | C12: =ROUND(F10,1) -> 8
A13: 当前股价（2026-09-24） | C13: ='DCF'!$C$76 -> 8.9
A14: 隐含涨跌幅 | C14: =C12/C13-1 -> -0.1011236
A15: 加：预期股息率（2026E） | C15: ='DCF Inputs'!$G$34 -> 0.015822125
A16: 预期总回报 | C16: =C14+C15 -> -0.08530147
A17: 评级（预期总回报 >15% 买入｜5–15% 增持｜−5%~5% 中性｜<−5% 减持） | C17: =IF(C16>0.15,"买入 BUY",IF(C16>0.05,"增持 OUTPERFORM",IF(C16>=-0.05,"中性 HOLD","减持 SELL"))) -> 减持 SELL
A18: 目标价对应 2026E / 2027E PE | C18: =C12/'Income Statement'!$G$75 -> 22.724543 | D18: =C12/'Income Statement'!$H$75 -> 20.056729
A20: 情景估值 Scenario valuation（DCF 目标价，全模型重算静态快照）
A21: 情景 | B21: 概率 | C21: 2026E 归母 | D21: 2030E 归母 | E21: 2027E EPS | F21: DCF 目标价 | G21: PE 可比（中位） | I21: 情景说明
A22: Bull 牛市 | B22: 0.25 | C22: 85.129041 | D22: 131.71367 | E22: 0.49568451 | F22: 13.798035 | G22: =E22*'Comps'!$E$28 -> 10.136748 | I22: 机制电价全国推广、电价回升至 0.39 元、利用小时 8,050
A23: Base 基准 | B23: 0.5 | C23: 72.480554 | D23: 97.590465 | E23: 0.39886862 | F23: 7.4882047 | G23: =E23*'Comps'!$E$28 -> 8.1568633 | I23: 电价 0.375 元企稳、利用小时 7,950、按计划投产
A24: Bear 熊市 | B24: 0.25 | C24: 59.552186 | D24: 45.633535 | E24: 0.28145682 | F24: -2.8366691 | G24: =E24*'Comps'!$E$28 -> 5.755792 | I24: 电价降至 0.35 元、新机组推迟 1 年、资本开支超支 5%
A25: 概率加权 | F25: =SUMPRODUCT($B22:$B24,F22:F24) -> 6.4844438 | G25: =SUMPRODUCT($B22:$B24,G22:G24) -> 8.0515667
A27: 估值区间图数据 Football field
A28: 方法 | B28: 低 | C28: 高 | D28: 区间宽度 | I28: 备注
A29: =A5 -> DCF（三阶段） | B29: =B5 -> 4.4092215 | C29: =D5 -> 12.635951 | D29: =C29-B29 -> 8.2267299
A30: =A6 -> PE 可比（2027E） | B30: =B6 -> 6.2522656 | C30: =D6 -> 10.161178 | D30: =C30-B30 -> 3.9089125
A31: =A7 -> PB 可比（2026E） | B31: =B7 -> 9.1168545 | C31: =D7 -> 10.683121 | D31: =C31-B31 -> 1.5662667
A32: =A8 -> 股息率（2026E） | B32: =B8 -> 4.4212532 | C32: =D8 -> 7.6844155 | D32: =C32-B32 -> 3.2631623
A33: =A9 -> 可比交易 PB | B33: =B9 -> 8.6883475 | C33: =D9 -> 12.88476 | D33: =C33-B33 -> 4.1964128
A34: 52 周股价区间 | I34: 未能获取可靠的 52 周区间数据（检索摘要缺失），留空
A35: 当前股价 / 目标价 | B35: ='DCF'!$C$76 -> 8.9 | C35: =C12 -> 8

Sheet Checks
A1: 模型校验 Checks（全部应为 TRUE）
A2: 单位：亿元人民币（另有注明除外）｜蓝色=硬编码输入 黑色=公式 绿色=跨表链接｜A=实际 E=预测
A3: 项目 / Line item | B3: 单位 | C3: 2022 | D3: 2023 | E3: 2024 | F3: 2025 | G3: 2026 | H3: 2027 | I3: 2028 | J3: 2029 | K3: 2030 | L3: 来源 / 说明
A5: 资产负债表平衡（|资产−负债−权益|<0.01） | B5: TRUE/FALSE | C5: =ABS('Balance Sheet'!C61)<0.01 -> TRUE | D5: =ABS('Balance Sheet'!D61)<0.01 -> TRUE | E5: =ABS('Balance Sheet'!E61)<0.01 -> TRUE | F5: =ABS('Balance Sheet'!F61)<0.01 -> TRUE | G5: =ABS('Balance Sheet'!G61)<0.01 -> TRUE | H5: =ABS('Balance Sheet'!H61)<0.01 -> TRUE | I5: =ABS('Balance Sheet'!I61)<0.01 -> TRUE | J5: =ABS('Balance Sheet'!J61)<0.01 -> TRUE | K5: =ABS('Balance Sheet'!K61)<0.01 -> TRUE
A6: 历史期：模型资产总计 = 报告资产总计 | B6: TRUE/FALSE | C6: =ABS('Balance Sheet'!C27-'Balance Sheet'!C66)<0.01 -> TRUE | D6: =ABS('Balance Sheet'!D27-'Balance Sheet'!D66)<0.01 -> TRUE | E6: =ABS('Balance Sheet'!E27-'Balance Sheet'!E66)<0.01 -> TRUE | F6: =ABS('Balance Sheet'!F27-'Balance Sheet'!F66)<0.01 -> TRUE
A7: 历史期：模型权益合计 = 报告权益合计 | B7: TRUE/FALSE | C7: =ABS('Balance Sheet'!C59-'Balance Sheet'!C70)<0.01 -> TRUE | D7: =ABS('Balance Sheet'!D59-'Balance Sheet'!D70)<0.01 -> TRUE | E7: =ABS('Balance Sheet'!E59-'Balance Sheet'!E70)<0.01 -> TRUE | F7: =ABS('Balance Sheet'!F59-'Balance Sheet'!F70)<0.01 -> TRUE
A8: 现金流量表期末现金 = 资产负债表货币资金（预测期） | B8: TRUE/FALSE | G8: =ABS('Cash Flow'!G50-'Balance Sheet'!G7)<0.01 -> TRUE | H8: =ABS('Cash Flow'!H50-'Balance Sheet'!H7)<0.01 -> TRUE | I8: =ABS('Cash Flow'!I50-'Balance Sheet'!I7)<0.01 -> TRUE | J8: =ABS('Cash Flow'!J50-'Balance Sheet'!J7)<0.01 -> TRUE | K8: =ABS('Cash Flow'!K50-'Balance Sheet'!K7)<0.01 -> TRUE
A9: 现金流：期初+净增加=期末 | B9: TRUE/FALSE | C9: =ABS('Cash Flow'!C49+'Cash Flow'!C48-'Cash Flow'!C50)<0.01 -> TRUE | D9: =ABS('Cash Flow'!D49+'Cash Flow'!D48-'Cash Flow'!D50)<0.01 -> TRUE | E9: =ABS('Cash Flow'!E49+'Cash Flow'!E48-'Cash Flow'!E50)<0.01 -> TRUE | F9: =ABS('Cash Flow'!F49+'Cash Flow'!F48-'Cash Flow'!F50)<0.01 -> TRUE | G9: =ABS('Cash Flow'!G49+'Cash Flow'!G48-'Cash Flow'!G50)<0.01 -> TRUE | H9: =ABS('Cash Flow'!H49+'Cash Flow'!H48-'Cash Flow'!H50)<0.01 -> TRUE | I9: =ABS('Cash Flow'!I49+'Cash Flow'!I48-'Cash Flow'!I50)<0.01 -> TRUE | J9: =ABS('Cash Flow'!J49+'Cash Flow'!J48-'Cash Flow'!J50)<0.01 -> TRUE | K9: =ABS('Cash Flow'!K49+'Cash Flow'!K48-'Cash Flow'!K50)<0.01 -> TRUE
A10: 净利润 = 归母 + 少数股东 | B10: TRUE/FALSE | C10: =ABS('Income Statement'!C65-'Income Statement'!C68-'Income Statement'!C67)<0.01 -> TRUE | D10: =ABS('Income Statement'!D65-'Income Statement'!D68-'Income Statement'!D67)<0.01 -> TRUE | E10: =ABS('Income Statement'!E65-'Income Statement'!E68-'Income Statement'!E67)<0.01 -> TRUE | F10: =ABS('Income Statement'!F65-'Income Statement'!F68-'Income Statement'!F67)<0.01 -> TRUE | G10: =ABS('Income Statement'!G65-'Income Statement'!G68-'Income Statement'!G67)<0.01 -> TRUE | H10: =ABS('Income Statement'!H65-'Income Statement'!H68-'Income Statement'!H67)<0.01 -> TRUE | I10: =ABS('Income Statement'!I65-'Income Statement'!I68-'Income Statement'!I67)<0.01 -> TRUE | J10: =ABS('Income Statement'!J65-'Income Statement'!J68-'Income Statement'!J67)<0.01 -> TRUE | K10: =ABS('Income Statement'!K65-'Income Statement'!K68-'Income Statement'!K67)<0.01 -> TRUE
A11: 现金流量表净利润 = 利润表净利润 | B11: TRUE/FALSE | C11: =ABS('Cash Flow'!C7-'Income Statement'!C65)<0.01 -> TRUE | D11: =ABS('Cash Flow'!D7-'Income Statement'!D65)<0.01 -> TRUE | E11: =ABS('Cash Flow'!E7-'Income Statement'!E65)<0.01 -> TRUE | F11: =ABS('Cash Flow'!F7-'Income Statement'!F65)<0.01 -> TRUE | G11: =ABS('Cash Flow'!G7-'Income Statement'!G65)<0.01 -> TRUE | H11: =ABS('Cash Flow'!H7-'Income Statement'!H65)<0.01 -> TRUE | I11: =ABS('Cash Flow'!I7-'Income Statement'!I65)<0.01 -> TRUE | J11: =ABS('Cash Flow'!J7-'Income Statement'!J65)<0.01 -> TRUE | K11: =ABS('Cash Flow'!K7-'Income Statement'!K65)<0.01 -> TRUE
A12: 收入模型合计 = 利润表收入 | B12: TRUE/FALSE | C12: =ABS('Revenue Model'!C100-'Income Statement'!C7)<0.01 -> TRUE | D12: =ABS('Revenue Model'!D100-'Income Statement'!D7)<0.01 -> TRUE | E12: =ABS('Revenue Model'!E100-'Income Statement'!E7)<0.01 -> TRUE | F12: =ABS('Revenue Model'!F100-'Income Statement'!F7)<0.01 -> TRUE | G12: =ABS('Revenue Model'!G100-'Income Statement'!G7)<0.01 -> TRUE | H12: =ABS('Revenue Model'!H100-'Income Statement'!H7)<0.01 -> TRUE | I12: =ABS('Revenue Model'!I100-'Income Statement'!I7)<0.01 -> TRUE | J12: =ABS('Revenue Model'!J100-'Income Statement'!J7)<0.01 -> TRUE | K12: =ABS('Revenue Model'!K100-'Income Statement'!K7)<0.01 -> TRUE
A13: 分地区合计 = 营业收入 | B13: TRUE/FALSE | C13: =ABS('Revenue Model'!C124-'Income Statement'!C7)<0.5 -> TRUE | D13: =ABS('Revenue Model'!D124-'Income Statement'!D7)<0.5 -> TRUE | E13: =ABS('Revenue Model'!E124-'Income Statement'!E7)<0.5 -> TRUE | F13: =ABS('Revenue Model'!F124-'Income Statement'!F7)<0.5 -> TRUE | G13: =ABS('Revenue Model'!G124-'Income Statement'!G7)<0.01 -> TRUE | H13: =ABS('Revenue Model'!H124-'Income Statement'!H7)<0.01 -> TRUE | I13: =ABS('Revenue Model'!I124-'Income Statement'!I7)<0.01 -> TRUE | J13: =ABS('Revenue Model'!J124-'Income Statement'!J7)<0.01 -> TRUE | K13: =ABS('Revenue Model'!K124-'Income Statement'!K7)<0.01 -> TRUE
A14: 成本分项合计 = 营业成本（2024A 起） | B14: TRUE/FALSE | E14: =ABS(SUM('Income Statement'!E24:E28)-'Income Statement'!E29)<0.05 -> TRUE | F14: =ABS(SUM('Income Statement'!F24:F28)-'Income Statement'!F29)<0.05 -> TRUE
A15: 新能源地区占比合计 = 100% | B15: TRUE/FALSE | G15: =ABS('Revenue Model'!G127-1)<0.001 -> TRUE | H15: =ABS('Revenue Model'!H127-1)<0.001 -> TRUE | I15: =ABS('Revenue Model'!I127-1)<0.001 -> TRUE | J15: =ABS('Revenue Model'!J127-1)<0.001 -> TRUE | K15: =ABS('Revenue Model'!K127-1)<0.001 -> TRUE
A16: 在建及核准待建容量 = 2,563.50 万千瓦 | B16: TRUE/FALSE | G16: =ABS('Revenue Model'!$C$29-2563.5)<0.01 -> TRUE | H16: =ABS('Revenue Model'!$C$29-2563.5)<0.01 -> TRUE | I16: =ABS('Revenue Model'!$C$29-2563.5)<0.01 -> TRUE | J16: =ABS('Revenue Model'!$C$29-2563.5)<0.01 -> TRUE | K16: =ABS('Revenue Model'!$C$29-2563.5)<0.01 -> TRUE
A18: 全部校验通过 ALL CHECKS | C18: =IF(COUNTIF(C5:K16,FALSE)=0,TRUE,FALSE) -> TRUE

Sheet Hist_Data
A1: 原始报表数据（元，按年报原文逐项抄录；由子代理提取并经配平校验）
A3: 合并利润表 | B3: 2022A | C3: 2023A | D3: 2024A | E3: 2025A | F3: 2026H1A | G3: 2025H1A/2025-12-31
A4: 一、营业总收入 | B4: 7.1285601e+10 | C4: 7.495718e+10 | D4: 7.7272059e+10 | E4: 8.2075495e+10 | F4: 3.8397892e+10 | G4: 4.0972997e+10
A5: 其中：营业收入 | B5: 7.1285601e+10 | C5: 7.495718e+10 | D5: 7.7272059e+10 | E5: 8.2075495e+10 | F5: 3.8397892e+10 | G5: 4.0972997e+10
A6: 二、营业总成本 | B6: 5.3867855e+10 | C6: 5.5170217e+10 | D6: 5.7500145e+10 | E6: 6.1890131e+10 | F6: 3.0473498e+10 | G6: 2.8819149e+10
A7: 其中：营业成本 | B7: 3.8756965e+10 | C7: 4.1509673e+10 | D7: 4.4115696e+10 | E7: 4.8161107e+10 | F7: 2.4392926e+10 | G7: 2.2415322e+10
A8: 税金及附加 | B8: 8.7219897e+08 | C8: 1.0316661e+09 | D8: 1.0767414e+09 | E8: 1.2366211e+09 | F8: 6.3786891e+08 | G8: 6.1935567e+08
A9: 销售费用 | B9: 77723590 | C9: 1.1510935e+08 | D9: 62491706 | E9: 99677502 | F9: 38652973 | G9: 40451051
A10: 管理费用 | B10: 4.6185416e+09 | C10: 3.8282356e+09 | D10: 4.0270412e+09 | E10: 4.1186341e+09 | F10: 1.5347234e+09 | G10: 1.798693e+09
A11: 研发费用 | B11: 1.3979152e+09 | C11: 1.383789e+09 | D11: 1.3745778e+09 | E11: 1.4396078e+09 | F11: 3.620268e+08 | G11: 4.4094139e+08
A12: 财务费用 | B12: 8.144511e+09 | C12: 7.3017438e+09 | D12: 6.8435973e+09 | E12: 6.8344836e+09 | F12: 3.5072999e+09 | G12: 3.5043862e+09
A13: 其中：利息费用 | B13: 7.6409893e+09 | C13: 6.9337257e+09 | D13: 6.7099447e+09 | E13: 6.5398222e+09 | F13: 3.3786572e+09 | G13: 3.3095044e+09
A14: 利息收入 | B14: 2.0783818e+08 | C14: 1.8277831e+08 | D14: 1.5554526e+08 | E14: 1.449198e+08 | F14: 63288544 | G14: 85186044
A15: 加：其他收益 | B15: 2.1113832e+09 | C15: 2.7107082e+09 | D15: 2.7526228e+09 | E15: 3.1503853e+09 | F15: 1.2315323e+09 | G15: 1.6639851e+09
A16: 投资收益（损失以“－”号填列） | B16: 2.752364e+08 | C16: 3.8207071e+08 | D16: 4.1072614e+08 | E16: 3.0864305e+08
A17: 其中：对联营企业和合营企业的投资收益 | B17: 2.6904652e+08 | C17: 3.7636824e+08 | D17: 3.3882882e+08 | E17: 2.7708857e+08 | F17: 83846760 | G17: 97115701
A18: 公允价值变动收益（损失以“－”号填列） | B18: 48245.47 | C18: 155869.98
A19: 信用减值损失（损失以“-”号填列） | B19: 87265327 | C19: -83733888 | D19: -65902374 | E19: -23533976 | F19: -40178907 | G19: -47086320
A20: 资产减值损失（损失以“-”号填列） | B20: -2.4754308e+08 | C20: -2.0821848e+08 | D20: -4.9857074e+08 | E20: -4.9585678e+08 | F20: 13987479 | G20: 4980368.6
A21: 资产处置收益（损失以“－”号填列） | B21: 1042201.7 | C21: 57929545 | D21: 11230510 | E21: -2729203.4
A22: 三、营业利润（亏损以“－”号填列） | B22: 1.9645178e+10 | C22: 2.2645875e+10 | D22: 2.238202e+10 | E22: 2.3122273e+10
A23: 加：营业外收入 | B23: 43656631 | C23: 4.5910363e+08 | D23: 2.600014e+08 | E23: 2.7670827e+08 | F23: 86872483 | G23: 56862696
A24: 减：营业外支出 | B24: 1.1905966e+08 | C24: 1.2382113e+08 | D24: 78106216 | E24: 1.0991295e+08 | F24: 10154599 | G24: 40430962
A25: 四、利润总额（亏损总额以“－”号填列） | B25: 1.9569775e+10 | C25: 2.2981158e+10 | D25: 2.2563915e+10 | E25: 2.3289068e+10
A26: 减：所得税费用 | B26: 3.2469156e+09 | C26: 3.5705371e+09 | D26: 6.0108199e+09 | E26: 5.3184904e+09 | F26: 2.1827606e+09 | G26: 2.8218177e+09
A27: 五、净利润（净亏损以“－”号填列） | B27: 1.6322859e+10 | C27: 1.9410621e+10 | D27: 1.6553095e+10 | E27: 17970577667
A28: 1.持续经营净利润（净亏损以“－”号填列） | B28: 1.6322859e+10 | C28: 1.9410621e+10 | D28: 1.6553095e+10 | E28: 17970577667
A29: 1.归属于母公司股东的净利润（净亏损以“-”号填列） | B29: 9.0103466e+09 | C29: 1.0623827e+10 | D29: 8.7773421e+09 | E29: 9.3042115e+09 | F29: 3.6411537e+09 | G29: 5.6663399e+09
A30: 2.少数股东损益（净亏损以“-”号填列） | B30: 7.3125126e+09 | C30: 8.786794e+09 | D30: 7.775753e+09 | E30: 8.6663661e+09 | F30: 3.467754e+09 | G30: 5.4363187e+09
A31: 六、其他综合收益的税后净额 | B31: -9071293.9 | C31: -9954207.7 | D31: -64502918 | E31: 5026645.2 | F31: 1004501.6 | G31: -1609270.1
A32: （一）归属母公司所有者的其他综合收益的税后净额 | B32: -7242148.1 | C32: -7589616 | D32: -43618856 | E32: 5659948.9 | F32: 259132.58 | G32: 94167.42
A33: 1．不能重分类进损益的其他综合收益 | B33: -3661321 | C33: -6167658.3 | D33: -21064549 | E33: -627587.67
A34: （1）重新计量设定受益计划变动额 | B34: -1903442 | C34: -5951670.6 | D34: -20749102 | E34: -437683.52
A35: （2）权益法下不能转损益的其他综合收益 | B35: -1757879.1 | C35: -215987.67 | D35: -315446.61 | E35: -189904.15 | G35: 158845.53
A36: 2．将重分类进损益的其他综合收益 | B36: -3580827 | C36: -1421957.7 | D36: -22554307 | E36: 6287536.5
A37: （1）权益法下可转损益的其他综合收益 | B37: -3370872.6 | C37: -2067798.4 | D37: 804531.51 | E37: 6101689.6 | F37: -1267521.2 | G37: 2616607.8
A38: （6）外币财务报表折算差额 | B38: -209954.43 | C38: 645840.71 | D38: -23358839 | E38: 185846.97 | F38: 1526653.7 | G38: -2681285.9
A39: （二）归属于少数股东的其他综合收益的税后净额 | B39: -1829145.9 | C39: -2364591.7 | D39: -20884062 | E39: -633303.71 | F39: 745369.01 | G39: -1703437.5
A40: 七、综合收益总额 | B40: 1.6313788e+10 | C40: 1.9400667e+10 | D40: 1.6488592e+10 | E40: 1.7975604e+10 | F40: 7.1099123e+09 | G40: 1.1101049e+10
A41: （一）归属于母公司所有者的综合收益总额 | B41: 9.0031045e+09 | C41: 1.0616237e+10 | D41: 8.7337232e+09 | E41: 9.3098715e+09 | F41: 3.6414129e+09 | G41: 5.666434e+09
A42: （二）归属于少数股东的综合收益总额 | B42: 7.3106834e+09 | C42: 8.7844294e+09 | D42: 7.754869e+09 | E42: 8.6657328e+09 | F42: 3.4684994e+09 | G42: 5.4346152e+09
A43: （一）基本每股收益(元/股) | B43: 0.468 | C43: 0.554 | D43: 0.463 | E43: 0.453 | F43: 0.177 | G43: 0.275
A44: （二）稀释每股收益(元/股) | B44: 0.467 | C44: 0.554 | D44: 0.463 | E44: 0.453 | F44: 0.177 | G44: 0.275
A46: 合并资产负债表 | B46: 2022A | C46: 2023A | D46: 2024A | E46: 2025A | F46: 2026H1A | G46: 2025H1A/2025-12-31
A47: 货币资金 | B47: 1.6161672e+10 | C47: 9.7738191e+09 | D47: 1.9738017e+10 | E47: 1.5581643e+10 | F47: 1.8432078e+10 | G47: 1.5581643e+10
A48: 交易性金融资产 | B48: 1907551.7
A49: 应收票据 | B49: 1.5274168e+08 | C49: 48900767 | D49: 34317715 | E49: 51520531 | F49: 30717773 | G49: 51520531
A50: 应收账款 | B50: 1.7210913e+10 | C50: 2.1365205e+10 | D50: 2.4650948e+10 | E50: 2.5373224e+10 | F50: 2.7686691e+10 | G50: 2.5373224e+10
A51: 应收款项融资 | B51: 1000000
A52: 预付款项 | B52: 2.7938991e+09 | C52: 4.8451601e+09 | D52: 2.743421e+09 | E52: 2.6962542e+09 | F52: 2.9290422e+09 | G52: 2.6962542e+09
A53: 其他应收款 | B53: 1.1925764e+09 | C53: 1.789873e+09 | D53: 2.0925286e+09 | E53: 2.1824026e+09 | F53: 2.7821843e+09 | G53: 2.1824026e+09
A54: 应收股利 | B54: 1493072.4 | C54: 1079812.3 | D54: 460215.18 | E54: 230107.59 | F54: 20476443 | G54: 230107.59
A55: 存货 | B55: 2.4809228e+10 | C55: 2.6422613e+10 | D55: 3.0860056e+10 | E55: 3.6321656e+10 | F55: 4.051789e+10 | G55: 3.6321656e+10
A56: 合同资产 | B56: 1.8119181e+08 | C56: 2.5253365e+08 | D56: 1.9919503e+08 | E56: 1.8105998e+08 | F56: 1.6461118e+08 | G56: 1.8105998e+08
A57: 一年内到期的非流动资产 | B57: 54866333 | C57: 57080667 | D57: 55273303 | F57: 58634265
A58: 其他流动资产 | B58: 3.2004215e+09 | C58: 3.6851478e+09 | D58: 3.8079212e+09 | E58: 3.6896684e+09 | F58: 4.2371681e+09 | G58: 3.6896684e+09
A59: 流动资产合计 | B59: 6.5760417e+10 | C59: 6.8240333e+10 | D59: 8.4181678e+10 | E59: 8.6077428e+10 | F59: 9.6839017e+10 | G59: 8.6077428e+10
A60: 债权投资 | B60: 50631185 | C60: 52999528 | D60: 40777760 | E60: 86636774 | F60: 29126972 | G60: 86636774
A61: 长期应收款 | B61: 17219815 | C61: 17941807 | D61: 18793118 | E61: 19240250 | F61: 19240250 | G61: 19240250
A62: 长期股权投资 | B62: 5.6845889e+09 | C62: 7.5799619e+09 | D62: 8.411163e+09 | E62: 1.0385289e+10 | F62: 1.0724612e+10 | G62: 1.0385289e+10
A63: 其他非流动金融资产 | B63: 52651511 | C63: 52651511 | D63: 53924334 | E63: 54924334 | F63: 54924334 | G63: 54924334
A64: 投资性房地产 | B64: 4.2301533e+08 | C64: 4.2205206e+08 | D64: 3.7723299e+08 | E64: 3.6752599e+08 | F64: 3.5560603e+08 | G64: 3.6752599e+08
A65: 固定资产 | B65: 2.6903165e+11 | C65: 2.7692238e+11 | D65: 2.9923683e+11 | E65: 3.520164e+11 | F65: 3.5993779e+11 | G65: 3.520164e+11
A66: 在建工程 | B66: 1.0151365e+11 | C66: 1.5357484e+11 | D66: 2.1576575e+11 | E66: 2.4007903e+11 | F66: 2.5623028e+11 | G66: 2.4007903e+11
A67: 使用权资产 | B67: 3.6654379e+09 | C67: 5.3931421e+09 | D67: 7.5194289e+09 | E67: 6.5056554e+09 | F67: 6.2858378e+09 | G67: 6.5056554e+09
A68: 无形资产 | B68: 2.1341545e+09 | C68: 2.735935e+09 | D68: 6.1618407e+09 | E68: 7.6796987e+09 | F68: 7.5539027e+09 | G68: 7.6796987e+09
A69: 开发支出 | B69: 1.0113197e+09 | C69: 1.0674407e+09 | D69: 1.2552001e+09 | E69: 1.7036461e+09 | F69: 1.7668731e+09 | G69: 1.7036461e+09
... A101: 资本公积 | B101: 2.7400131e+10 | C101: 2.7336443e+10 | D101: 4.0206008e+10 | E101: 4.3444432e+10 | F101: 4.375923e+10 | G101: 4.3444432e+10
A102: 减：库存股 | E102: 3.7484054e+08 | F102: 4.8381666e+08 | G102: 3.7484054e+08
A103: 其他综合收益 | B103: -78395738 | C103: -85985354 | D103: -1.2960421e+08 | E103: -1.2394426e+08 | F103: -1.2368513e+08 | G103: -1.2394426e+08
A104: 专项储备 | B104: 3.2207166e+08 | C104: 404939622 | D104: 4.7054496e+08 | E104: 5.2412027e+08 | F104: 6.6501231e+08 | G104: 5.2412027e+08
A105: 盈余公积 | B105: 4.8940033e+09 | C105: 5.6607519e+09 | D105: 6.4440596e+09 | E105: 7.1664065e+09 | F105: 7.1664065e+09 | G105: 7.1664065e+09
A106: 未分配利润 | B106: 3.133447e+10 | C106: 3.775019e+10 | D106: 4.1658018e+10 | E106: 4.651343e+10 | F106: 4.6872345e+10 | G106: 4.651343e+10
A107: 归属于母公司所有者权益（或股东权益）合计 | B107: 8.8732984e+10 | C107: 9.0949624e+10 | D107: 1.1021703e+11 | E107: 1.1871761e+11 | F107: 1.1942349e+11 | G107: 1.1871761e+11
A108: 少数股东权益 | B108: 5.9228137e+10 | C108: 7.1848379e+10 | D108: 9.9150932e+10 | E108: 1.1350814e+11 | F108: 1.1331271e+11 | G108: 1.1350814e+11
A109: 所有者权益（或股东权益）合计 | B109: 1.4796112e+11 | C109: 1.62798e+11 | D109: 2.0936796e+11 | E109: 2.3222575e+11 | F109: 2.327362e+11 | G109: 2.3222575e+11
A110: 负债和所有者权益（或股东权益）总计 | B110: 4.6485117e+11 | C110: 5.3926725e+11 | D110: 6.5973917e+11 | E110: 7.4926199e+11 | F110: 7.8767081e+11 | G110: 7.4926199e+11
A112: 合并现金流量表 | B112: 2022A | C112: 2023A | D112: 2024A | E112: 2025A | F112: 2026H1A | G112: 2025H1A/2025-12-31
A113: 销售商品、提供劳务收到的现金 | B113: 8.1477166e+10 | C113: 8.2724536e+10 | D113: 8.613035e+10 | E113: 9.2408761e+10 | F113: 4.1593478e+10 | G113: 4.2999256e+10
A114: 收到的税费返还 | B114: 7.0094542e+08 | C114: 5.5831111e+08 | D114: 2.8357034e+08 | E114: 3.3638614e+08 | F114: 86419198 | G114: 1.7558891e+08
A115: 收到其他与经营活动有关的现金 | B115: 3.7069571e+09 | C115: 4.2542447e+09 | D115: 5.1393022e+09 | E115: 6.0587057e+09 | F115: 2.4368537e+09 | G115: 3.2513525e+09
A116: 经营活动现金流入小计 | B116: 8.5885068e+10 | C116: 8.7537092e+10 | D116: 9.1553223e+10 | E116: 9.8803853e+10 | F116: 4.4116751e+10 | G116: 4.6426197e+10
A117: 购买商品、接受劳务支付的现金 | B117: 1.825448e+10 | C117: 2.0905689e+10 | D117: 2.6103035e+10 | E117: 3.2049501e+10 | F117: 1.0354341e+10 | G117: 1.0945031e+10
A118: 支付给职工及为职工支付的现金 | B118: 7.1726256e+09 | C118: 8.0438483e+09 | D118: 8.4540568e+09 | E118: 9.0083952e+09 | F118: 3.9554121e+09 | G118: 3.7499388e+09
A119: 支付的各项税费 | B119: 1.1001759e+10 | C119: 1.3516349e+10 | D119: 1.424776e+10 | E119: 1.8166832e+10 | F119: 9.6586202e+09 | G119: 1.1822949e+10
A120: 支付其他与经营活动有关的现金 | B120: 2.7583867e+09 | C120: 1.9451306e+09 | D120: 2.0278373e+09 | E120: 2.1707279e+09 | F120: 9.7093583e+08 | G120: 1.1846194e+09
A121: 经营活动现金流出小计 | B121: 3.9187251e+10 | C121: 4.4411017e+10 | D121: 5.083269e+10 | E121: 6.1395456e+10 | F121: 2.4939309e+10 | G121: 2.7702539e+10
A122: 经营活动产生的现金流量净额 | B122: 4.6697817e+10 | C122: 4.3126075e+10 | D122: 4.0720533e+10 | E122: 3.7408397e+10 | F122: 1.9177442e+10 | G122: 1.8723658e+10
A123: 收回投资收到的现金 | B123: 56496581 | C123: 35564864 | D123: 19900000 | E123: 4.7964033e+08 | G123: 106893.33
A124: 取得投资收益收到的现金 | B124: 1.7298906e+08 | C124: 1.7198278e+08 | D124: 2.3907131e+08 | E124: 2.4990222e+08 | F124: 63817672 | G124: 42076164
A125: 处置固定资产、无形资产和其他长期资产收回的现金净额 | B125: 23052797 | C125: 1.2608991e+08 | D125: 921075.24 | E125: 65287999 | F125: 5066386.2 | G125: 50625882
A126: 收到其他与投资活动有关的现金 | B126: 4.3063102e+08 | C126: 7.297445e+08 | D126: 6.4143864e+08 | E126: 6.6085517e+08 | F126: 2.4645078e+08 | G126: 3.5759191e+08
A127: 投资活动现金流入小计 | B127: 6.8316946e+08 | C127: 1.0633821e+09 | D127: 9.0133103e+08 | E127: 1.4556857e+09 | F127: 3.1533483e+08 | G127: 4.5040084e+08
A128: 购建固定资产、无形资产和其他长期资产支付的现金 | B128: 5.0509691e+10 | C128: 6.7100346e+10 | D128: 9.0708324e+10 | E128: 9.3683638e+10 | F128: 3.4603305e+10 | G128: 4.2998052e+10
A129: 投资支付的现金 | B129: 760988500 | C129: 1682098266 | D129: 1.0705756e+09 | E129: 1704755449 | F129: 2.8517662e+08 | G129: 585810961
A130: 取得子公司及其他营业单位支付的现金净额 | B130: 2.3571262e+09 | C130: 3.5524845e+09 | D130: 2.0938072e+09 | E130: 1.5061815e+08 | F130: 10867888 | G130: 1.008083e+08
A131: 支付其他与投资活动有关的现金 | B131: 63844726 | C131: 4.3998697e+08 | D131: 1.9732747e+09 | E131: 5.951772e+08 | F131: 56012242 | G131: 4.7554513e+08
A132: 投资活动现金流出小计 | B132: 5.369165e+10 | C132: 7.2774916e+10 | D132: 9.5845982e+10 | E132: 9.6134189e+10 | F132: 3.4955362e+10 | G132: 4.4160216e+10
A133: 投资活动产生的现金流量净额 | B133: -5.3008481e+10 | C133: -7.1711534e+10 | D133: -9.4944651e+10 | E133: -9.4678503e+10 | F133: -3.4640027e+10 | G133: -4.3709816e+10
A134: 吸收投资收到的现金 | B134: 1.1176313e+10 | C134: 1.2035876e+10 | D134: 4.0934008e+10 | E134: 1.9524447e+10 | F134: 4.8634215e+09 | G134: 6.0116822e+09
...
